Workbook
Name Aux_fatork: 'CEE CED'!#REF!
Name Aux_fatork: 'CEE CED'!#REF!
Name Aux_FC: 'CEE CED'!#REF!
Name Aux_FC: 'CEE CED'!#REF!
Name CheckBoxIlum: "Check Box 68"
Name Lista_Atividade: Apoio!$AH$4:$AH$6
Name Lista_Confiabilidade: Apoio!#REF!
Name Lista_Confiabilidade: Apoio!#REF!
Name Lista_Empresa: Apoio!$AK$4:$AK$7
Name Lista_Localizacao: Apoio!$C$4:$C$400
Name Lista_Precisao: Apoio!#REF!
Name Lista_Precisao: Apoio!#REF!
Name Lista_SAS: Apoio!$AS$4:$AS$6
Name Lista_Solar: Apoio!$BS$4:$BS$29
Name Lista_SubgrupoTarifa: 'CEE CED'!$C$5:$C$15
Name Lista_Tarifa: Apoio!$AQ$4:$AQ$8
Name Lista_Tipologia: Apoio!$G$4:$G$9
Name Selecione_a_tipologia: Projeto!$J$10

Sheet Ajuda
C3: ÍNDICE | AD3: Voltar ao topo
D4: 1. | E4: Orientações gerais sobre a planilha
D5: 2. | E5: Guia do preenchimento das UCs (Unidades Consumidoras)
D6: 3. | E6: Guia do Cálculo dos custos do projeto
D7: 4. | E7: Guia do Cálculo dos benefícios do projeto
D8: 5. | E8: Ações de medição e verificação do projeto
D9: 6. | E9: Cronograma físico e financeiro
D10: 7. | E10: Projeção de economia de energia
D11: 8. | E11: Simulação das parcelas do contrato de desempenho
D12: 9. | E12: Disposições gerais
C16: ORIENTAÇÕES GERAIS SOBRE A PLANILHA | AD16: Voltar ao topo
D17: 1. | E17: Esta planilha deverá ser utilizada em conjunto com o Roteiro do Diagnóstico Energético, o Regulamento/Especificação Técnica
E18: da CPP e as Tabelas Auxiliares CEMIG.
D19: 2. | E19: A planilha realiza cálculos para uma única subclasse tarifária (nível de tensão de atendimento).
D20: 3. | E20: As seguintes avaliações devem ser realizadas nos projetos de eficiência energética, dependendo do estágio do projeto.
D21: 4. | E21: Avaliação ex ante: | J21: 4.1. | K21: Avaliação realizada através de valores estimados, na fase de definição do projeto.
J22: 4.2. | K22: Custos e benefícios são avaliados através de levantamentos, dados de catálogos e estimativas.
J23: 4.3. | K23: É a avaliação inicial do projeto, realizada antes do início do projeto.
J24: 4.4. | K24: Avaliação realizada para avaliar a viabilidade dos investimentos a serem realizados.
J25: 4.5. | K25: A avaliação ex ante apresentada nesta planilha é baseada no disposto no PROPEE.
D26: 5. | E26: Avaliação ex post: | J26: 5.1. | K26: Avaliação realizada através de valores consolidados, na fase de fechamento do projeto.
J27: 5.2. | K27: Custos e benefícios são avaliados em função dos custos despendidos e medições realizadas.
J28: 5.3. | K28: É a avaliação final do projeto, realizada após seu encerramento.
J29: 5.4. | K29: Avaliação realizada para apurar a viabilidade dos investimentos realizados.
J30: 5.5. | K30: A avaliação ex post será feita através da planilha disponibilizada pela Agência Nacional de Energia
K31: Elétrica - ANEEL e planilhas disponibilizadas pela Cemig.
D32: 6. | E32: A planilha realiza somente a avaliação ex ante do projeto.
D33: 7. | E33: A planilha realiza a avaliação dos custos do projeto nas duas situações descritas pelo Propee:
E34: 7.1. | F34: Ponto de vista do PEE: avaliam-se somente os custos despendidos pelo PEE.
E35: 7.2. | F35: Ponto de vista do projeto: avaliam-se todos os custos despendidos no projeto, independente da origem do recurso.
D36: 8. | E36: A planilha realiza a avaliação dos benefícios do projeto em uma situação descrita pelo PROPEE:
E37: 8.1 | F37: Ótica do sistema elétrico: valorando os benefícios em comparação pelo custo marginal de expansão do sistema.
E38: 8.2 | F38: Ótica do do consumidor: valorando os benefícios pelo custo efetivamente pago pelo consumidor (Fonte Incentivada).
D39: 9. | E39: A planilha apresenta uma estimativa das parcelas do contrato de desempenho, não refletindo necessariamente a
E40: situação final, uma vez que podem haver diferenças entre as metas previstas e realizadas de custos e benefícios, bem
E41: como pode haver a variação da taxa de referência utilizada na simulação (IPCA).
D42: 10. | E42: A planilha realiza uma projeção da economia de energia a ser obtida com a realização do projeto de eficiência energética.
E43: A utilização desta planilha é obrigatória. O principal objetivo desta projeção é proporcionar uma ferramenta para a verificação
E44: da coerência dos dados utilizados nos cálculos.
D45: 11. | E45: O preenchimento de toda planilha deve ser feito apenas nas células em branco. Todas as outras células de cor azul
E46: estão protegidas e serão automaticamente preenchidas conforme o acréscimo de dados na planilha.
D47: 12. | E47: Para que não haja alteração das fórmulas na planilha, as células protegidas serão verificadas se possuem a mesma senha de
E48: bloqueio de quando foram enviadas.
C52: GUIA DO PREENCHIMENTO DAS UCs (UNIDADES CONSUMIDORAS) | AD52: Voltar ao topo
D53: 1. | E53: Inserir os dados da identificação de cada unidade consumidora contemplada no projeto.
D54: 2. | E54: Inserir, logo abaixo da identificação da unidade consumidora, os seus respectivos dados da Fatura de Energia Elétrica.
E55: 2.1. | F55: Para unidades consumidoras de baixa tensão, preencher o histórico de consumo pela coluna "Consumo Fora Ponta".
C59: GUIA DO CÁLCULO DOS CUSTOS DO PROJETO | AD59: Voltar ao topo
D60: 1. | E60: Os equipamentos deverão ser agrupados de acordo com suas características nominais e perfis de funcionamento. Desta
E61: forma, os materiais ficarão agrupados de acordo com as respectivas características técnicas e vidas úteis.
D62: 2. | E62: Recomenda-se que os custos do projeto fiquem diretamente referenciados ao benefício proporcionado pela substituição,
E63: ou seja, o item 1 do custo da iluminação referenciado ao item 1 do benefício da iluminação (ilumin 1), o item 2 do custo
E64: referenciado ao item 2 do benefício e assim por diante. Este procedimento torna mais claro o entendimento do projeto.
D65: 3. | E65: A planilha calcula o valor global de cada custo do projeto, sendo que a origem dos recursos é inserida posteriormente.
D66: 4. | E66: Os custos do projeto devem ser lançados da seguinte forma:
E67: 4.1. | F67: Custos dos usos finais: todos os custos relacionados diretamente com um uso final deverá ser lançado na planilha do
F68: uso final correspondente (materiais e equipamentos, mão de obra para instalação, descarte e eventuais outros custos).
E69: 4.2. | F69: Custos de marketing, treinamento, diagnóstico, gerenciamento do projeto e relatório final: como estes custos não são
F70: referentes a uma ação específica e sim ao projeto como um todo, estes custos são lançados em separado para que sejam
F71: rateados entre os usos finais do projeto.
E72: 4.3. | F72: Custos com medição e verificação: deverão ser lançados na planilha os custos somente com o plano de M&V e medições
F73: para a Linha de Base e os custos com o Relatório de M&V e medições para o período de Determinação da Economia.
F74: A quantidade de amostras será definida no Diagnóstico, no qual deverá ser apresentado o cálculo do número de amostras
F75: a serem medidas bem como a justificativa pra o CV utilizado.
D76: 5. | E76: Deverão ser inseridos os valores globais de cada item de custo em cada campo de inserção de custos, ou seja, o custo total
E77: relacionado ao material ou serviço, independente da origem do recurso que irá custeá-lo.
D78: 6. | E78: Os valores de outras origem de recursos deverão ser inseridos nos campos específicos "terceiros" e "consumidor",
E79: dispostos nas colunas de "ORIGEM DOS RECURSOS". O custo das outras origens inseridos serão substraídos do custo total e
E80: o restante irá compor o custo aportado com recursos do PEE. Sobre a origem dos recursos, entende-se:
E81: 6.1. | F81: PEE: recursos financeiros aportados pelo Programa de Eficiência Energética, ou seja, pela concessionária.
E82: 6.2. | F82: Terceiros: recursos financeiros aportados por entidades parceiras (instuições financeiras, etc).
E83: 6.3. | F83: Consumidor: recursos financeiros aportados pelo consumidor beneficiado pela ação de eficiência energética.
D84: 7. | E84: Havendo a inserção de custos de outras origens, a planilha calculará na aba "RCB" a relação custo-benefício do projeto
E85: sobre o ponto de vista do projeto. Esta analise é ilustrativa e tem como objetivo demonstrar que, com a inserção de
E86: recursos de outras origens, foi possível uma otimização dos recursos do Programa de Eficiência Energética.
D87: 8. | E87: Todos os materiais que forem substituídos deverão ser descartados.
C91: GUIA DO CÁLCULO DOS BENEFÍCIOS DO PROJETO | AD91: Voltar ao topo
D92: 1. | E92: Os dados a serem preenchidos em cada guia de benefícios variam de acordo com o uso final da energia.
D93: 2. | E93: As guias destinadas aos usos finais de energia que serão substituídos possuem duas tabelas que devem ser preenchidas:
F94: 2.1. | G94: Sistema atual
F95: 2.2. | G95: Sistema proposto
D96: 3. | E96: As guias destinadas à implantação de fontes incentivadas de energia deverão ser preenchidas com os dados pedidos
E97: da nova instalação.
D98: 4. | E98: Os equipamentos deverão ser agrupados de acordo com suas características nominais, perfis de funcionamento e Unidade
E99: Consumidora.
D100: 5. | E100: Os tempos de utilização informados na planilha devem estar dentro das premissas abaixo (valor igual ou menor):
E101: 5.1. | F101: Tempo de utilização do sistema: | N101: 24 horas por dia
N102: 365 dias por ano
N103: 8.760 horas por ano
E104: 5.2. | F104: Fator de coincidência na ponta: | N104: 3 horas por dia
N105: 22 dias úteis por mês
N106: 12 meses por ano
N107: 792 horas na ponta por ano
E108: 5.3. | F108: O horário de ponta da CEMIG é das 17h00 às 20h00.
C112: AÇÕES DE MEDIÇÃO E VERIFICAÇÃO DO PROJETO | AD112: Voltar ao topo
D113: 1. | E113: Devem ser atendidos os níveis de precisão e de confiança determinados pelo PROPEE:
E114: 1.1. | F114: Nível de precisão: ± 10%
E115: 1.2. | F115: Nível de confiança : 95%
D116: 2. | E116: Preenchimento da Guia M&V:
J117: 2.1 | K117: Plano de M&V: Lançar os custos referente à elaboração do plano de M&V para o período de
...

Sheet Fluxo
G2: *** As células possuem links para as respectivas guias do arquivo.
S17: Legenda:
U19: Planilha RCB (preenchimento obrigatório)
U21: Planilha "Tabelas Auxiliares CEMIG" (preenchimento obrigatório)

Sheet CEE CED
B2: CEE E CED
B3: Valores de CEE e CED para utilização em projetos de eficiência energética
B4: Subclasse tarifária | D4: CEE | E4: CED | F4: FC | G4: k
B5: 1 | C5: Selecione a subclasse tarifária | D5: 0 | E5: 0 | F5: 0 | G5: 0
B6: 2 | C6: A1 - Acima de 230 kV | F6: 0.7 | G6: 0.15
B7: 3 | C7: A2 - De 88 kV a 230 kV | D7: 429.6 | E7: 341.73 | F7: 0.7 | G7: 0.15
B8: 4 | C8: A3 - 69 kV | D8: 452.36 | E8: 526.86 | F8: 0.7 | G8: 0.15
B9: 5 | C9: A3a - De 30 kV a 44 kV | D9: 506.48 | E9: 1009.76 | F9: 0.7 | G9: 0.15
B10: 6 | C10: A4 - De 2,3 kV a 25 kV | D10: 506.48 | E10: 1009.76 | F10: 0.7 | G10: 0.15
B11: 7 | C11: AS - Subterrâneo | D11: 574.31 | E11: 1472.68 | F11: 0.7 | G11: 0.15
B12: 8 | C12: B1 - Baixa tensão (residencial) | D12: 320.97 | E12: 2062.63 | F12: 0.7 | G12: 0.15
B13: 9 | C13: B2 - Baixa tensão (rural) | D13: 320.97 | E13: 2180.34 | F13: 0.7 | G13: 0.15
B14: 12 | C14: B3 - Baixa tensão (demais classes) | D14: 320.97 | E14: 2121.48 | F14: 0.7 | G14: 0.15
B15: 13 | C15: B4 - Iluminação Pública | D15: 320.97 | E15: 2121.48 | F15: 0.7 | G15: 0.15
B17: =SUMIF(Lista_SubgrupoTarifa,C17,B5:B14) -> 1 | C17: =Projeto!J24 -> Selecione a subclasse tarifária | D17: =IF(C17="A1 - Acima de 230 kV","Não Permitido",SUMIF($C$5:$C$15,$C$17,$D$5:$D$15)) -> 0 | E17: =IF(C17="A1 - Acima de 230 kV","Não Permitido",SUMIF($C$5:$C$15,$C$17,$E$5:$E$15)) -> 0 | F17: =SUMIF($C$5:$C$15,$C$17,$F$5:$F$15) -> 0 | G17: =SUMIF($C$5:$C$15,$C$17,$G$5:$G$15) -> 0
D19: Número | E19: Data
C20: Resolução Homologatória ANEEL | D20: 3589 | E20: 46168

Sheet Avaliação
C3: CRITÉRIOS PARA AVALIAÇÃO DA CHAMADA PÚBLICA
C4: Nesta planilha estão dispostos os critérios para pontuação dos projetos apresentados na chamada pública. Os demais
C5: critérios são dependentes da documentação apresentada pelo proponente, dos demais projetos apresentados ou da
C6: avaliação da comissão julgadora.
C10: ITEM | D10: CRITÉRIO | F10: VALOR
C11: A | D11: Relação custo-benefício
D12: RCB | E12: Relação custo-benefício do projeto | F12: =RCB!H9 -> 0
C14: B | D14: Peso do investimento em equipamentos no custo total
D15: K | E15: Custo do equipamento comparticipado pelo PEE | F15: =CustoContábil!F6 -> 0
D16: CT | E16: Custo total do investimento considerando os custos aportados pelo PEE | F16: =CustoContábil!F18 -> 0
C18: C | D18: Impacto direto na economia de energia e na redução de demanda
D19: EP | E19: Energia economizada pelo projeto (MWh/ano) | F19: =RCB!C18 -> 1.296
D20: DP | E20: Demanda evitada pelo projeto (kW) | F20: =RCB!D18 -> 0
C22: D | D22: Qualidade na apresentação do projeto
D23: n/a | E23: Prova documental / comissão julgadora
C25: E | D25: Capacidade de superar barreiras de mercado e efeito multiplicador
D26: n/a | E26: Prova documental / comissão julgadora
C28: F | D28: Experiência em projetos semelhantes
D29: n/a | E29: Prova documental / comissão julgadora
C31: G | D31: Contrapartida
D32: INVPEE | E32: Investimento aportado pelo PEE | F32: =CustoContábil!F18 -> 0
D33: INVtotal | E33: Investimento total do projeto | F33: =CustoContábil!D18 -> 0
C35: H | D35: Incentico à usos finais
D36: UF1 | E36: Investimento do PEE considerado para o uso final 1 (iluminação) | F36: =IlumCusto!K165 -> 0
D37: UF2 | E37: Investimento do PEE considerado para o uso final 2 (condicionamento ambiental) | F37: =CondAmbCusto!K115 -> 0
D38: UF3 | E38: Investimento do PEE considerado para o uso final 3 (sistemas motrizes) | F38: =MotorCusto!K115 -> 0
D39: UF4 | E39: Investimento do PEE considerado para o uso final 4 (sistemas de refrigeração) | F39: =RefrigCusto!K115 -> 0
D40: UF6 | E40: Investimento do PEE considerado para o uso final 6 (equipamentos hospitalares) | F40: =HospCusto!K115 -> 0
D41: UF7 | E41: Investimento do PEE considerado para o uso final 7 (usina fotovoltaica) | F41: =UFVCusto!K115 -> 0
D42: UF8 | E42: Investimento do PEE considerado para o uso final 8 (outros) | F42: =OutrosCusto!K115 -> 0
C44: I | D44: Ações educacionais, divulgação e gestão
D45: INVaed | E45: Investimento aplicado em treinamentos | F45: =CustoContábil!D14 -> 0
D46: INVge | E46: Investimento aplicado em gestão energética | F46: 0
D47: INVtotal | E47: Investimento total do projeto | F47: =CustoContábil!D18 -> 0

Sheet Apoio
B2: INFORMAÇÕES SOBRE O PROJETO - Planilha_RCB_CPP2026_REV01 | AA2: INFORMAÇÕES SOBRE AS FATURAS DE ENERGIA ELÉTRICA DAS UCs | AG2: INFORMAÇÕES SOBRE A UNIDADE CONSUMIDORA | AU2: ESTIMATIVA DE CUSTOS DA CONCESSIONÁRIA APLICADOS NO PROJETO | BJ2: CONTRATO DE DESEMPENHO | BS2: AQUECIMENTO SOLAR DE ÁGUA
B3: Localização | D3: Distância | F3: Tipologia | I3: Tipo desta Planilha RCB | L3: Usos finais previstos - Ex ante | O3: Chamada pública | R3: RCB limite | U3: RCB limite CP | X3: Mensagem avaliação RCB | AA3: Ambiente de contratação de energia | AD3: Número de fases do padrão de entrada | AG3: Forma de contratação | AJ3: Atividade | AM3: Retorno do investimento | AP3: Tarifa | AU3: Divisão de valores | AX3: Mão de obra própria CEMIG | BA3: Transporte CEMIG | BD3: Administração própria CEMIG | BG3: Auditoria Contábil e Financeira CEMIG | BJ3: Taxas | BM3: Divisão da vida útil ex ante | BQ3: Vida útil (anos) | BS3: Cidade | BT3: Fator de correção
B4: 1 | C4: Selecione o município | D4: 0 | F4: 1 | G4: Selecione a tipologia | I4: 1 | J4: Selecione o tipo desta Planilha RCB | L4: Iluminação | M4: =IF(AND(RCB!E9=0,RCB!F9=0),"não",IF(OR(RCB!E9>0,RCB!F9>0),"sim","erro")) -> não | O4: Marcar para chamada pública | P4: X | R4: 1 | S4: 0.8 | U4: 1 | V4: 0.75 | X4: 1 | Y4: Avaliação preliminar do projeto conforme critérios ANEEL | AA4: 1 | AB4: Selecione o tipo de contratação | AD4: 1 | AE4: Selecione a quantidade de fases | AG4: 1 | AH4: Selecione a forma de Contratação | AJ4: 1 | AK4: Selecione o tipo de empresa | AM4: Não selecionado | AN4: 0 | AP4: 1 | AQ4: Selecione a modalidade tarifária | AS4: Não selecionado | AU4: Iluminação | AV4: =IF(CustoContábil!$F$6=0,0,IlumCusto!K108/CustoContábil!$F$6) -> 0 | AX4: Iluminação | AY4: =IF($AV$13=0,0,$AY$13*AV4) -> 0 | BA4: Iluminação | BB4: =IF($AV$13=0,0,$BB$13*AV4) -> 0 | BD4: Iluminação | BE4: =IF($AV$13=0,0,$BE$13*AV4) -> 0 | BG4: Iluminação | BH4: =IF($AV$13=0,0,$BH$15*AV4) -> 0 | BJ4: IPCA mensal de referência | BK4: 0.0016 | BM4: Iluminação | BN4: =RCB!C9 -> 0 | BO4: MWh/ano | BQ4: =IF(COUNT(IlumCusto!V8:V107)=0,0,AVERAGE(IlumCusto!V8:V107)) -> 0 | BS4: Aracaju - SE | BT4: 0.84
B5: 2 | C5: ABADIA DOS DOURADOS | D5: 547 | F5: 2 | G5: Industrial | I5: 2 | J5: Geral Viáveis | L5: Condicionamento ambiental | M5: =IF(AND(RCB!E10=0,RCB!F10=0),"não",IF(OR(RCB!E10>0,RCB!F10>0),"sim","erro")) -> não | R5: 2 | S5: 0.9 | U5: 2 | V5: 0.85 | AA5: 2 | AB5: Cliente Cativo | AD5: 2 | AE5: Monofásico (1 fase) | AG5: 2 | AH5: Contrato de Desempenho | AJ5: 2 | AK5: Micro ou pequena empresa | AM5: Micro ou pequena empresa | AN5: 0.8 | AP5: 2 | AQ5: Tarifa convencional | AS5: Convencional | AU5: Condicionamento ambiental | AV5: =IF(CustoContábil!$F$6=0,0,CondAmbCusto!K58/CustoContábil!F6) -> 0 | AX5: Condicionamento ambiental | AY5: =IF($AV$13=0,0,$AY$13*AV5) -> 0 | BA5: Condicionamento ambiental | BB5: =IF($AV$13=0,0,$BB$13*AV5) -> 0 | BD5: Condicionamento ambiental | BE5: =IF($AV$13=0,0,$BE$13*AV5) -> 0 | BG5: Condicionamento ambiental | BH5: =IF($AV$13=0,0,$BH$15*AV5) -> 0 | BJ5: Mês referência IPCA | BK5: 46174 | BM5: Condicionamento ambiental | BN5: =RCB!C10 -> 0 | BO5: MWh/ano | BQ5: =IF(COUNT(CondAmbCusto!V8:V57)=0,0,AVERAGE(CondAmbCusto!V8:V57)) -> 0 | BS5: Belém - PA | BT5: 0.65
B6: 3 | C6: ABAETÉ | D6: 213 | F6: 3 | G6: Comércio e serviços | I6: 3 | J6: Geral Inviáveis | L6: Sistemas motrizes | M6: =IF(AND(RCB!E11=0,RCB!F11=0),"não",IF(OR(RCB!E11>0,RCB!F11>0),"sim","erro")) -> não | O6: =IF(P4="","Projeto fora da chamada pública","Projeto de chamada pública") -> Projeto de chamada pública | R6: 3 | S6: 0.8 | U6: 3 | V6: 0.75 | X6: 2 | Y6: Avaliação preliminar do projeto conforme chamada pública | AA6: 3 | AB6: Cliente Livre | AD6: 3 | AE6: Bifásico (2 fases) | AG6: 3 | AH6: Fundo Perdido | AJ6: 3 | AK6: Demais empresas | AM6: Demais empresas | AN6: 1 | AP6: 3 | AQ6: Tarifa verde | AS6: Central de água quente | AU6: Motores | AV6: =IF(CustoContábil!$F$6=0,0,MotorCusto!K58/CustoContábil!F6) -> 0 | AX6: Motores | AY6: =IF($AV$13=0,0,$AY$13*AV6) -> 0 | BA6: Motores | BB6: =IF($AV$13=0,0,$BB$13*AV6) -> 0 | BD6: Motores | BE6: =IF($AV$13=0,0,$BE$13*AV6) -> 0 | BG6: Motores | BH6: =IF($AV$13=0,0,$BH$15*AV6) -> 0 | BJ6: Multa atraso | BK6: 0.02 | BM6: Motores | BN6: =RCB!C11 -> 0 | BO6: MWh/ano | BQ6: =IF(COUNT(MotorCusto!V8:V57)=0,0,AVERAGE(MotorCusto!V8:V57)) -> 0 | BS6: Belo Horizonte - MG | BT6: 0.68
B7: 4 | C7: ABRE CAMPO | D7: 216 | F7: 4 | G7: Poder Público | L7: Sistemas de refrigeração | M7: =IF(AND(RCB!E12=0,RCB!F12=0),"não",IF(OR(RCB!E12>0,RCB!F12>0),"sim","erro")) -> não | AD7: 4 | AE7: Trifásico (3 fases) | AJ7: 4 | AK7: Não se aplica (fundo perdido) | AM7: Não se aplica | AN7: 1 | AP7: 4 | AQ7: Tarifa azul | AU7: Sistemas de refrigeração | AV7: =IF(CustoContábil!$F$6=0,0,RefrigCusto!K58/CustoContábil!F6) -> 0 | AX7: Sistemas de refrigeração | AY7: =IF($AV$13=0,0,$AY$13*AV7) -> 0 | BA7: Sistemas de refrigeração | BB7: =IF($AV$13=0,0,$BB$13*AV7) -> 0 | BD7: Sistemas de refrigeração | BE7: =IF($AV$13=0,0,$BE$13*AV7) -> 0 | BG7: Sistemas de refrigeração | BH7: =IF($AV$13=0,0,$BH$15*AV7) -> 0 | BM7: Sistemas de refrigeração | BN7: =RCB!C12 -> 0 | BO7: MWh/ano | BQ7: =IF(COUNT(RefrigCusto!V8:V57)=0,0,AVERAGE(RefrigCusto!V8:V57)) -> 0 | BS7: Brasília - DF | BT7: 0.7
B8: 5 | C8: ACAIACA | D8: 158 | F8: 5 | G8: Rural | L8: Equipamentos hospitalares | M8: =IF(AND(RCB!E13=0,RCB!F13=0),"não",IF(OR(RCB!E13>0,RCB!F13>0),"sim","erro")) -> não | R8: =$AG$8 -> 1 | S8: =IF(AND(($AV$9+$AV$10+$AV$12>0),(SUM($AV$4:$AV$8,$AV$11)=0)),0.9,IF($P$4="",SUMIF($R$4:$R$6,$R$8,$S$4:$S$6),SUMIF($U$4:$U$6,$R$8,$V$4:$V$6))) -> 0.75 | AG8: =SUMIF(Lista_Atividade,AH8,AG4:AG6) -> 1 | AH8: =Projeto!J21 -> Selecione a forma de Contratação | AP8: 5 | AQ8: Tarifa branca | AS8: Selecione o Tipo do Sistema | AU8: Equipamentos hospitalares | AV8: =IF(CustoContábil!$F$6=0,0,HospCusto!K58/CustoContábil!F6) -> 0 | AX8: Equipamentos hospitalares | AY8: =IF($AV$13=0,0,$AY$13*AV8) -> 0 | BA8: Equipamentos hospitalares | BB8: =IF($AV$13=0,0,$BB$13*AV8) -> 0 | BD8: Equipamentos hospitalares | BE8: =IF($AV$13=0,0,$BE$13*AV8) -> 0 | BG8: Equipamentos hospitalares | BH8: =IF($AV$13=0,0,$BH$15*AV8) -> 0 | BM8: Equipamentos hospitalares | BN8: =RCB!C13 -> 0 | BO8: MWh/ano | BQ8: =IF(COUNT(HospCusto!V8:V57)=0,0,AVERAGE(HospCusto!V8:V57)) -> 0 | BS8: Campo Grande - MS | BT8: 0.73
B9: 6 | C9: AÇUCENA | D9: 280 | F9: 6 | G9: Residencial (Condomínios) | L9: Fotovoltaico | M9: =IF(AND(RCB!E14=0,RCB!F14=0),"não",IF(OR(RCB!E14>0,RCB!F14>0),"sim","erro")) -> não | X9: =IF(P4="",X4,X6) -> 2 | Y9: =IF(P4="",Y4,Y6) -> Avaliação preliminar do projeto conforme chamada pública | AJ9: =SUMIF(Lista_Empresa,AK9,AJ4:AJ7) -> 1 | AK9: =Projeto!J22 -> Selecione o tipo de empresa | AM9: Retorno do investimento | AN9: =IF(AJ9=2,AN5,IF(AJ9=3,AN6,IF(AJ9=4,AN7,AN4))) -> 0 | AU9: Usina Fotovoltaica | AV9: =IF(CustoContábil!$F$6=0,0,UFVCusto!K58/CustoContábil!F6) -> 0 | AX9: Usina Fotovoltaica | AY9: =IF($AV$13=0,0,$AY$13*AV9) -> 0 | BA9: Usina Fotovoltaica | BB9: =IF($AV$13=0,0,$BB$13*AV9) -> 0 | BD9: Usina Fotovoltaica | BE9: =IF($AV$13=0,0,$BE$13*AV9) -> 0 | BG9: Usina Fotovoltaica | BH9: =IF($AV$13=0,0,$BH$15*AV9) -> 0 | BM9: Usina Fotovoltaica | BN9: =RCB!C14 -> 1.296 | BO9: MWh/ano | BQ9: =IF(COUNT(UFVCusto!V8:V57)=0,0,AVERAGE(UFVCusto!V8:V57)) -> 0 | BS9: Cuiabá - MT | BT9: 0.74
B10: 7 | C10: ÁGUA BOA | D10: 379 | F10: 7 | G10: Serviço público | L10: Outras Fontes Incentivadas | M10: =IF(AND(RCB!E15=0,RCB!F15=0),"não",IF(OR(RCB!E15>0,RCB!F15>0),"sim","erro")) -> não | AP10: =SUMIF(Lista_Tarifa,AQ10,AP4:AP8) -> 1 | AQ10: =Projeto!J23 -> Selecione a modalidade tarifária | AU10: Outras Fontes Incentivadas | AV10: =IF(CustoContábil!$F$6=0,0,OutrasFICusto!K58/CustoContábil!F6) -> 0 | AX10: Outras Fontes Incentivadas | AY10: =IF($AV$13=0,0,$AY$13*AV10) -> 0 | BA10: Outras Fontes Incentivadas | BB10: =IF($AV$13=0,0,$BB$13*AV10) -> 0 | BD10: Outras Fontes Incentivadas | BE10: =IF($AV$13=0,0,$BE$13*AV10) -> 0 | BG10: Outras Fontes Incentivadas | BH10: =IF($AV$13=0,0,$BH$15*AV10) -> 0 | BM10: Outras Fontes Incentivadas | BN10: =RCB!C15 -> 0 | BO10: MWh/ano | BQ10: =IF(COUNT(OutrasFICusto!V8:V57)=0,0,AVERAGE(OutrasFICusto!V8:V57)) -> 0 | BS10: Curitiba - PR | BT10: 0.49
B11: 8 | C11: ÁGUA COMPRIDA | D11: 513 | F11: 8 | G11: Iluminação Pública | L11: Outros | M11: =IF(AND(RCB!E16=0,RCB!F16=0),"não",IF(OR(RCB!E16>0,RCB!F16>0),"sim","erro")) -> não | AU11: Outros | AV11: =IF(CustoContábil!$F$6=0,0,OutrosCusto!K58/CustoContábil!F6) -> 0 | AX11: Outros | AY11: =IF($AV$13=0,0,$AY$13*AV11) -> 0 | BA11: Outros | BB11: =IF($AV$13=0,0,$BB$13*AV11) -> 0 | BD11: Outros | BE11: =IF($AV$13=0,0,$BE$13*AV11) -> 0 | BG11: Outros | BH11: =IF($AV$13=0,0,$BH$15*AV11) -> 0 | BM11: Outros | BN11: =RCB!C16 -> 0 | BO11: MWh/ano | BQ11: =IF(COUNT(OutrosCusto!V8:V57)=0,0,AVERAGE(OutrosCusto!V8:V57)) -> 0 | BS11: Florianópolis - SC | BT11: 0.55
B12: 9 | C12: AGUANIL | D12: 239 | L12: SAE | M12: =IF(AND(RCB!E17=0,RCB!F17=0),"não",IF(OR(RCB!E17>0,RCB!F17>0),"sim","erro")) -> não | AU12: SAE | AV12: =IF(CustoContábil!$F$6=0,0,SAECusto!K58/CustoContábil!F6) -> 0 | AX12: SAE | AY12: =IF($AV$13=0,0,$AY$13*AV12) -> 0 | BA12: SAE | BB12: =IF($AV$13=0,0,$BB$13*AV12) -> 0 | BD12: SAE | BE12: =IF($AV$13=0,0,$BE$13*AV12) -> 0 | BG12: SAE | BH12: =IF($AV$13=0,0,$BH$15*AV12) -> 0 | BM12: SAE | BN12: =RCB!C17 -> 0 | BO12: MWh/ano | BQ12: =IF(COUNT(SAECusto!V8:V57)=0,0,AVERAGE(SAECusto!V8:V57)) -> 0 | BS12: Fortaleza - CE | BT12: 0.82
B13: 10 | C13: ÁGUAS FORMOSAS | D13: 610 | AU13: TOTAL | AV13: =SUM(AV4:AV12) -> 0 | AX13: TOTAL | AY13: =(AY16*AY17)+(AY20*AY21) -> 29535.52 | BA13: TOTAL | BB13: =BB17*(96+(BB18*BB15)) -> 0 | BD13: TOTAL | BE13: =BE16*SUM(BE17,BE18, BE20, BE21, BE22) - BE19 -> 0 | BG13: TOTAL | BH13: =SUM(BH4:BH12) -> 0 | BM13: TOTAL | BN13: =SUM(BN4:BN12) -> 1.296 | BO13: MWh/ano | BQ13: =IF(BN13=0,0,(BQ5*(BN5/BN13))+(BQ6*(BN6/BN13))+(BQ7*(BN7/BN13))+(BQ8*(BN8/BN13))+(BQ9*(BN9/BN13))+(BQ10*(BN10/BN13))+(BQ12*(BN12/BN13))+(BQ11*(BN11/BN13))+BQ4*(BN4/BN13)) -> 0 | BS13: Goiânia - GO | BT13: 0.78
B14: 11 | C14: ÁGUAS VERMELHAS | D14: 756 | BS14: João Pessoa - PB | BT14: 0.76
B15: 12 | C15: AIMORÉS | D15: 489 | AX15: Parcela fixa | BA15: Distância entre a cidade e BH | BB15: =IF(BB16="Selecione o município",0, LOOKUP(BB16,C6:C779,D6:D779)) -> 31 | BD15: Parcela variável | BG15: Custo Fixo | BH15: 1500 | BS15: Macapá - AP | BT15: 0.7
B16: 13 | C16: AIURUOCA | D16: 370 | AX16: Horas utilizadas | AY16: 154 | BA16: Cidade | BB16: =Projeto!J21 -> Selecione a forma de Contratação | BD16: Porcentagem | BE16: =1/19 -> 0.052631579 | BS16: Maceió - AL | BT16: 0.8
B17: 14 | C17: ALAGOA | D17: 400 | AX17: Custo homem-hora | AY17: 191.78909 | BA17: Tempo do Projeto (meses) | BB17: 0 | BD17: Materiais e Equipamentos | BE17: =CustoContábil!F6 -> 0 | BS17: Manaus - AM | BT17: 0.55
B18: 15 | C18: ALBERTINA | D18: 475 | BA18: Custo do km (CEMIG) | BB18: 0 | BD18: Mão de obra de terceiros | BE18: =CustoContábil!F8 -> 0 | BS18: Natal - RN | BT18: 0.81
B19: 16 | C19: ALFENAS | D19: 378 | AX19: Parcela variável | BD19: Marketing | BE19: =CustoContábil!F13 -> 0 | BS19: Porto Alegre - RS | BT19: 0.57
B20: 17 | C20: ALFREDO VASCONCELOS | D20: 161 | AX20: Porcentagem | AY20: 0.05 | BD20: Treinamento e capacitação | BE20: =CustoContábil!F14 -> 0 | BS20: Porto Nacional - TO | BT20: 0.74
B21: 18 | C21: ALMENARA | D21: 730 | AX21: Equip + MOT + MKT + Trein + | AY21: =SUM(BE17:BE22) -> 0 | BD21: Descarte de materiais | BE21: =CustoContábil!F15 -> 0 | BS21: Porto Velho - RO | BT21: 0.6
B22: 19 | C22: ALPERCATA | D22: 330 | AX22: Desc + M&V | BD22: Medição e verificação | BE22: =CustoContábil!F16 -> 0 | BS22: Recife - PE | BT22: 0.77
B23: 20 | C23: ALPINÓPOLIS | D23: 332 | BS23: Ribeirão Preto - SP | BT23: 0.69
B24: 21 | C24: ALTEROSA | D24: 394 | BS24: Rio de Janeiro - RJ | BT24: 0.6
B25: 22 | C25: ALTO CAPARAÓ | D25: 322 | BS25: Salvador - BA | BT25: 0.7
B26: 23 | C26: ALTO RIO DOCE | D26: 224 | BS26: São Luís - MA | BT26: 0.73
B27: 24 | C27: ALVARENGA | D27: 464 | BS27: São Paulo - SP | BT27: 0.5
B28: 25 | C28: ALVINÓPOLIS | D28: 163 | BS28: Teresina - PI | BT28: 0.86
B29: 26 | C29: ALVORADA DE MINAS | D29: 342 | BS29: Vitória - ES | BT29: 0.65
B30: 27 | C30: AMPARO DO SERRA | D30: 203 | BS30: Condições:
B31: 28 | C31: ANDRADAS | D31: 498 | BS31: Temperatura de armazenamento = 40°C
B32: 29 | C32: ANDRELÂNDIA | D32: 280 | BS32: Volume armazenado = Volume consumido
B33: 30 | C33: ANGELÂNDIA | D33: 449
B34: 31 | C34: ANTÔNIO CARLOS | D34: 190
B35: 32 | C35: ANTÔNIO DIAS | D35: 172
B36: 33 | C36: ARAÇAÍ | D36: 122
B37: 34 | C37: ARACITABA | D37: 225
B38: 35 | C38: ARAÇUAÍ | D38: 678
B39: 36 | C39: ARAGUARI | D39: 569
B40: 37 | C40: ARANTINA | D40: 304
B41: 38 | C41: ARAPORÃ | D41: 670
B42: 39 | C42: ARAPUÁ | D42: 339
B43: 40 | C43: ARAÚJOS | D43: 160
B44: 41 | C44: ARAXÁ | D44: 367
... B61: 58 | C61: BELMIRO BRAGA | D61: 290
B62: 59 | C62: BELO HORIZONTE
B63: 60 | C63: BELO ORIENTE | D63: 253
B64: 61 | C64: BELO VALE | D64: 82
B65: 62 | C65: BERILO | D65: 545
B66: 63 | C66: BERIZAL | D66: 749
B67: 64 | C67: BERTÓPOLIS | D67: 654
B68: 65 | C68: BETIM | D68: 30
B69: 66 | C69: BIAS FORTES | D69: 238
B70: 67 | C70: BICAS | D70: 290
B71: 68 | C71: BIQUINHAS | D71: 268
B72: 69 | C72: BOA ESPERANÇA | D72: 310
B73: 70 | C73: BOCAINA DE MINAS | D73: 360
B74: 71 | C74: BOCAIÚVA | D74: 369
... B378: 375 | C378: JEQUITAÍ | D378: 504
B379: 376 | C379: JEQUITIBÁ | D379: 11 5
B380: 377 | C380: JEQUITINHONHA | D380: 667
B381: 378 | C381: JESUÂNIA | D381: 379
B382: 379 | C382: JOAÍMA | D382: 692
B383: 380 | C383: JOANÉSIA | D383: 260
B384: 381 | C384: JOÃO MONLEVADE | D384: 116
B385: 382 | C385: JOÃO PINHEIRO | D385: 380
B386: 383 | C386: JOAQUIM FELÍCIO | D386: 289
B387: 384 | C387: JORDÂNIA | D387: 804
B388: 385 | C388: JOSÉ GONÇALVES DE MINAS | D388: 529
B389: 386 | C389: JOSÉ RAYDAN | D389: 342
B390: 387 | C390: JOSENÓPOLIS | D390: 649
B391: 388 | C391: JUATUBA | D391: 55
... B660: 657 | C660: SÃO GONÇALO DO ABAETÉ | D660: 405
B661: 658 | C661: SÃO GONÇALO DO PARÁ | D661: 11 8
B662: 659 | C662: SÃO GONÇALO DO RIO ABAIXO | D662: 89
B663: 660 | C663: SÃO GONÇALO DO RIO PRETO | D663: 345
B664: 661 | C664: SÃO GONÇALO DO SAPUCAÍ | D664: 348
B665: 662 | C665: SÃO GOTARDO | D665: 261
B666: 663 | C666: SÃO JOÃO BATISTA DO GLÓRIA | D666: 350
B667: 664 | C667: SÃO JOÃO DA LAGOA | D667: 479
B668: 665 | C668: SÃO JOÃO DA MATA | D668: 412
B669: 666 | C669: SÃO JOÃO DA PONTE | D669: 551
B670: 667 | C670: SÃO JOÃO DAS MISSÕES | D670: 687
B671: 668 | C671: SÃO JOÃO DEL REI | D671: 185
B672: 669 | C672: SÃO JOÃO DO MANTENINHA | D672: 430
B673: 670 | C673: SÃO JOÃO DO ORIENTE | D673: 273
... B778: 775 | C778: WENCESLAU BRAZ | D778: 471

Sheet Projeto
R5: PROGRAMA DE EFICIÊNCIA ENERGÉTICA - CHAMADA PÚBLICA DE PROJETOS
C7: IDENTIFICAÇÃO DO PROJETO
D8: Concessionária | J8: Cemig Distribuição S.A. | AA8: CNPJ | AB8: 6981180000116
D9: Nome do projeto
D10: Tipologia do projeto | J10: Selecione a tipologia | AC10: Taxa de desconto (i) | AD10: 0.08
D11: Tipo desta Planilha RCB | J11: Selecione o tipo desta Planilha RCB
C13: IDENTIFICAÇÃO DO CONSUMIDOR BENEFICIADO (UC Principal)
D14: Nome
D15: Endereço
D16: CNPJ
D17: Nº da Unidade Consumidora
D18: Responsável
D19: Telefone | Q19: e-mail
D20: Município
D21: Forma de Contratação | J21: Selecione a forma de Contratação
D22: Porte de empresa | J22: Selecione o tipo de empresa
D23: Modalidade tarifária | J23: Selecione a modalidade tarifária
D24: Subclasse tarifária | J24: Selecione a subclasse tarifária
C26: IDENTIFICAÇÃO DA EMPRESA RESPONSÁVEL PELO PROJETO
D27: Nome da empresa
D28: Endereço
D29: CNPJ
D30: Responsável técnico
D31: Telefone | P31: e-mail
C35: AVALIAÇÃO EX ANTE - RESUMO DAS AÇÕES PREVISTAS NO PROJETO
C37: Usos Finais contemplados: | J37: =_xlfn.TEXTJOIN( "; ", TRUE, IF(RCB!G9>0,IF(Projeto!J24="B4 - Iluminação Pública","Iluminação pública","Iluminação"),""), IF(RCB!G10>0,"Condicionamento ambiental",""), IF(RCB!G11>0,"Sistemas motrizes ("&MotorBenef!E2&")",""), IF(RCB!G12>0,"Sistemas de refrigeração ("&RefrigBenef!E2&")",""), IF(RCB!G13>0,"Equipamentos hospitalares ("&HospBenef!E2&")",""), IF(RCB!G14>0,IF(RCB!G17>0,"Usina Fotovoltaica + SAE","Usina Fotovoltaica"),""), IF(RCB!G15>0,"Outras Fontes incentivadas ("&OutrasFIBenef!E2&")",""), IF(RCB!G16>0,"Outros ("&OutrosBenef!E2&")","") ) | AJ37: =IF(AND(RCB!G17>0,RCB!G14<=0), "ERRO: SAE exige Usina Fotovoltaica", "")
C42: VALORES DE CEE E CED - EX ANTE
K43: CEE = | L43: ='CEE CED'!$D$17 -> 0 | Q43: R$/MWh | Z43: Fator de carga | AA43: ='CEE CED'!F17 -> 0
K44: CED = | L44: ='CEE CED'!$E$17 -> 0 | Q44: R$/kW ano | Z44: Constante k | AA44: ='CEE CED'!G17 -> 0
K46: Resolução homologatória ANEEL | L46: ='CEE CED'!D20 -> 3589 | Z46: Resolução publicada em | AA46: ='CEE CED'!E20 -> 46168
C48: CUSTO TOTAL DO PEE | L48: =CustoContábil!F18 -> 0 | T48: Valor total do projeto | AB48: =CustoContábil!D18 -> 0
C49: ENERGIA ECONOMIZADA | L49: =RCB!C18 -> 1.296 | Q49: MWh/ano | T49: Custo da energia economizada | AB49: =IF(RCB!C18=0,0,CustoContábil!F18/RCB!C18) -> 0 | AF49: R$/MWh
C50: REDUÇÃO DE DEMANDA NA PONTA | L50: =RCB!D18 -> 0 | Q50: kW | T50: Custo da demanda evitada | AB50: =IF(RCB!D18=0,0,CustoContábil!F18/RCB!D18) -> 0 | AF50: R$/kW
F52: RCBLIMITE = | L52: =Apoio!$S$8 -> 0.75 | U52: RCBEX ANTE = | AA52: =RCB!$H$9 -> 0
B55: =IF(CustoContábil!H21>CustoContábil!G21,"EXTRAPOLADO ALGUM LIMITE DE RECURSO POR RUBRICA, VER GUIA CustoContábil",IF(CustoContábil!H22>CustoContábil!G22,"EXTRAPOLADO ALGUM LIMITE DE RECURSO POR RUBRICA, VER GUIA CustoContábil",IF(CustoContábil!H23>CustoContábil!G23,"EXTRAPOLADO ALGUM LIMITE DE RECURSO POR RUBRICA, VER GUIA CustoContábil",IF(CustoContábil!H24>CustoContábil!G24,"EXTRAPOLADO ALGUM LIMITE DE RECURSO POR RUBRICA, VER GUIA CustoContábil",""))))

Sheet UCs
N2: 1 | O2: - Unidade consumidora: | U2: 2 | V2: - Unidade consumidora: | AB2: 3 | AC2: - Unidade consumidora: | AI2: 4 | AJ2: - Unidade consumidora: | AP2: 5 | AQ2: - Unidade consumidora: | AW2: 6 | AX2: - Unidade consumidora: | BD2: 7 | BE2: - Unidade consumidora: | BK2: 8 | BL2: - Unidade consumidora: | BR2: 9 | BS2: - Unidade consumidora: | BY2: 10 | BZ2: - Unidade consumidora: | CF2: 11 | CG2: - Unidade consumidora: | CM2: 12 | CN2: - Unidade consumidora: | CT2: 13 | CU2: - Unidade consumidora: | DA2: 14 | DB2: - Unidade consumidora: | DH2: 15 | DI2: - Unidade consumidora: | DO2: 16 | DP2: - Unidade consumidora: | DV2: 17 | DW2: - Unidade consumidora: | EC2: 18 | ED2: - Unidade consumidora: | EJ2: 19 | EK2: - Unidade consumidora: | EQ2: 20 | ER2: - Unidade consumidora:
N3: Identificação | U3: Identificação | AB3: Identificação | AI3: Identificação | AP3: Identificação | AW3: Identificação | BD3: Identificação | BK3: Identificação | BR3: Identificação | BY3: Identificação | CF3: Identificação | CM3: Identificação | CT3: Identificação | DA3: Identificação | DH3: Identificação | DO3: Identificação | DV3: Identificação | EC3: Identificação | EJ3: Identificação | EQ3: Identificação
N4: Nome ou razão social | U4: Nome ou razão social | AB4: Nome ou razão social | AI4: Nome ou razão social | AP4: Nome ou razão social | AW4: Nome ou razão social | BD4: Nome ou razão social | BK4: Nome ou razão social | BR4: Nome ou razão social | BY4: Nome ou razão social | CF4: Nome ou razão social | CM4: Nome ou razão social | CT4: Nome ou razão social | DA4: Nome ou razão social | DH4: Nome ou razão social | DO4: Nome ou razão social | DV4: Nome ou razão social | EC4: Nome ou razão social | EJ4: Nome ou razão social | EQ4: Nome ou razão social
N5: CNPJ | U5: CNPJ | AB5: CNPJ | AI5: CNPJ | AP5: CNPJ | AW5: CNPJ | BD5: CNPJ | BK5: CNPJ | BR5: CNPJ | BY5: CNPJ | CF5: CNPJ | CM5: CNPJ | CT5: CNPJ | DA5: CNPJ | DH5: CNPJ | DO5: CNPJ | DV5: CNPJ | EC5: CNPJ | EJ5: CNPJ | EQ5: CNPJ
N6: Endereço | U6: Endereço | AB6: Endereço | AI6: Endereço | AP6: Endereço | AW6: Endereço | BD6: Endereço | BK6: Endereço | BR6: Endereço | BY6: Endereço | CF6: Endereço | CM6: Endereço | CT6: Endereço | DA6: Endereço | DH6: Endereço | DO6: Endereço | DV6: Endereço | EC6: Endereço | EJ6: Endereço | EQ6: Endereço
N7: Cidade | U7: Cidade | AB7: Cidade | AI7: Cidade | AP7: Cidade | AW7: Cidade | BD7: Cidade | BK7: Cidade | BR7: Cidade | BY7: Cidade | CF7: Cidade | CM7: Cidade | CT7: Cidade | DA7: Cidade | DH7: Cidade | DO7: Cidade | DV7: Cidade | EC7: Cidade | EJ7: Cidade | EQ7: Cidade
N8: Estado | Q8: Minas Gerais | U8: Estado | X8: Minas Gerais | AB8: Estado | AE8: Minas Gerais | AI8: Estado | AL8: Minas Gerais | AP8: Estado | AS8: Minas Gerais | AW8: Estado | AZ8: Minas Gerais | BD8: Estado | BG8: Minas Gerais | BK8: Estado | BN8: Minas Gerais | BR8: Estado | BU8: Minas Gerais | BY8: Estado | CB8: Minas Gerais | CF8: Estado | CI8: Minas Gerais | CM8: Estado | CP8: Minas Gerais | CT8: Estado | CW8: Minas Gerais | DA8: Estado | DD8: Minas Gerais | DH8: Estado | DK8: Minas Gerais | DO8: Estado | DR8: Minas Gerais | DV8: Estado | DY8: Minas Gerais | EC8: Estado | EF8: Minas Gerais | EJ8: Estado | EM8: Minas Gerais | EQ8: Estado | ET8: Minas Gerais
N9: CEP | U9: CEP | AB9: CEP | AI9: CEP | AP9: CEP | AW9: CEP | BD9: CEP | BK9: CEP | BR9: CEP | BY9: CEP | CF9: CEP | CM9: CEP | CT9: CEP | DA9: CEP | DH9: CEP | DO9: CEP | DV9: CEP | EC9: CEP | EJ9: CEP | EQ9: CEP
N10: Horário de Funcionamento | P10: Início: | R10: Fim: | U10: Horário de Funcionamento | W10: Início: | Y10: Fim: | AB10: Horário de Funcionamento | AD10: Início: | AF10: Fim: | AI10: Horário de Funcionamento | AK10: Início: | AM10: Fim: | AP10: Horário de Funcionamento | AR10: Início: | AT10: Fim: | AW10: Horário de Funcionamento | AY10: Início: | BA10: Fim: | BD10: Horário de Funcionamento | BF10: Início: | BH10: Fim: | BK10: Horário de Funcionamento | BM10: Início: | BO10: Fim: | BR10: Horário de Funcionamento | BT10: Início: | BV10: Fim: | BY10: Horário de Funcionamento | CA10: Início: | CC10: Fim: | CF10: Horário de Funcionamento | CH10: Início: | CJ10: Fim: | CM10: Horário de Funcionamento | CO10: Início: | CQ10: Fim: | CT10: Horário de Funcionamento | CV10: Início: | CX10: Fim: | DA10: Horário de Funcionamento | DC10: Início: | DE10: Fim: | DH10: Horário de Funcionamento | DJ10: Início: | DL10: Fim: | DO10: Horário de Funcionamento | DQ10: Início: | DS10: Fim: | DV10: Horário de Funcionamento | DX10: Início: | DZ10: Fim: | EC10: Horário de Funcionamento | EE10: Início: | EG10: Fim: | EJ10: Horário de Funcionamento | EL10: Início: | EN10: Fim: | EQ10: Horário de Funcionamento | ES10: Início: | EU10: Fim:
N11: Dias de Funcionamento | U11: Dias de Funcionamento | AB11: Dias de Funcionamento | AI11: Dias de Funcionamento | AP11: Dias de Funcionamento | AW11: Dias de Funcionamento | BD11: Dias de Funcionamento | BK11: Dias de Funcionamento | BR11: Dias de Funcionamento | BY11: Dias de Funcionamento | CF11: Dias de Funcionamento | CM11: Dias de Funcionamento | CT11: Dias de Funcionamento | DA11: Dias de Funcionamento | DH11: Dias de Funcionamento | DO11: Dias de Funcionamento | DV11: Dias de Funcionamento | EC11: Dias de Funcionamento | EJ11: Dias de Funcionamento | EQ11: Dias de Funcionamento
N12: Nome do responsável | U12: Nome do responsável | AB12: Nome do responsável | AI12: Nome do responsável | AP12: Nome do responsável | AW12: Nome do responsável | BD12: Nome do responsável | BK12: Nome do responsável | BR12: Nome do responsável | BY12: Nome do responsável | CF12: Nome do responsável | CM12: Nome do responsável | CT12: Nome do responsável | DA12: Nome do responsável | DH12: Nome do responsável | DO12: Nome do responsável | DV12: Nome do responsável | EC12: Nome do responsável | EJ12: Nome do responsável | EQ12: Nome do responsável
N13: Telefone de contato | U13: Telefone de contato | AB13: Telefone de contato | AI13: Telefone de contato | AP13: Telefone de contato | AW13: Telefone de contato | BD13: Telefone de contato | BK13: Telefone de contato | BR13: Telefone de contato | BY13: Telefone de contato | CF13: Telefone de contato | CM13: Telefone de contato | CT13: Telefone de contato | DA13: Telefone de contato | DH13: Telefone de contato | DO13: Telefone de contato | DV13: Telefone de contato | EC13: Telefone de contato | EJ13: Telefone de contato | EQ13: Telefone de contato
N14: E-mail | U14: E-mail | AB14: E-mail | AI14: E-mail | AP14: E-mail | AW14: E-mail | BD14: E-mail | BK14: E-mail | BR14: E-mail | BY14: E-mail | CF14: E-mail | CM14: E-mail | CT14: E-mail | DA14: E-mail | DH14: E-mail | DO14: E-mail | DV14: E-mail | EC14: E-mail | EJ14: E-mail | EQ14: E-mail
N15: Número de fases do padrão de entrada | Q15: Selecione a quantidade de fases | U15: Número de fases do padrão de entrada | X15: Selecione a quantidade de fases | AB15: Número de fases do padrão de entrada | AE15: Selecione a quantidade de fases | AI15: Número de fases do padrão de entrada | AL15: Selecione a quantidade de fases | AP15: Número de fases do padrão de entrada | AS15: Selecione a quantidade de fases | AW15: Número de fases do padrão de entrada | AZ15: Selecione a quantidade de fases | BD15: Número de fases do padrão de entrada | BG15: Selecione a quantidade de fases | BK15: Número de fases do padrão de entrada | BN15: Selecione a quantidade de fases | BR15: Número de fases do padrão de entrada | BU15: Selecione a quantidade de fases | BY15: Número de fases do padrão de entrada | CB15: Selecione a quantidade de fases | CF15: Número de fases do padrão de entrada | CI15: Selecione a quantidade de fases | CM15: Número de fases do padrão de entrada | CP15: Selecione a quantidade de fases | CT15: Número de fases do padrão de entrada | CW15: Selecione a quantidade de fases | DA15: Número de fases do padrão de entrada | DD15: Selecione a quantidade de fases | DH15: Número de fases do padrão de entrada | DK15: Selecione a quantidade de fases | DO15: Número de fases do padrão de entrada | DR15: Selecione a quantidade de fases | DV15: Número de fases do padrão de entrada | DY15: Selecione a quantidade de fases | EC15: Número de fases do padrão de entrada | EF15: Selecione a quantidade de fases | EJ15: Número de fases do padrão de entrada | EM15: Selecione a quantidade de fases | EQ15: Número de fases do padrão de entrada | ET15: Selecione a quantidade de fases
N16: Subclasse tarifária | Q16: Selecione a subclasse tarifária | U16: Subclasse tarifária | X16: Selecione a subclasse tarifária | AB16: Subclasse tarifária | AE16: Selecione a subclasse tarifária | AI16: Subclasse tarifária | AL16: Selecione a subclasse tarifária | AP16: Subclasse tarifária | AS16: Selecione a subclasse tarifária | AW16: Subclasse tarifária | AZ16: Selecione a subclasse tarifária | BD16: Subclasse tarifária | BG16: Selecione a subclasse tarifária | BK16: Subclasse tarifária | BN16: Selecione a subclasse tarifária | BR16: Subclasse tarifária | BU16: Selecione a subclasse tarifária | BY16: Subclasse tarifária | CB16: Selecione a subclasse tarifária | CF16: Subclasse tarifária | CI16: Selecione a subclasse tarifária | CM16: Subclasse tarifária | CP16: Selecione a subclasse tarifária | CT16: Subclasse tarifária | CW16: Selecione a subclasse tarifária | DA16: Subclasse tarifária | DD16: Selecione a subclasse tarifária | DH16: Subclasse tarifária | DK16: Selecione a subclasse tarifária | DO16: Subclasse tarifária | DR16: Selecione a subclasse tarifária | DV16: Subclasse tarifária | DY16: Selecione a subclasse tarifária | EC16: Subclasse tarifária | EF16: Selecione a subclasse tarifária | EJ16: Subclasse tarifária | EM16: Selecione a subclasse tarifária | EQ16: Subclasse tarifária | ET16: Selecione a subclasse tarifária
N17: Modalidade Tarifária | Q17: Selecione a modalidade tarifária | U17: Modalidade Tarifária | X17: Selecione a modalidade tarifária | AB17: Modalidade Tarifária | AE17: Selecione a modalidade tarifária | AI17: Modalidade Tarifária | AL17: Selecione a modalidade tarifária | AP17: Modalidade Tarifária | AS17: Selecione a modalidade tarifária | AW17: Modalidade Tarifária | AZ17: Selecione a modalidade tarifária | BD17: Modalidade Tarifária | BG17: Selecione a modalidade tarifária | BK17: Modalidade Tarifária | BN17: Selecione a modalidade tarifária | BR17: Modalidade Tarifária | BU17: Selecione a modalidade tarifária | BY17: Modalidade Tarifária | CB17: Selecione a modalidade tarifária | CF17: Modalidade Tarifária | CI17: Selecione a modalidade tarifária | CM17: Modalidade Tarifária | CP17: Selecione a modalidade tarifária | CT17: Modalidade Tarifária | CW17: Selecione a modalidade tarifária | DA17: Modalidade Tarifária | DD17: Selecione a modalidade tarifária | DH17: Modalidade Tarifária | DK17: Selecione a modalidade tarifária | DO17: Modalidade Tarifária | DR17: Selecione a modalidade tarifária | DV17: Modalidade Tarifária | DY17: Selecione a modalidade tarifária | EC17: Modalidade Tarifária | EF17: Selecione a modalidade tarifária | EJ17: Modalidade Tarifária | EM17: Selecione a modalidade tarifária | EQ17: Modalidade Tarifária | ET17: Selecione a modalidade tarifária
N18: Ambiente de contratação de energia | Q18: Selecione o tipo de contratação | U18: Ambiente de contratação de energia | X18: Selecione o tipo de contratação | AB18: Ambiente de contratação de energia | AE18: Selecione o tipo de contratação | AI18: Ambiente de contratação de energia | AL18: Selecione o tipo de contratação | AP18: Ambiente de contratação de energia | AS18: Selecione o tipo de contratação | AW18: Ambiente de contratação de energia | AZ18: Selecione o tipo de contratação | BD18: Ambiente de contratação de energia | BG18: Selecione o tipo de contratação | BK18: Ambiente de contratação de energia | BN18: Selecione o tipo de contratação | BR18: Ambiente de contratação de energia | BU18: Selecione o tipo de contratação | BY18: Ambiente de contratação de energia | CB18: Selecione o tipo de contratação | CF18: Ambiente de contratação de energia | CI18: Selecione o tipo de contratação | CM18: Ambiente de contratação de energia | CP18: Selecione o tipo de contratação | CT18: Ambiente de contratação de energia | CW18: Selecione o tipo de contratação | DA18: Ambiente de contratação de energia | DD18: Selecione o tipo de contratação | DH18: Ambiente de contratação de energia | DK18: Selecione o tipo de contratação | DO18: Ambiente de contratação de energia | DR18: Selecione o tipo de contratação | DV18: Ambiente de contratação de energia | DY18: Selecione o tipo de contratação | EC18: Ambiente de contratação de energia | EF18: Selecione o tipo de contratação | EJ18: Ambiente de contratação de energia | EM18: Selecione o tipo de contratação | EQ18: Ambiente de contratação de energia | ET18: Selecione o tipo de contratação
N19: Possui sistema fotovoltaico? Se sim, inserir potência total instalada (kW) | U19: Possui sistema fotovoltaico? Se sim, inserir potência total instalada (kW) | AB19: Possui sistema fotovoltaico? Se sim, inserir potência total instalada (kW) | AI19: Possui sistema fotovoltaico? Se sim, inserir potência total instalada (kW) | AP19: Possui sistema fotovoltaico? Se sim, inserir potência total instalada (kW) | AW19: Possui sistema fotovoltaico? Se sim, inserir potência total instalada (kW) | BD19: Possui sistema fotovoltaico? Se sim, inserir potência total instalada (kW) | BK19: Possui sistema fotovoltaico? Se sim, inserir potência total instalada (kW) | BR19: Possui sistema fotovoltaico? Se sim, inserir potência total instalada (kW) | BY19: Possui sistema fotovoltaico? Se sim, inserir potência total instalada (kW) | CF19: Possui sistema fotovoltaico? Se sim, inserir potência total instalada (kW) | CM19: Possui sistema fotovoltaico? Se sim, inserir potência total instalada (kW) | CT19: Possui sistema fotovoltaico? Se sim, inserir potência total instalada (kW) | DA19: Possui sistema fotovoltaico? Se sim, inserir potência total instalada (kW) | DH19: Possui sistema fotovoltaico? Se sim, inserir potência total instalada (kW) | DO19: Possui sistema fotovoltaico? Se sim, inserir potência total instalada (kW) | DV19: Possui sistema fotovoltaico? Se sim, inserir potência total instalada (kW) | EC19: Possui sistema fotovoltaico? Se sim, inserir potência total instalada (kW) | EJ19: Possui sistema fotovoltaico? Se sim, inserir potência total instalada (kW) | EQ19: Possui sistema fotovoltaico? Se sim, inserir potência total instalada (kW)
N20: Ramo de Atividade | U20: Ramo de Atividade | AB20: Ramo de Atividade | AI20: Ramo de Atividade | AP20: Ramo de Atividade | AW20: Ramo de Atividade | BD20: Ramo de Atividade | BK20: Ramo de Atividade | BR20: Ramo de Atividade | BY20: Ramo de Atividade | CF20: Ramo de Atividade | CM20: Ramo de Atividade | CT20: Ramo de Atividade | DA20: Ramo de Atividade | DH20: Ramo de Atividade | DO20: Ramo de Atividade | DV20: Ramo de Atividade | EC20: Ramo de Atividade | EJ20: Ramo de Atividade | EQ20: Ramo de Atividade
B22: LISTA DAS UNIDADES CONSUMIDORAS DO PROJETO | F22: CONSUMO GLOBAL | N22: 1 - CONSUMO DA UC: | Q22: =R2 -> 0 | U22: 2 - CONSUMO DA UC: | X22: =Y2 -> 0 | AB22: 3 - CONSUMO DA UC: | AE22: =AF2 -> 0 | AI22: 4 - CONSUMO DA UC: | AL22: =AM2 -> 0 | AP22: 5 - CONSUMO DA UC: | AS22: =AT2 -> 0 | AW22: 6 - CONSUMO DA UC: | AZ22: =BA2 -> 0 | BD22: 7 - CONSUMO DA UC: | BG22: =BH2 -> 0 | BK22: 8 - CONSUMO DA UC: | BN22: =BO2 -> 0 | BR22: 9 - CONSUMO DA UC: | BU22: =BV2 -> 0 | BY22: 10 - CONSUMO DA UC: | CB22: =CC2 -> 0 | CF22: 11 - CONSUMO DA UC: | CI22: =CJ2 -> 0 | CM22: 12 - CONSUMO DA UC: | CP22: =CQ2 -> 0 | CT22: 13 - CONSUMO DA UC: | CW22: =CX2 -> 0 | DA22: 14 - CONSUMO DA UC: | DD22: =DE2 -> 0 | DH22: 15 - CONSUMO DA UC: | DK22: =DL2 -> 0 | DO22: 16 - CONSUMO DA UC: | DR22: =DS2 -> 0 | DV22: 17 - CONSUMO DA UC: | DY22: =DZ2 -> 0 | EC22: 18 - CONSUMO DA UC: | EF22: =EG2 -> 0 | EJ22: 19 - CONSUMO DA UC: | EM22: =EN2 -> 0 | EQ22: 20 - CONSUMO DA UC: | ET22: =EU2 -> 0
B23: Nº | C23: Nº da Unidade Consumidora | D23: Identificação | F23: Mês/Ano | G23: Demanda Ponta (kW) | H23: Demanda Fora Ponta (kW) | I23: Consumo Ponta (kWh/mês) | J23: Consumo Fora Ponta (kWh/mês) | K23: Consumo Total (kWh/mês) | M23: Mês | N23: Mês/Ano | O23: Demanda Ponta (kW) | P23: Demanda Fora Ponta (kW) | Q23: Consumo Ponta (kWh/mês) | R23: Consumo Fora Ponta (kWh/mês) | S23: Consumo Total (kWh/mês) | U23: Mês/Ano | V23: Demanda Ponta (kW) | W23: Demanda Fora Ponta (kW) | X23: Consumo Ponta (kWh/mês) | Y23: Consumo Fora Ponta (kWh/mês) | Z23: Consumo Total (kWh/mês) | AB23: Mês/Ano | AC23: Demanda Ponta (kW) | AD23: Demanda Fora Ponta (kW) | AE23: Consumo Ponta (kWh/mês) | AF23: Consumo Fora Ponta (kWh/mês) | AG23: Consumo Total (kWh/mês) | AI23: Mês/Ano | AJ23: Demanda Ponta (kW) | AK23: Demanda Fora Ponta (kW) | AL23: Consumo Ponta (kWh/mês) | AM23: Consumo Fora Ponta (kWh/mês) | AN23: Consumo Total (kWh/mês) | AP23: Mês/Ano | AQ23: Demanda Ponta (kW) | AR23: Demanda Fora Ponta (kW) | AS23: Consumo Ponta (kWh/mês) | AT23: Consumo Fora Ponta (kWh/mês) | AU23: Consumo Total (kWh/mês) | AW23: Mês/Ano | AX23: Demanda Ponta (kW) | AY23: Demanda Fora Ponta (kW) | AZ23: Consumo Ponta (kWh/mês) | BA23: Consumo Fora Ponta (kWh/mês) | BB23: Consumo Total (kWh/mês) | BD23: Mês/Ano | BE23: Demanda Ponta (kW) | BF23: Demanda Fora Ponta (kW) | BG23: Consumo Ponta (kWh/mês) | BH23: Consumo Fora Ponta (kWh/mês) | BI23: Consumo Total (kWh/mês) | BK23: Mês/Ano | BL23: Demanda Ponta (kW) | BM23: Demanda Fora Ponta (kW) | BN23: Consumo Ponta (kWh/mês) | BO23: Consumo Fora Ponta (kWh/mês) | BP23: Consumo Total (kWh/mês) | BR23: Mês/Ano | BS23: Demanda Ponta (kW) | BT23: Demanda Fora Ponta (kW) | BU23: Consumo Ponta (kWh/mês) | BV23: Consumo Fora Ponta (kWh/mês) | BW23: Consumo Total (kWh/mês) | BY23: Mês/Ano | BZ23: Demanda Ponta (kW) | CA23: Demanda Fora Ponta (kW) | CB23: Consumo Ponta (kWh/mês) | CC23: Consumo Fora Ponta (kWh/mês) | CD23: Consumo Total (kWh/mês) | CF23: Mês/Ano | CG23: Demanda Ponta (kW) | CH23: Demanda Fora Ponta (kW) | CI23: Consumo Ponta (kWh/mês) | CJ23: Consumo Fora Ponta (kWh/mês) | CK23: Consumo Total (kWh/mês) | CM23: Mês/Ano | CN23: Demanda Ponta (kW) | CO23: Demanda Fora Ponta (kW) | CP23: Consumo Ponta (kWh/mês) | CQ23: Consumo Fora Ponta (kWh/mês) | CR23: Consumo Total (kWh/mês) | CT23: Mês/Ano | CU23: Demanda Ponta (kW) | CV23: Demanda Fora Ponta (kW) | CW23: Consumo Ponta (kWh/mês) | CX23: Consumo Fora Ponta (kWh/mês) | CY23: Consumo Total (kWh/mês) | DA23: Mês/Ano | DB23: Demanda Ponta (kW) | DC23: Demanda Fora Ponta (kW) | DD23: Consumo Ponta (kWh/mês) | DE23: Consumo Fora Ponta (kWh/mês) | DF23: Consumo Total (kWh/mês) | DH23: Mês/Ano | DI23: Demanda Ponta (kW) | DJ23: Demanda Fora Ponta (kW) | DK23: Consumo Ponta (kWh/mês) | DL23: Consumo Fora Ponta (kWh/mês) | DM23: Consumo Total (kWh/mês) | DO23: Mês/Ano | DP23: Demanda Ponta (kW) | DQ23: Demanda Fora Ponta (kW) | DR23: Consumo Ponta (kWh/mês) | DS23: Consumo Fora Ponta (kWh/mês) | DT23: Consumo Total (kWh/mês) | DV23: Mês/Ano | DW23: Demanda Ponta (kW) | DX23: Demanda Fora Ponta (kW) | DY23: Consumo Ponta (kWh/mês) | DZ23: Consumo Fora Ponta (kWh/mês) | EA23: Consumo Total (kWh/mês) | EC23: Mês/Ano | ED23: Demanda Ponta (kW) | EE23: Demanda Fora Ponta (kW) | EF23: Consumo Ponta (kWh/mês) | EG23: Consumo Fora Ponta (kWh/mês) | EH23: Consumo Total (kWh/mês) | EJ23: Mês/Ano | EK23: Demanda Ponta (kW) | EL23: Demanda Fora Ponta (kW) | EM23: Consumo Ponta (kWh/mês) | EN23: Consumo Fora Ponta (kWh/mês) | EO23: Consumo Total (kWh/mês) | EQ23: Mês/Ano | ER23: Demanda Ponta (kW) | ES23: Demanda Fora Ponta (kW) | ET23: Consumo Ponta (kWh/mês) | EU23: Consumo Fora Ponta (kWh/mês) | EV23: Consumo Total (kWh/mês)
B24: 1 | C24: =IF(R2<>"",R2,"") | D24: =IF(Q3<>"",Q3,"") | F24: =IF($N$24="","",$N$24) | G24: =O24+V24+AC24+AJ24+AQ24+AX24+BE24+BL24+BS24+BZ24+CG24+CN24+CU24+DB24+DI24+DP24+DW24+ED24+EK24+ER24 -> 0 | H24: =P24+W24+AD24+AK24+AR24+AY24+BF24+BM24+BT24+CA24+CH24+CO24+CV24+DC24+DJ24+DQ24+DX24+EE24+EL24+ES24 -> 0 | I24: =Q24+X24+AE24+AL24+AS24+AZ24+BG24+BN24+BU24+CB24+CI24+CP24+CW24+DD24+DK24+DR24+DY24+EF24+EM24+ET24 -> 0 | J24: =R24+Y24+AF24+AM24+AT24+BA24+BH24+BO24+BV24+CC24+CJ24+CQ24+CX24+DE24+DL24+DS24+DZ24+EG24+EN24+EU24 -> 0 | K24: =S24+Z24+AG24+AN24+AU24+BB24+BI24+BP24+BW24+CD24+CK24+CR24+CY24+DF24+DM24+DT24+EA24+EH24+EO24+EV24 -> 0 | M24: 1 | S24: =Q24+R24 -> 0 | U24: =IF($N$24="","",$N$24) | Z24: =X24+Y24 -> 0 | AB24: =IF($N$24="","",$N$24) | AG24: =AE24+AF24 -> 0 | AI24: =IF($N$24="","",$N$24) | AN24: =AL24+AM24 -> 0 | AP24: =IF($N$24="","",$N$24) | AU24: =AS24+AT24 -> 0 | AW24: =IF($N$24="","",$N$24) | BB24: =AZ24+BA24 -> 0 | BD24: =IF($N$24="","",$N$24) | BI24: =BG24+BH24 -> 0 | BK24: =IF($N$24="","",$N$24) | BP24: =BN24+BO24 -> 0 | BR24: =IF($N$24="","",$N$24) | BW24: =BU24+BV24 -> 0 | BY24: =IF($N$24="","",$N$24) | CD24: =CB24+CC24 -> 0 | CF24: =IF($N$24="","",$N$24) | CK24: =CI24+CJ24 -> 0 | CM24: =IF($N$24="","",$N$24) | CR24: =CP24+CQ24 -> 0 | CT24: =IF($N$24="","",$N$24) | CY24: =CW24+CX24 -> 0 | DA24: =IF($N$24="","",$N$24) | DF24: =DD24+DE24 -> 0 | DH24: =IF($N$24="","",$N$24) | DM24: =DK24+DL24 -> 0 | DO24: =IF($N$24="","",$N$24) | DT24: =DR24+DS24 -> 0 | DV24: =IF($N$24="","",$N$24) | EA24: =DY24+DZ24 -> 0 | EC24: =IF($N$24="","",$N$24) | EH24: =EF24+EG24 -> 0 | EJ24: =IF($N$24="","",$N$24) | EO24: =EM24+EN24 -> 0 | EQ24: =IF($N$24="","",$N$24) | EV24: =ET24+EU24 -> 0
B25: 2 | C25: =IF(Y2<>"",Y2,"") | D25: =IF(X3<>"",X3,"") | F25: =IF($N$25="","",$N$25) | G25: =O25+V25+AC25+AJ25+AQ25+AX25+BE25+BL25+BS25+BZ25+CG25+CN25+CU25+DB25+DI25+DP25+DW25+ED25+EK25+ER25 -> 0 | H25: =P25+W25+AD25+AK25+AR25+AY25+BF25+BM25+BT25+CA25+CH25+CO25+CV25+DC25+DJ25+DQ25+DX25+EE25+EL25+ES25 -> 0 | I25: =Q25+X25+AE25+AL25+AS25+AZ25+BG25+BN25+BU25+CB25+CI25+CP25+CW25+DD25+DK25+DR25+DY25+EF25+EM25+ET25 -> 0 | J25: =R25+Y25+AF25+AM25+AT25+BA25+BH25+BO25+BV25+CC25+CJ25+CQ25+CX25+DE25+DL25+DS25+DZ25+EG25+EN25+EU25 -> 0 | K25: =S25+Z25+AG25+AN25+AU25+BB25+BI25+BP25+BW25+CD25+CK25+CR25+CY25+DF25+DM25+DT25+EA25+EH25+EO25+EV25 -> 0 | M25: 2 | S25: =Q25+R25 -> 0 | U25: =IF($N$25="","",$N$25) | Z25: =X25+Y25 -> 0 | AB25: =IF($N$25="","",$N$25) | AG25: =AE25+AF25 -> 0 | AI25: =IF($N$25="","",$N$25) | AN25: =AL25+AM25 -> 0 | AP25: =IF($N$25="","",$N$25) | AU25: =AS25+AT25 -> 0 | AW25: =IF($N$25="","",$N$25) | BB25: =AZ25+BA25 -> 0 | BD25: =IF($N$25="","",$N$25) | BI25: =BG25+BH25 -> 0 | BK25: =IF($N$25="","",$N$25) | BP25: =BN25+BO25 -> 0 | BR25: =IF($N$25="","",$N$25) | BW25: =BU25+BV25 -> 0 | BY25: =IF($N$25="","",$N$25) | CD25: =CB25+CC25 -> 0 | CF25: =IF($N$25="","",$N$25) | CK25: =CI25+CJ25 -> 0 | CM25: =IF($N$25="","",$N$25) | CR25: =CP25+CQ25 -> 0 | CT25: =IF($N$25="","",$N$25) | CY25: =CW25+CX25 -> 0 | DA25: =IF($N$25="","",$N$25) | DF25: =DD25+DE25 -> 0 | DH25: =IF($N$25="","",$N$25) | DM25: =DK25+DL25 -> 0 | DO25: =IF($N$25="","",$N$25) | DT25: =DR25+DS25 -> 0 | DV25: =IF($N$25="","",$N$25) | EA25: =DY25+DZ25 -> 0 | EC25: =IF($N$25="","",$N$25) | EH25: =EF25+EG25 -> 0 | EJ25: =IF($N$25="","",$N$25) | EO25: =EM25+EN25 -> 0 | EQ25: =IF($N$25="","",$N$25) | EV25: =ET25+EU25 -> 0
B26: 3 | C26: =IF(AF2<>"",AF2,"") | D26: =IF(AE3<>"",AE3,"") | F26: =IF($N$26="","",$N$26) | G26: =O26+V26+AC26+AJ26+AQ26+AX26+BE26+BL26+BS26+BZ26+CG26+CN26+CU26+DB26+DI26+DP26+DW26+ED26+EK26+ER26 -> 0 | H26: =P26+W26+AD26+AK26+AR26+AY26+BF26+BM26+BT26+CA26+CH26+CO26+CV26+DC26+DJ26+DQ26+DX26+EE26+EL26+ES26 -> 0 | I26: =Q26+X26+AE26+AL26+AS26+AZ26+BG26+BN26+BU26+CB26+CI26+CP26+CW26+DD26+DK26+DR26+DY26+EF26+EM26+ET26 -> 0 | J26: =R26+Y26+AF26+AM26+AT26+BA26+BH26+BO26+BV26+CC26+CJ26+CQ26+CX26+DE26+DL26+DS26+DZ26+EG26+EN26+EU26 -> 0 | K26: =S26+Z26+AG26+AN26+AU26+BB26+BI26+BP26+BW26+CD26+CK26+CR26+CY26+DF26+DM26+DT26+EA26+EH26+EO26+EV26 -> 0 | M26: 3 | S26: =Q26+R26 -> 0 | U26: =IF($N$26="","",$N$26) | Z26: =X26+Y26 -> 0 | AB26: =IF($N$26="","",$N$26) | AG26: =AE26+AF26 -> 0 | AI26: =IF($N$26="","",$N$26) | AN26: =AL26+AM26 -> 0 | AP26: =IF($N$26="","",$N$26) | AU26: =AS26+AT26 -> 0 | AW26: =IF($N$26="","",$N$26) | BB26: =AZ26+BA26 -> 0 | BD26: =IF($N$26="","",$N$26) | BI26: =BG26+BH26 -> 0 | BK26: =IF($N$26="","",$N$26) | BP26: =BN26+BO26 -> 0 | BR26: =IF($N$26="","",$N$26) | BW26: =BU26+BV26 -> 0 | BY26: =IF($N$26="","",$N$26) | CD26: =CB26+CC26 -> 0 | CF26: =IF($N$26="","",$N$26) | CK26: =CI26+CJ26 -> 0 | CM26: =IF($N$26="","",$N$26) | CR26: =CP26+CQ26 -> 0 | CT26: =IF($N$26="","",$N$26) | CY26: =CW26+CX26 -> 0 | DA26: =IF($N$26="","",$N$26) | DF26: =DD26+DE26 -> 0 | DH26: =IF($N$26="","",$N$26) | DM26: =DK26+DL26 -> 0 | DO26: =IF($N$26="","",$N$26) | DT26: =DR26+DS26 -> 0 | DV26: =IF($N$26="","",$N$26) | EA26: =DY26+DZ26 -> 0 | EC26: =IF($N$26="","",$N$26) | EH26: =EF26+EG26 -> 0 | EJ26: =IF($N$26="","",$N$26) | EO26: =EM26+EN26 -> 0 | EQ26: =IF($N$26="","",$N$26) | EV26: =ET26+EU26 -> 0
B27: 4 | C27: =IF(AM2<>"",AM2,"") | D27: =IF(AL3<>"",AL3,"") | F27: =IF($N$27="","",$N$27) | G27: =O27+V27+AC27+AJ27+AQ27+AX27+BE27+BL27+BS27+BZ27+CG27+CN27+CU27+DB27+DI27+DP27+DW27+ED27+EK27+ER27 -> 0 | H27: =P27+W27+AD27+AK27+AR27+AY27+BF27+BM27+BT27+CA27+CH27+CO27+CV27+DC27+DJ27+DQ27+DX27+EE27+EL27+ES27 -> 0 | I27: =Q27+X27+AE27+AL27+AS27+AZ27+BG27+BN27+BU27+CB27+CI27+CP27+CW27+DD27+DK27+DR27+DY27+EF27+EM27+ET27 -> 0 | J27: =R27+Y27+AF27+AM27+AT27+BA27+BH27+BO27+BV27+CC27+CJ27+CQ27+CX27+DE27+DL27+DS27+DZ27+EG27+EN27+EU27 -> 0 | K27: =S27+Z27+AG27+AN27+AU27+BB27+BI27+BP27+BW27+CD27+CK27+CR27+CY27+DF27+DM27+DT27+EA27+EH27+EO27+EV27 -> 0 | M27: 4 | S27: =Q27+R27 -> 0 | U27: =IF($N$27="","",$N$27) | Z27: =X27+Y27 -> 0 | AB27: =IF($N$27="","",$N$27) | AG27: =AE27+AF27 -> 0 | AI27: =IF($N$27="","",$N$27) | AN27: =AL27+AM27 -> 0 | AP27: =IF($N$27="","",$N$27) | AU27: =AS27+AT27 -> 0 | AW27: =IF($N$27="","",$N$27) | BB27: =AZ27+BA27 -> 0 | BD27: =IF($N$27="","",$N$27) | BI27: =BG27+BH27 -> 0 | BK27: =IF($N$27="","",$N$27) | BP27: =BN27+BO27 -> 0 | BR27: =IF($N$27="","",$N$27) | BW27: =BU27+BV27 -> 0 | BY27: =IF($N$27="","",$N$27) | CD27: =CB27+CC27 -> 0 | CF27: =IF($N$27="","",$N$27) | CK27: =CI27+CJ27 -> 0 | CM27: =IF($N$27="","",$N$27) | CR27: =CP27+CQ27 -> 0 | CT27: =IF($N$27="","",$N$27) | CY27: =CW27+CX27 -> 0 | DA27: =IF($N$27="","",$N$27) | DF27: =DD27+DE27 -> 0 | DH27: =IF($N$27="","",$N$27) | DM27: =DK27+DL27 -> 0 | DO27: =IF($N$27="","",$N$27) | DT27: =DR27+DS27 -> 0 | DV27: =IF($N$27="","",$N$27) | EA27: =DY27+DZ27 -> 0 | EC27: =IF($N$27="","",$N$27) | EH27: =EF27+EG27 -> 0 | EJ27: =IF($N$27="","",$N$27) | EO27: =EM27+EN27 -> 0 | EQ27: =IF($N$27="","",$N$27) | EV27: =ET27+EU27 -> 0
B28: 5 | C28: =IF(AT2<>"",AT2,"") | D28: =IF(AS3<>"",AS3,"") | F28: =IF($N$28="","",$N$28) | G28: =O28+V28+AC28+AJ28+AQ28+AX28+BE28+BL28+BS28+BZ28+CG28+CN28+CU28+DB28+DI28+DP28+DW28+ED28+EK28+ER28 -> 0 | H28: =P28+W28+AD28+AK28+AR28+AY28+BF28+BM28+BT28+CA28+CH28+CO28+CV28+DC28+DJ28+DQ28+DX28+EE28+EL28+ES28 -> 0 | I28: =Q28+X28+AE28+AL28+AS28+AZ28+BG28+BN28+BU28+CB28+CI28+CP28+CW28+DD28+DK28+DR28+DY28+EF28+EM28+ET28 -> 0 | J28: =R28+Y28+AF28+AM28+AT28+BA28+BH28+BO28+BV28+CC28+CJ28+CQ28+CX28+DE28+DL28+DS28+DZ28+EG28+EN28+EU28 -> 0 | K28: =S28+Z28+AG28+AN28+AU28+BB28+BI28+BP28+BW28+CD28+CK28+CR28+CY28+DF28+DM28+DT28+EA28+EH28+EO28+EV28 -> 0 | M28: 5 | S28: =Q28+R28 -> 0 | U28: =IF($N$28="","",$N$28) | Z28: =X28+Y28 -> 0 | AB28: =IF($N$28="","",$N$28) | AG28: =AE28+AF28 -> 0 | AI28: =IF($N$28="","",$N$28) | AN28: =AL28+AM28 -> 0 | AP28: =IF($N$28="","",$N$28) | AU28: =AS28+AT28 -> 0 | AW28: =IF($N$28="","",$N$28) | BB28: =AZ28+BA28 -> 0 | BD28: =IF($N$28="","",$N$28) | BI28: =BG28+BH28 -> 0 | BK28: =IF($N$28="","",$N$28) | BP28: =BN28+BO28 -> 0 | BR28: =IF($N$28="","",$N$28) | BW28: =BU28+BV28 -> 0 | BY28: =IF($N$28="","",$N$28) | CD28: =CB28+CC28 -> 0 | CF28: =IF($N$28="","",$N$28) | CK28: =CI28+CJ28 -> 0 | CM28: =IF($N$28="","",$N$28) | CR28: =CP28+CQ28 -> 0 | CT28: =IF($N$28="","",$N$28) | CY28: =CW28+CX28 -> 0 | DA28: =IF($N$28="","",$N$28) | DF28: =DD28+DE28 -> 0 | DH28: =IF($N$28="","",$N$28) | DM28: =DK28+DL28 -> 0 | DO28: =IF($N$28="","",$N$28) | DT28: =DR28+DS28 -> 0 | DV28: =IF($N$28="","",$N$28) | EA28: =DY28+DZ28 -> 0 | EC28: =IF($N$28="","",$N$28) | EH28: =EF28+EG28 -> 0 | EJ28: =IF($N$28="","",$N$28) | EO28: =EM28+EN28 -> 0 | EQ28: =IF($N$28="","",$N$28) | EV28: =ET28+EU28 -> 0
B29: 6 | C29: =IF(BA2<>"",BA2,"") | D29: =IF(AZ3<>"",AZ3,"") | F29: =IF($N$29="","",$N$29) | G29: =O29+V29+AC29+AJ29+AQ29+AX29+BE29+BL29+BS29+BZ29+CG29+CN29+CU29+DB29+DI29+DP29+DW29+ED29+EK29+ER29 -> 0 | H29: =P29+W29+AD29+AK29+AR29+AY29+BF29+BM29+BT29+CA29+CH29+CO29+CV29+DC29+DJ29+DQ29+DX29+EE29+EL29+ES29 -> 0 | I29: =Q29+X29+AE29+AL29+AS29+AZ29+BG29+BN29+BU29+CB29+CI29+CP29+CW29+DD29+DK29+DR29+DY29+EF29+EM29+ET29 -> 0 | J29: =R29+Y29+AF29+AM29+AT29+BA29+BH29+BO29+BV29+CC29+CJ29+CQ29+CX29+DE29+DL29+DS29+DZ29+EG29+EN29+EU29 -> 0 | K29: =S29+Z29+AG29+AN29+AU29+BB29+BI29+BP29+BW29+CD29+CK29+CR29+CY29+DF29+DM29+DT29+EA29+EH29+EO29+EV29 -> 0 | M29: 6 | S29: =Q29+R29 -> 0 | U29: =IF($N$29="","",$N$29) | Z29: =X29+Y29 -> 0 | AB29: =IF($N$29="","",$N$29) | AG29: =AE29+AF29 -> 0 | AI29: =IF($N$29="","",$N$29) | AN29: =AL29+AM29 -> 0 | AP29: =IF($N$29="","",$N$29) | AU29: =AS29+AT29 -> 0 | AW29: =IF($N$29="","",$N$29) | BB29: =AZ29+BA29 -> 0 | BD29: =IF($N$29="","",$N$29) | BI29: =BG29+BH29 -> 0 | BK29: =IF($N$29="","",$N$29) | BP29: =BN29+BO29 -> 0 | BR29: =IF($N$29="","",$N$29) | BW29: =BU29+BV29 -> 0 | BY29: =IF($N$29="","",$N$29) | CD29: =CB29+CC29 -> 0 | CF29: =IF($N$29="","",$N$29) | CK29: =CI29+CJ29 -> 0 | CM29: =IF($N$29="","",$N$29) | CR29: =CP29+CQ29 -> 0 | CT29: =IF($N$29="","",$N$29) | CY29: =CW29+CX29 -> 0 | DA29: =IF($N$29="","",$N$29) | DF29: =DD29+DE29 -> 0 | DH29: =IF($N$29="","",$N$29) | DM29: =DK29+DL29 -> 0 | DO29: =IF($N$29="","",$N$29) | DT29: =DR29+DS29 -> 0 | DV29: =IF($N$29="","",$N$29) | EA29: =DY29+DZ29 -> 0 | EC29: =IF($N$29="","",$N$29) | EH29: =EF29+EG29 -> 0 | EJ29: =IF($N$29="","",$N$29) | EO29: =EM29+EN29 -> 0 | EQ29: =IF($N$29="","",$N$29) | EV29: =ET29+EU29 -> 0
B30: 7 | C30: =IF(BH2<>"",BH2,"") | D30: =IF(BG3<>"",BG3,"") | F30: =IF($N$30="","",$N$30) | G30: =O30+V30+AC30+AJ30+AQ30+AX30+BE30+BL30+BS30+BZ30+CG30+CN30+CU30+DB30+DI30+DP30+DW30+ED30+EK30+ER30 -> 0 | H30: =P30+W30+AD30+AK30+AR30+AY30+BF30+BM30+BT30+CA30+CH30+CO30+CV30+DC30+DJ30+DQ30+DX30+EE30+EL30+ES30 -> 0 | I30: =Q30+X30+AE30+AL30+AS30+AZ30+BG30+BN30+BU30+CB30+CI30+CP30+CW30+DD30+DK30+DR30+DY30+EF30+EM30+ET30 -> 0 | J30: =R30+Y30+AF30+AM30+AT30+BA30+BH30+BO30+BV30+CC30+CJ30+CQ30+CX30+DE30+DL30+DS30+DZ30+EG30+EN30+EU30 -> 0 | K30: =S30+Z30+AG30+AN30+AU30+BB30+BI30+BP30+BW30+CD30+CK30+CR30+CY30+DF30+DM30+DT30+EA30+EH30+EO30+EV30 -> 0 | M30: 7 | S30: =Q30+R30 -> 0 | U30: =IF($N$30="","",$N$30) | Z30: =X30+Y30 -> 0 | AB30: =IF($N$30="","",$N$30) | AG30: =AE30+AF30 -> 0 | AI30: =IF($N$30="","",$N$30) | AN30: =AL30+AM30 -> 0 | AP30: =IF($N$30="","",$N$30) | AU30: =AS30+AT30 -> 0 | AW30: =IF($N$30="","",$N$30) | BB30: =AZ30+BA30 -> 0 | BD30: =IF($N$30="","",$N$30) | BI30: =BG30+BH30 -> 0 | BK30: =IF($N$30="","",$N$30) | BP30: =BN30+BO30 -> 0 | BR30: =IF($N$30="","",$N$30) | BW30: =BU30+BV30 -> 0 | BY30: =IF($N$30="","",$N$30) | CD30: =CB30+CC30 -> 0 | CF30: =IF($N$30="","",$N$30) | CK30: =CI30+CJ30 -> 0 | CM30: =IF($N$30="","",$N$30) | CR30: =CP30+CQ30 -> 0 | CT30: =IF($N$30="","",$N$30) | CY30: =CW30+CX30 -> 0 | DA30: =IF($N$30="","",$N$30) | DF30: =DD30+DE30 -> 0 | DH30: =IF($N$30="","",$N$30) | DM30: =DK30+DL30 -> 0 | DO30: =IF($N$30="","",$N$30) | DT30: =DR30+DS30 -> 0 | DV30: =IF($N$30="","",$N$30) | EA30: =DY30+DZ30 -> 0 | EC30: =IF($N$30="","",$N$30) | EH30: =EF30+EG30 -> 0 | EJ30: =IF($N$30="","",$N$30) | EO30: =EM30+EN30 -> 0 | EQ30: =IF($N$30="","",$N$30) | EV30: =ET30+EU30 -> 0
B31: 8 | C31: =IF(BO2<>"",BO2,"") | D31: =IF(BN3<>"",BN3,"") | F31: =IF($N$31="","",$N$31) | G31: =O31+V31+AC31+AJ31+AQ31+AX31+BE31+BL31+BS31+BZ31+CG31+CN31+CU31+DB31+DI31+DP31+DW31+ED31+EK31+ER31 -> 0 | H31: =P31+W31+AD31+AK31+AR31+AY31+BF31+BM31+BT31+CA31+CH31+CO31+CV31+DC31+DJ31+DQ31+DX31+EE31+EL31+ES31 -> 0 | I31: =Q31+X31+AE31+AL31+AS31+AZ31+BG31+BN31+BU31+CB31+CI31+CP31+CW31+DD31+DK31+DR31+DY31+EF31+EM31+ET31 -> 0 | J31: =R31+Y31+AF31+AM31+AT31+BA31+BH31+BO31+BV31+CC31+CJ31+CQ31+CX31+DE31+DL31+DS31+DZ31+EG31+EN31+EU31 -> 0 | K31: =S31+Z31+AG31+AN31+AU31+BB31+BI31+BP31+BW31+CD31+CK31+CR31+CY31+DF31+DM31+DT31+EA31+EH31+EO31+EV31 -> 0 | M31: 8 | S31: =Q31+R31 -> 0 | U31: =IF($N$31="","",$N$31) | Z31: =X31+Y31 -> 0 | AB31: =IF($N$31="","",$N$31) | AG31: =AE31+AF31 -> 0 | AI31: =IF($N$31="","",$N$31) | AN31: =AL31+AM31 -> 0 | AP31: =IF($N$31="","",$N$31) | AU31: =AS31+AT31 -> 0 | AW31: =IF($N$31="","",$N$31) | BB31: =AZ31+BA31 -> 0 | BD31: =IF($N$31="","",$N$31) | BI31: =BG31+BH31 -> 0 | BK31: =IF($N$31="","",$N$31) | BP31: =BN31+BO31 -> 0 | BR31: =IF($N$31="","",$N$31) | BW31: =BU31+BV31 -> 0 | BY31: =IF($N$31="","",$N$31) | CD31: =CB31+CC31 -> 0 | CF31: =IF($N$31="","",$N$31) | CK31: =CI31+CJ31 -> 0 | CM31: =IF($N$31="","",$N$31) | CR31: =CP31+CQ31 -> 0 | CT31: =IF($N$31="","",$N$31) | CY31: =CW31+CX31 -> 0 | DA31: =IF($N$31="","",$N$31) | DF31: =DD31+DE31 -> 0 | DH31: =IF($N$31="","",$N$31) | DM31: =DK31+DL31 -> 0 | DO31: =IF($N$31="","",$N$31) | DT31: =DR31+DS31 -> 0 | DV31: =IF($N$31="","",$N$31) | EA31: =DY31+DZ31 -> 0 | EC31: =IF($N$31="","",$N$31) | EH31: =EF31+EG31 -> 0 | EJ31: =IF($N$31="","",$N$31) | EO31: =EM31+EN31 -> 0 | EQ31: =IF($N$31="","",$N$31) | EV31: =ET31+EU31 -> 0
B32: 9 | C32: =IF(BV2<>"",BV2,"") | D32: =IF(BU3<>"",BU3,"") | F32: =IF($N$32="","",$N$32) | G32: =O32+V32+AC32+AJ32+AQ32+AX32+BE32+BL32+BS32+BZ32+CG32+CN32+CU32+DB32+DI32+DP32+DW32+ED32+EK32+ER32 -> 0 | H32: =P32+W32+AD32+AK32+AR32+AY32+BF32+BM32+BT32+CA32+CH32+CO32+CV32+DC32+DJ32+DQ32+DX32+EE32+EL32+ES32 -> 0 | I32: =Q32+X32+AE32+AL32+AS32+AZ32+BG32+BN32+BU32+CB32+CI32+CP32+CW32+DD32+DK32+DR32+DY32+EF32+EM32+ET32 -> 0 | J32: =R32+Y32+AF32+AM32+AT32+BA32+BH32+BO32+BV32+CC32+CJ32+CQ32+CX32+DE32+DL32+DS32+DZ32+EG32+EN32+EU32 -> 0 | K32: =S32+Z32+AG32+AN32+AU32+BB32+BI32+BP32+BW32+CD32+CK32+CR32+CY32+DF32+DM32+DT32+EA32+EH32+EO32+EV32 -> 0 | M32: 9 | S32: =Q32+R32 -> 0 | U32: =IF($N$32="","",$N$32) | Z32: =X32+Y32 -> 0 | AB32: =IF($N$32="","",$N$32) | AG32: =AE32+AF32 -> 0 | AI32: =IF($N$32="","",$N$32) | AN32: =AL32+AM32 -> 0 | AP32: =IF($N$32="","",$N$32) | AU32: =AS32+AT32 -> 0 | AW32: =IF($N$32="","",$N$32) | BB32: =AZ32+BA32 -> 0 | BD32: =IF($N$32="","",$N$32) | BI32: =BG32+BH32 -> 0 | BK32: =IF($N$32="","",$N$32) | BP32: =BN32+BO32 -> 0 | BR32: =IF($N$32="","",$N$32) | BW32: =BU32+BV32 -> 0 | BY32: =IF($N$32="","",$N$32) | CD32: =CB32+CC32 -> 0 | CF32: =IF($N$32="","",$N$32) | CK32: =CI32+CJ32 -> 0 | CM32: =IF($N$32="","",$N$32) | CR32: =CP32+CQ32 -> 0 | CT32: =IF($N$32="","",$N$32) | CY32: =CW32+CX32 -> 0 | DA32: =IF($N$32="","",$N$32) | DF32: =DD32+DE32 -> 0 | DH32: =IF($N$32="","",$N$32) | DM32: =DK32+DL32 -> 0 | DO32: =IF($N$32="","",$N$32) | DT32: =DR32+DS32 -> 0 | DV32: =IF($N$32="","",$N$32) | EA32: =DY32+DZ32 -> 0 | EC32: =IF($N$32="","",$N$32) | EH32: =EF32+EG32 -> 0 | EJ32: =IF($N$32="","",$N$32) | EO32: =EM32+EN32 -> 0 | EQ32: =IF($N$32="","",$N$32) | EV32: =ET32+EU32 -> 0
B33: 10 | C33: =IF(CC2<>"",CC2,"") | D33: =IF(CB3<>"",CB3,"") | F33: =IF($N$33="","",$N$33) | G33: =O33+V33+AC33+AJ33+AQ33+AX33+BE33+BL33+BS33+BZ33+CG33+CN33+CU33+DB33+DI33+DP33+DW33+ED33+EK33+ER33 -> 0 | H33: =P33+W33+AD33+AK33+AR33+AY33+BF33+BM33+BT33+CA33+CH33+CO33+CV33+DC33+DJ33+DQ33+DX33+EE33+EL33+ES33 -> 0 | I33: =Q33+X33+AE33+AL33+AS33+AZ33+BG33+BN33+BU33+CB33+CI33+CP33+CW33+DD33+DK33+DR33+DY33+EF33+EM33+ET33 -> 0 | J33: =R33+Y33+AF33+AM33+AT33+BA33+BH33+BO33+BV33+CC33+CJ33+CQ33+CX33+DE33+DL33+DS33+DZ33+EG33+EN33+EU33 -> 0 | K33: =S33+Z33+AG33+AN33+AU33+BB33+BI33+BP33+BW33+CD33+CK33+CR33+CY33+DF33+DM33+DT33+EA33+EH33+EO33+EV33 -> 0 | M33: 10 | S33: =Q33+R33 -> 0 | U33: =IF($N$33="","",$N$33) | Z33: =X33+Y33 -> 0 | AB33: =IF($N$33="","",$N$33) | AG33: =AE33+AF33 -> 0 | AI33: =IF($N$33="","",$N$33) | AN33: =AL33+AM33 -> 0 | AP33: =IF($N$33="","",$N$33) | AU33: =AS33+AT33 -> 0 | AW33: =IF($N$33="","",$N$33) | BB33: =AZ33+BA33 -> 0 | BD33: =IF($N$33="","",$N$33) | BI33: =BG33+BH33 -> 0 | BK33: =IF($N$33="","",$N$33) | BP33: =BN33+BO33 -> 0 | BR33: =IF($N$33="","",$N$33) | BW33: =BU33+BV33 -> 0 | BY33: =IF($N$33="","",$N$33) | CD33: =CB33+CC33 -> 0 | CF33: =IF($N$33="","",$N$33) | CK33: =CI33+CJ33 -> 0 | CM33: =IF($N$33="","",$N$33) | CR33: =CP33+CQ33 -> 0 | CT33: =IF($N$33="","",$N$33) | CY33: =CW33+CX33 -> 0 | DA33: =IF($N$33="","",$N$33) | DF33: =DD33+DE33 -> 0 | DH33: =IF($N$33="","",$N$33) | DM33: =DK33+DL33 -> 0 | DO33: =IF($N$33="","",$N$33) | DT33: =DR33+DS33 -> 0 | DV33: =IF($N$33="","",$N$33) | EA33: =DY33+DZ33 -> 0 | EC33: =IF($N$33="","",$N$33) | EH33: =EF33+EG33 -> 0 | EJ33: =IF($N$33="","",$N$33) | EO33: =EM33+EN33 -> 0 | EQ33: =IF($N$33="","",$N$33) | EV33: =ET33+EU33 -> 0
B34: 11 | C34: =IF(CJ2<>"",CJ2,"") | D34: =IF(CI3<>"",CI3,"") | F34: =IF($N$34="","",$N$34) | G34: =O34+V34+AC34+AJ34+AQ34+AX34+BE34+BL34+BS34+BZ34+CG34+CN34+CU34+DB34+DI34+DP34+DW34+ED34+EK34+ER34 -> 0 | H34: =P34+W34+AD34+AK34+AR34+AY34+BF34+BM34+BT34+CA34+CH34+CO34+CV34+DC34+DJ34+DQ34+DX34+EE34+EL34+ES34 -> 0 | I34: =Q34+X34+AE34+AL34+AS34+AZ34+BG34+BN34+BU34+CB34+CI34+CP34+CW34+DD34+DK34+DR34+DY34+EF34+EM34+ET34 -> 0 | J34: =R34+Y34+AF34+AM34+AT34+BA34+BH34+BO34+BV34+CC34+CJ34+CQ34+CX34+DE34+DL34+DS34+DZ34+EG34+EN34+EU34 -> 0 | K34: =S34+Z34+AG34+AN34+AU34+BB34+BI34+BP34+BW34+CD34+CK34+CR34+CY34+DF34+DM34+DT34+EA34+EH34+EO34+EV34 -> 0 | M34: 11 | S34: =Q34+R34 -> 0 | U34: =IF($N$34="","",$N$34) | Z34: =X34+Y34 -> 0 | AB34: =IF($N$34="","",$N$34) | AG34: =AE34+AF34 -> 0 | AI34: =IF($N$34="","",$N$34) | AN34: =AL34+AM34 -> 0 | AP34: =IF($N$34="","",$N$34) | AU34: =AS34+AT34 -> 0 | AW34: =IF($N$34="","",$N$34) | BB34: =AZ34+BA34 -> 0 | BD34: =IF($N$34="","",$N$34) | BI34: =BG34+BH34 -> 0 | BK34: =IF($N$34="","",$N$34) | BP34: =BN34+BO34 -> 0 | BR34: =IF($N$34="","",$N$34) | BW34: =BU34+BV34 -> 0 | BY34: =IF($N$34="","",$N$34) | CD34: =CB34+CC34 -> 0 | CF34: =IF($N$34="","",$N$34) | CK34: =CI34+CJ34 -> 0 | CM34: =IF($N$34="","",$N$34) | CR34: =CP34+CQ34 -> 0 | CT34: =IF($N$34="","",$N$34) | CY34: =CW34+CX34 -> 0 | DA34: =IF($N$34="","",$N$34) | DF34: =DD34+DE34 -> 0 | DH34: =IF($N$34="","",$N$34) | DM34: =DK34+DL34 -> 0 | DO34: =IF($N$34="","",$N$34) | DT34: =DR34+DS34 -> 0 | DV34: =IF($N$34="","",$N$34) | EA34: =DY34+DZ34 -> 0 | EC34: =IF($N$34="","",$N$34) | EH34: =EF34+EG34 -> 0 | EJ34: =IF($N$34="","",$N$34) | EO34: =EM34+EN34 -> 0 | EQ34: =IF($N$34="","",$N$34) | EV34: =ET34+EU34 -> 0
B35: 12 | C35: =IF(CQ2<>"",CQ2,"") | D35: =IF(CP3<>"",CP3,"") | F35: =IF($N$35="","",$N$35) | G35: =O35+V35+AC35+AJ35+AQ35+AX35+BE35+BL35+BS35+BZ35+CG35+CN35+CU35+DB35+DI35+DP35+DW35+ED35+EK35+ER35 -> 0 | H35: =P35+W35+AD35+AK35+AR35+AY35+BF35+BM35+BT35+CA35+CH35+CO35+CV35+DC35+DJ35+DQ35+DX35+EE35+EL35+ES35 -> 0 | I35: =Q35+X35+AE35+AL35+AS35+AZ35+BG35+BN35+BU35+CB35+CI35+CP35+CW35+DD35+DK35+DR35+DY35+EF35+EM35+ET35 -> 0 | J35: =R35+Y35+AF35+AM35+AT35+BA35+BH35+BO35+BV35+CC35+CJ35+CQ35+CX35+DE35+DL35+DS35+DZ35+EG35+EN35+EU35 -> 0 | K35: =S35+Z35+AG35+AN35+AU35+BB35+BI35+BP35+BW35+CD35+CK35+CR35+CY35+DF35+DM35+DT35+EA35+EH35+EO35+EV35 -> 0 | M35: 12 | S35: =Q35+R35 -> 0 | U35: =IF($N$35="","",$N$35) | Z35: =X35+Y35 -> 0 | AB35: =IF($N$35="","",$N$35) | AG35: =AE35+AF35 -> 0 | AI35: =IF($N$35="","",$N$35) | AN35: =AL35+AM35 -> 0 | AP35: =IF($N$35="","",$N$35) | AU35: =AS35+AT35 -> 0 | AW35: =IF($N$35="","",$N$35) | BB35: =AZ35+BA35 -> 0 | BD35: =IF($N$35="","",$N$35) | BI35: =BG35+BH35 -> 0 | BK35: =IF($N$35="","",$N$35) | BP35: =BN35+BO35 -> 0 | BR35: =IF($N$35="","",$N$35) | BW35: =BU35+BV35 -> 0 | BY35: =IF($N$35="","",$N$35) | CD35: =CB35+CC35 -> 0 | CF35: =IF($N$35="","",$N$35) | CK35: =CI35+CJ35 -> 0 | CM35: =IF($N$35="","",$N$35) | CR35: =CP35+CQ35 -> 0 | CT35: =IF($N$35="","",$N$35) | CY35: =CW35+CX35 -> 0 | DA35: =IF($N$35="","",$N$35) | DF35: =DD35+DE35 -> 0 | DH35: =IF($N$35="","",$N$35) | DM35: =DK35+DL35 -> 0 | DO35: =IF($N$35="","",$N$35) | DT35: =DR35+DS35 -> 0 | DV35: =IF($N$35="","",$N$35) | EA35: =DY35+DZ35 -> 0 | EC35: =IF($N$35="","",$N$35) | EH35: =EF35+EG35 -> 0 | EJ35: =IF($N$35="","",$N$35) | EO35: =EM35+EN35 -> 0 | EQ35: =IF($N$35="","",$N$35) | EV35: =ET35+EU35 -> 0
B36: 13 | C36: =IF(CX2<>"",CX2,"") | D36: =IF(CW3<>"",CW3,"") | F36: MÉDIA | G36: =SUM(G24:G35)/12 -> 0 | H36: =SUM(H24:H35)/12 -> 0 | I36: =SUM(I24:I35)/12 -> 0 | J36: =SUM(J24:J35)/12 -> 0 | K36: =SUM(K24:K35)/12 -> 0 | N36: MÉDIA | O36: =SUM(O24:O35)/12 -> 0 | P36: =SUM(P24:P35)/12 -> 0 | Q36: =SUM(Q24:Q35)/12 -> 0 | R36: =SUM(R24:R35)/12 -> 0 | S36: =SUM(S24:S35)/12 -> 0 | U36: MÉDIA | V36: =SUM(V24:V35)/12 -> 0 | W36: =SUM(W24:W35)/12 -> 0 | X36: =SUM(X24:X35)/12 -> 0 | Y36: =SUM(Y24:Y35)/12 -> 0 | Z36: =SUM(Z24:Z35)/12 -> 0 | AB36: MÉDIA | AC36: =SUM(AC24:AC35)/12 -> 0 | AD36: =SUM(AD24:AD35)/12 -> 0 | AE36: =SUM(AE24:AE35)/12 -> 0 | AF36: =SUM(AF24:AF35)/12 -> 0 | AG36: =SUM(AG24:AG35)/12 -> 0 | AI36: MÉDIA | AJ36: =SUM(AJ24:AJ35)/12 -> 0 | AK36: =SUM(AK24:AK35)/12 -> 0 | AL36: =SUM(AL24:AL35)/12 -> 0 | AM36: =SUM(AM24:AM35)/12 -> 0 | AN36: =SUM(AN24:AN35)/12 -> 0 | AP36: MÉDIA | AQ36: =SUM(AQ24:AQ35)/12 -> 0 | AR36: =SUM(AR24:AR35)/12 -> 0 | AS36: =SUM(AS24:AS35)/12 -> 0 | AT36: =SUM(AT24:AT35)/12 -> 0 | AU36: =SUM(AU24:AU35)/12 -> 0 | AW36: MÉDIA | AX36: =SUM(AX24:AX35)/12 -> 0 | AY36: =SUM(AY24:AY35)/12 -> 0 | AZ36: =SUM(AZ24:AZ35)/12 -> 0 | BA36: =SUM(BA24:BA35)/12 -> 0 | BB36: =SUM(BB24:BB35)/12 -> 0 | BD36: MÉDIA | BE36: =SUM(BE24:BE35)/12 -> 0 | BF36: =SUM(BF24:BF35)/12 -> 0 | BG36: =SUM(BG24:BG35)/12 -> 0 | BH36: =SUM(BH24:BH35)/12 -> 0 | BI36: =SUM(BI24:BI35)/12 -> 0 | BK36: MÉDIA | BL36: =SUM(BL24:BL35)/12 -> 0 | BM36: =SUM(BM24:BM35)/12 -> 0 | BN36: =SUM(BN24:BN35)/12 -> 0 | BO36: =SUM(BO24:BO35)/12 -> 0 | BP36: =SUM(BP24:BP35)/12 -> 0 | BR36: MÉDIA | BS36: =SUM(BS24:BS35)/12 -> 0 | BT36: =SUM(BT24:BT35)/12 -> 0 | BU36: =SUM(BU24:BU35)/12 -> 0 | BV36: =SUM(BV24:BV35)/12 -> 0 | BW36: =SUM(BW24:BW35)/12 -> 0 | BY36: MÉDIA | BZ36: =SUM(BZ24:BZ35)/12 -> 0 | CA36: =SUM(CA24:CA35)/12 -> 0 | CB36: =SUM(CB24:CB35)/12 -> 0 | CC36: =SUM(CC24:CC35)/12 -> 0 | CD36: =SUM(CD24:CD35)/12 -> 0 | CF36: MÉDIA | CG36: =SUM(CG24:CG35)/12 -> 0 | CH36: =SUM(CH24:CH35)/12 -> 0 | CI36: =SUM(CI24:CI35)/12 -> 0 | CJ36: =SUM(CJ24:CJ35)/12 -> 0 | CK36: =SUM(CK24:CK35)/12 -> 0 | CM36: MÉDIA | CN36: =SUM(CN24:CN35)/12 -> 0 | CO36: =SUM(CO24:CO35)/12 -> 0 | CP36: =SUM(CP24:CP35)/12 -> 0 | CQ36: =SUM(CQ24:CQ35)/12 -> 0 | CR36: =SUM(CR24:CR35)/12 -> 0 | CT36: MÉDIA | CU36: =SUM(CU24:CU35)/12 -> 0 | CV36: =SUM(CV24:CV35)/12 -> 0 | CW36: =SUM(CW24:CW35)/12 -> 0 | CX36: =SUM(CX24:CX35)/12 -> 0 | CY36: =SUM(CY24:CY35)/12 -> 0 | DA36: MÉDIA | DB36: =SUM(DB24:DB35)/12 -> 0 | DC36: =SUM(DC24:DC35)/12 -> 0 | DD36: =SUM(DD24:DD35)/12 -> 0 | DE36: =SUM(DE24:DE35)/12 -> 0 | DF36: =SUM(DF24:DF35)/12 -> 0 | DH36: MÉDIA | DI36: =SUM(DI24:DI35)/12 -> 0 | DJ36: =SUM(DJ24:DJ35)/12 -> 0 | DK36: =SUM(DK24:DK35)/12 -> 0 | DL36: =SUM(DL24:DL35)/12 -> 0 | DM36: =SUM(DM24:DM35)/12 -> 0 | DO36: MÉDIA | DP36: =SUM(DP24:DP35)/12 -> 0 | DQ36: =SUM(DQ24:DQ35)/12 -> 0 | DR36: =SUM(DR24:DR35)/12 -> 0 | DS36: =SUM(DS24:DS35)/12 -> 0 | DT36: =SUM(DT24:DT35)/12 -> 0 | DV36: MÉDIA | DW36: =SUM(DW24:DW35)/12 -> 0 | DX36: =SUM(DX24:DX35)/12 -> 0 | DY36: =SUM(DY24:DY35)/12 -> 0 | DZ36: =SUM(DZ24:DZ35)/12 -> 0 | EA36: =SUM(EA24:EA35)/12 -> 0 | EC36: MÉDIA | ED36: =SUM(ED24:ED35)/12 -> 0 | EE36: =SUM(EE24:EE35)/12 -> 0 | EF36: =SUM(EF24:EF35)/12 -> 0 | EG36: =SUM(EG24:EG35)/12 -> 0 | EH36: =SUM(EH24:EH35)/12 -> 0 | EJ36: MÉDIA | EK36: =SUM(EK24:EK35)/12 -> 0 | EL36: =SUM(EL24:EL35)/12 -> 0 | EM36: =SUM(EM24:EM35)/12 -> 0 | EN36: =SUM(EN24:EN35)/12 -> 0 | EO36: =SUM(EO24:EO35)/12 -> 0 | EQ36: MÉDIA | ER36: =SUM(ER24:ER35)/12 -> 0 | ES36: =SUM(ES24:ES35)/12 -> 0 | ET36: =SUM(ET24:ET35)/12 -> 0 | EU36: =SUM(EU24:EU35)/12 -> 0 | EV36: =SUM(EV24:EV35)/12 -> 0
B37: 14 | C37: =IF(DE2<>"",DE2,"") | D37: =IF(DD3<>"",DD3,"") | F37: TOTAL | G37: =SUM(G24:G35) -> 0 | H37: =SUM(H24:H35) -> 0 | I37: =SUM(I24:I35) -> 0 | J37: =SUM(J24:J35) -> 0 | K37: =SUM(K24:K35) -> 0 | N37: TOTAL | O37: =SUM(O24:O35) -> 0 | P37: =SUM(P24:P35) -> 0 | Q37: =SUM(Q24:Q35) -> 0 | R37: =SUM(R24:R35) -> 0 | S37: =SUM(S24:S35) -> 0 | U37: TOTAL | V37: =SUM(V24:V35) -> 0 | W37: =SUM(W24:W35) -> 0 | X37: =SUM(X24:X35) -> 0 | Y37: =SUM(Y24:Y35) -> 0 | Z37: =SUM(Z24:Z35) -> 0 | AB37: TOTAL | AC37: =SUM(AC24:AC35) -> 0 | AD37: =SUM(AD24:AD35) -> 0 | AE37: =SUM(AE24:AE35) -> 0 | AF37: =SUM(AF24:AF35) -> 0 | AG37: =SUM(AG24:AG35) -> 0 | AI37: TOTAL | AJ37: =SUM(AJ24:AJ35) -> 0 | AK37: =SUM(AK24:AK35) -> 0 | AL37: =SUM(AL24:AL35) -> 0 | AM37: =SUM(AM24:AM35) -> 0 | AN37: =SUM(AN24:AN35) -> 0 | AP37: TOTAL | AQ37: =SUM(AQ24:AQ35) -> 0 | AR37: =SUM(AR24:AR35) -> 0 | AS37: =SUM(AS24:AS35) -> 0 | AT37: =SUM(AT24:AT35) -> 0 | AU37: =SUM(AU24:AU35) -> 0 | AW37: TOTAL | AX37: =SUM(AX24:AX35) -> 0 | AY37: =SUM(AY24:AY35) -> 0 | AZ37: =SUM(AZ24:AZ35) -> 0 | BA37: =SUM(BA24:BA35) -> 0 | BB37: =SUM(BB24:BB35) -> 0 | BD37: TOTAL | BE37: =SUM(BE24:BE35) -> 0 | BF37: =SUM(BF24:BF35) -> 0 | BG37: =SUM(BG24:BG35) -> 0 | BH37: =SUM(BH24:BH35) -> 0 | BI37: =SUM(BI24:BI35) -> 0 | BK37: TOTAL | BL37: =SUM(BL24:BL35) -> 0 | BM37: =SUM(BM24:BM35) -> 0 | BN37: =SUM(BN24:BN35) -> 0 | BO37: =SUM(BO24:BO35) -> 0 | BP37: =SUM(BP24:BP35) -> 0 | BR37: TOTAL | BS37: =SUM(BS24:BS35) -> 0 | BT37: =SUM(BT24:BT35) -> 0 | BU37: =SUM(BU24:BU35) -> 0 | BV37: =SUM(BV24:BV35) -> 0 | BW37: =SUM(BW24:BW35) -> 0 | BY37: TOTAL | BZ37: =SUM(BZ24:BZ35) -> 0 | CA37: =SUM(CA24:CA35) -> 0 | CB37: =SUM(CB24:CB35) -> 0 | CC37: =SUM(CC24:CC35) -> 0 | CD37: =SUM(CD24:CD35) -> 0 | CF37: TOTAL | CG37: =SUM(CG24:CG35) -> 0 | CH37: =SUM(CH24:CH35) -> 0 | CI37: =SUM(CI24:CI35) -> 0 | CJ37: =SUM(CJ24:CJ35) -> 0 | CK37: =SUM(CK24:CK35) -> 0 | CM37: TOTAL | CN37: =SUM(CN24:CN35) -> 0 | CO37: =SUM(CO24:CO35) -> 0 | CP37: =SUM(CP24:CP35) -> 0 | CQ37: =SUM(CQ24:CQ35) -> 0 | CR37: =SUM(CR24:CR35) -> 0 | CT37: TOTAL | CU37: =SUM(CU24:CU35) -> 0 | CV37: =SUM(CV24:CV35) -> 0 | CW37: =SUM(CW24:CW35) -> 0 | CX37: =SUM(CX24:CX35) -> 0 | CY37: =SUM(CY24:CY35) -> 0 | DA37: TOTAL | DB37: =SUM(DB24:DB35) -> 0 | DC37: =SUM(DC24:DC35) -> 0 | DD37: =SUM(DD24:DD35) -> 0 | DE37: =SUM(DE24:DE35) -> 0 | DF37: =SUM(DF24:DF35) -> 0 | DH37: TOTAL | DI37: =SUM(DI24:DI35) -> 0 | DJ37: =SUM(DJ24:DJ35) -> 0 | DK37: =SUM(DK24:DK35) -> 0 | DL37: =SUM(DL24:DL35) -> 0 | DM37: =SUM(DM24:DM35) -> 0 | DO37: TOTAL | DP37: =SUM(DP24:DP35) -> 0 | DQ37: =SUM(DQ24:DQ35) -> 0 | DR37: =SUM(DR24:DR35) -> 0 | DS37: =SUM(DS24:DS35) -> 0 | DT37: =SUM(DT24:DT35) -> 0 | DV37: TOTAL | DW37: =SUM(DW24:DW35) -> 0 | DX37: =SUM(DX24:DX35) -> 0 | DY37: =SUM(DY24:DY35) -> 0 | DZ37: =SUM(DZ24:DZ35) -> 0 | EA37: =SUM(EA24:EA35) -> 0 | EC37: TOTAL | ED37: =SUM(ED24:ED35) -> 0 | EE37: =SUM(EE24:EE35) -> 0 | EF37: =SUM(EF24:EF35) -> 0 | EG37: =SUM(EG24:EG35) -> 0 | EH37: =SUM(EH24:EH35) -> 0 | EJ37: TOTAL | EK37: =SUM(EK24:EK35) -> 0 | EL37: =SUM(EL24:EL35) -> 0 | EM37: =SUM(EM24:EM35) -> 0 | EN37: =SUM(EN24:EN35) -> 0 | EO37: =SUM(EO24:EO35) -> 0 | EQ37: TOTAL | ER37: =SUM(ER24:ER35) -> 0 | ES37: =SUM(ES24:ES35) -> 0 | ET37: =SUM(ET24:ET35) -> 0 | EU37: =SUM(EU24:EU35) -> 0 | EV37: =SUM(EV24:EV35) -> 0
B38: 15 | C38: =IF(DL2<>"",DL2,"") | D38: =IF(DK3<>"",DK3,"")
B39: 16 | C39: =IF(DS2<>"",DS2,"") | D39: =IF(DR3<>"",DR3,"") | N39: =IF(Q18="Cliente Livre","ESTA UNIDADE CONSUMIDORA NÃO PODE CONTEMPLAR NA PROPOSTA DE PROJETO FONTE INCENTIVADA","") | U39: =IF(X18="Cliente Livre","ESTA UNIDADE CONSUMIDORA NÃO PODE CONTEMPLAR NA PROPOSTA DE PROJETO FONTE INCENTIVADA","") | AB39: =IF(AE18="Cliente Livre","ESTA UNIDADE CONSUMIDORA NÃO PODE CONTEMPLAR NA PROPOSTA DE PROJETO FONTE INCENTIVADA","") | AI39: =IF(AL18="Cliente Livre","ESTA UNIDADE CONSUMIDORA NÃO PODE CONTEMPLAR NA PROPOSTA DE PROJETO FONTE INCENTIVADA","") | AP39: =IF(AS18="Cliente Livre","ESTA UNIDADE CONSUMIDORA NÃO PODE CONTEMPLAR NA PROPOSTA DE PROJETO FONTE INCENTIVADA","") | AW39: =IF(AZ18="Cliente Livre","ESTA UNIDADE CONSUMIDORA NÃO PODE CONTEMPLAR NA PROPOSTA DE PROJETO FONTE INCENTIVADA","") | BD39: =IF(BG18="Cliente Livre","ESTA UNIDADE CONSUMIDORA NÃO PODE CONTEMPLAR NA PROPOSTA DE PROJETO FONTE INCENTIVADA","") | BK39: =IF(BN18="Cliente Livre","ESTA UNIDADE CONSUMIDORA NÃO PODE CONTEMPLAR NA PROPOSTA DE PROJETO FONTE INCENTIVADA","") | BR39: =IF(BU18="Cliente Livre","ESTA UNIDADE CONSUMIDORA NÃO PODE CONTEMPLAR NA PROPOSTA DE PROJETO FONTE INCENTIVADA","") | BY39: =IF(CB18="Cliente Livre","ESTA UNIDADE CONSUMIDORA NÃO PODE CONTEMPLAR NA PROPOSTA DE PROJETO FONTE INCENTIVADA","") | CF39: =IF(CI18="Cliente Livre","ESTA UNIDADE CONSUMIDORA NÃO PODE CONTEMPLAR NA PROPOSTA DE PROJETO FONTE INCENTIVADA","") | CM39: =IF(CP18="Cliente Livre","ESTA UNIDADE CONSUMIDORA NÃO PODE CONTEMPLAR NA PROPOSTA DE PROJETO FONTE INCENTIVADA","") | CT39: =IF(CW18="Cliente Livre","ESTA UNIDADE CONSUMIDORA NÃO PODE CONTEMPLAR NA PROPOSTA DE PROJETO FONTE INCENTIVADA","") | DA39: =IF(DD18="Cliente Livre","ESTA UNIDADE CONSUMIDORA NÃO PODE CONTEMPLAR NA PROPOSTA DE PROJETO FONTE INCENTIVADA","") | DH39: =IF(DK18="Cliente Livre","ESTA UNIDADE CONSUMIDORA NÃO PODE CONTEMPLAR NA PROPOSTA DE PROJETO FONTE INCENTIVADA","") | DO39: =IF(DR18="Cliente Livre","ESTA UNIDADE CONSUMIDORA NÃO PODE CONTEMPLAR NA PROPOSTA DE PROJETO FONTE INCENTIVADA","") | DV39: =IF(DY18="Cliente Livre","ESTA UNIDADE CONSUMIDORA NÃO PODE CONTEMPLAR NA PROPOSTA DE PROJETO FONTE INCENTIVADA","") | EC39: =IF(EF18="Cliente Livre","ESTA UNIDADE CONSUMIDORA NÃO PODE CONTEMPLAR NA PROPOSTA DE PROJETO FONTE INCENTIVADA","") | EJ39: =IF(EM18="Cliente Livre","ESTA UNIDADE CONSUMIDORA NÃO PODE CONTEMPLAR NA PROPOSTA DE PROJETO FONTE INCENTIVADA","") | EQ39: =IF(ET18="Cliente Livre","ESTA UNIDADE CONSUMIDORA NÃO PODE CONTEMPLAR NA PROPOSTA DE PROJETO FONTE INCENTIVADA","")
B40: 17 | C40: =IF(DZ2<>"",DZ2,"") | D40: =IF(DY3<>"",DY3,"")
B41: 18 | C41: =IF(EG2<>"",EG2,"") | D41: =IF(EF3<>"",EF3,"")
B42: 19 | C42: =IF(EN2<>"",EN2,"") | D42: =IF(EM3<>"",EM3,"")
B43: 20 | C43: =IF(EU2<>"",EU2,"") | D43: =IF(ET3<>"",ET3,"")

Sheet IlumCusto
B4: ILUMINAÇÃO | P4: =B4 -> ILUMINAÇÃO
B5: CUSTOS DIRETOS | P5: CUSTOS ANUALIZADOS
B6: MATERIAIS E EQUIPAMENTOS | K6: ORIGEM DOS RECURSOS | P6: MATERIAIS E EQUIPAMENTOS | X6: ORIGEM DOS RECURSOS
B7: Materiais e equipamentos | H7: Vida útil (anos) | I7: Quantidade | J7: Preço unitário | K7: PEE | L7: Terceiros | M7: Consumidor | N7: Total | P7: =B7 -> Materiais e equipamentos | V7: Vida útil | W7: FRC | X7: CAPEE | Y7: CATOTAL
B8: 1 | K8: =N8-L8-M8 -> 0 | N8: =I8*J8 -> 0 | P8: =B8 -> 1 | Q8: =IF(OR(C8=0,C8=""),"",C8) | V8: =IF(N8=0,"",H8) | W8: =IF(OR(V8="",V8=0),0,(Projeto!$AD$10*((1+Projeto!$AD$10)^V8))/(((1+Projeto!$AD$10)^V8)-1)) -> 0 | X8: =IF(AND(K8>0,CustoContábil!$F$6>0),K8*(CustoContábil!$F$18/CustoContábil!$F$6)*W8,0) -> 0 | Y8: =IF(AND(N8>0,CustoContábil!$D$6>0),N8*(CustoContábil!$D$18/CustoContábil!$D$6)*W8,0) -> 0
B9: 2 | K9: =N9-L9-M9 -> 0 | N9: =I9*J9 -> 0 | P9: =B9 -> 2 | Q9: =IF(OR(C9=0,C9=""),"",C9) | V9: =IF(N9=0,"",H9) | W9: =IF(OR(V9="",V9=0),0,(Projeto!$AD$10*((1+Projeto!$AD$10)^V9))/(((1+Projeto!$AD$10)^V9)-1)) -> 0 | X9: =IF(AND(K9>0,CustoContábil!$F$6>0),K9*(CustoContábil!$F$18/CustoContábil!$F$6)*W9,0) -> 0 | Y9: =IF(AND(N9>0,CustoContábil!$D$6>0),N9*(CustoContábil!$D$18/CustoContábil!$D$6)*W9,0) -> 0
B10: 3 | K10: =N10-L10-M10 -> 0 | N10: =I10*J10 -> 0 | P10: =B10 -> 3 | Q10: =IF(OR(C10=0,C10=""),"",C10) | V10: =IF(N10=0,"",H10) | W10: =IF(OR(V10="",V10=0),0,(Projeto!$AD$10*((1+Projeto!$AD$10)^V10))/(((1+Projeto!$AD$10)^V10)-1)) -> 0 | X10: =IF(AND(K10>0,CustoContábil!$F$6>0),K10*(CustoContábil!$F$18/CustoContábil!$F$6)*W10,0) -> 0 | Y10: =IF(AND(N10>0,CustoContábil!$D$6>0),N10*(CustoContábil!$D$18/CustoContábil!$D$6)*W10,0) -> 0
B11: 4 | K11: =N11-L11-M11 -> 0 | N11: =I11*J11 -> 0 | P11: =B11 -> 4 | Q11: =IF(OR(C11=0,C11=""),"",C11) | V11: =IF(N11=0,"",H11) | W11: =IF(OR(V11="",V11=0),0,(Projeto!$AD$10*((1+Projeto!$AD$10)^V11))/(((1+Projeto!$AD$10)^V11)-1)) -> 0 | X11: =IF(AND(K11>0,CustoContábil!$F$6>0),K11*(CustoContábil!$F$18/CustoContábil!$F$6)*W11,0) -> 0 | Y11: =IF(AND(N11>0,CustoContábil!$D$6>0),N11*(CustoContábil!$D$18/CustoContábil!$D$6)*W11,0) -> 0
B12: 5 | K12: =N12-L12-M12 -> 0 | N12: =I12*J12 -> 0 | P12: =B12 -> 5 | Q12: =IF(OR(C12=0,C12=""),"",C12) | V12: =IF(N12=0,"",H12) | W12: =IF(OR(V12="",V12=0),0,(Projeto!$AD$10*((1+Projeto!$AD$10)^V12))/(((1+Projeto!$AD$10)^V12)-1)) -> 0 | X12: =IF(AND(K12>0,CustoContábil!$F$6>0),K12*(CustoContábil!$F$18/CustoContábil!$F$6)*W12,0) -> 0 | Y12: =IF(AND(N12>0,CustoContábil!$D$6>0),N12*(CustoContábil!$D$18/CustoContábil!$D$6)*W12,0) -> 0
B13: 6 | K13: =N13-L13-M13 -> 0 | N13: =I13*J13 -> 0 | P13: =B13 -> 6 | Q13: =IF(OR(C13=0,C13=""),"",C13) | V13: =IF(N13=0,"",H13) | W13: =IF(OR(V13="",V13=0),0,(Projeto!$AD$10*((1+Projeto!$AD$10)^V13))/(((1+Projeto!$AD$10)^V13)-1)) -> 0 | X13: =IF(AND(K13>0,CustoContábil!$F$6>0),K13*(CustoContábil!$F$18/CustoContábil!$F$6)*W13,0) -> 0 | Y13: =IF(AND(N13>0,CustoContábil!$D$6>0),N13*(CustoContábil!$D$18/CustoContábil!$D$6)*W13,0) -> 0
B14: 7 | K14: =N14-L14-M14 -> 0 | N14: =I14*J14 -> 0 | P14: =B14 -> 7 | Q14: =IF(OR(C14=0,C14=""),"",C14) | V14: =IF(N14=0,"",H14) | W14: =IF(OR(V14="",V14=0),0,(Projeto!$AD$10*((1+Projeto!$AD$10)^V14))/(((1+Projeto!$AD$10)^V14)-1)) -> 0 | X14: =IF(AND(K14>0,CustoContábil!$F$6>0),K14*(CustoContábil!$F$18/CustoContábil!$F$6)*W14,0) -> 0 | Y14: =IF(AND(N14>0,CustoContábil!$D$6>0),N14*(CustoContábil!$D$18/CustoContábil!$D$6)*W14,0) -> 0
B15: 8 | K15: =N15-L15-M15 -> 0 | N15: =I15*J15 -> 0 | P15: =B15 -> 8 | Q15: =IF(OR(C15=0,C15=""),"",C15) | V15: =IF(N15=0,"",H15) | W15: =IF(OR(V15="",V15=0),0,(Projeto!$AD$10*((1+Projeto!$AD$10)^V15))/(((1+Projeto!$AD$10)^V15)-1)) -> 0 | X15: =IF(AND(K15>0,CustoContábil!$F$6>0),K15*(CustoContábil!$F$18/CustoContábil!$F$6)*W15,0) -> 0 | Y15: =IF(AND(N15>0,CustoContábil!$D$6>0),N15*(CustoContábil!$D$18/CustoContábil!$D$6)*W15,0) -> 0
B16: 9 | K16: =N16-L16-M16 -> 0 | N16: =I16*J16 -> 0 | P16: =B16 -> 9 | Q16: =IF(OR(C16=0,C16=""),"",C16) | V16: =IF(N16=0,"",H16) | W16: =IF(OR(V16="",V16=0),0,(Projeto!$AD$10*((1+Projeto!$AD$10)^V16))/(((1+Projeto!$AD$10)^V16)-1)) -> 0 | X16: =IF(AND(K16>0,CustoContábil!$F$6>0),K16*(CustoContábil!$F$18/CustoContábil!$F$6)*W16,0) -> 0 | Y16: =IF(AND(N16>0,CustoContábil!$D$6>0),N16*(CustoContábil!$D$18/CustoContábil!$D$6)*W16,0) -> 0
B17: 10 | K17: =N17-L17-M17 -> 0 | N17: =I17*J17 -> 0 | P17: =B17 -> 10 | Q17: =IF(OR(C17=0,C17=""),"",C17) | V17: =IF(N17=0,"",H17) | W17: =IF(OR(V17="",V17=0),0,(Projeto!$AD$10*((1+Projeto!$AD$10)^V17))/(((1+Projeto!$AD$10)^V17)-1)) -> 0 | X17: =IF(AND(K17>0,CustoContábil!$F$6>0),K17*(CustoContábil!$F$18/CustoContábil!$F$6)*W17,0) -> 0 | Y17: =IF(AND(N17>0,CustoContábil!$D$6>0),N17*(CustoContábil!$D$18/CustoContábil!$D$6)*W17,0) -> 0
B18: 11 | K18: =N18-L18-M18 -> 0 | N18: =I18*J18 -> 0 | P18: =B18 -> 11 | Q18: =IF(OR(C18=0,C18=""),"",C18) | V18: =IF(N18=0,"",H18) | W18: =IF(OR(V18="",V18=0),0,(Projeto!$AD$10*((1+Projeto!$AD$10)^V18))/(((1+Projeto!$AD$10)^V18)-1)) -> 0 | X18: =IF(AND(K18>0,CustoContábil!$F$6>0),K18*(CustoContábil!$F$18/CustoContábil!$F$6)*W18,0) -> 0 | Y18: =IF(AND(N18>0,CustoContábil!$D$6>0),N18*(CustoContábil!$D$18/CustoContábil!$D$6)*W18,0) -> 0
B19: 12 | K19: =N19-L19-M19 -> 0 | N19: =I19*J19 -> 0 | P19: =B19 -> 12 | Q19: =IF(OR(C19=0,C19=""),"",C19) | V19: =IF(N19=0,"",H19) | W19: =IF(OR(V19="",V19=0),0,(Projeto!$AD$10*((1+Projeto!$AD$10)^V19))/(((1+Projeto!$AD$10)^V19)-1)) -> 0 | X19: =IF(AND(K19>0,CustoContábil!$F$6>0),K19*(CustoContábil!$F$18/CustoContábil!$F$6)*W19,0) -> 0 | Y19: =IF(AND(N19>0,CustoContábil!$D$6>0),N19*(CustoContábil!$D$18/CustoContábil!$D$6)*W19,0) -> 0
... B107: 100 | K107: =N107-L107-M107 -> 0 | N107: =I107*J107 -> 0 | P107: =B107 -> 100 | Q107: =IF(OR(C107=0,C107=""),"",C107) | V107: =IF(N107=0,"",H107) | W107: =IF(OR(V107="",V107=0),0,(Projeto!$AD$10*((1+Projeto!$AD$10)^V107))/(((1+Projeto!$AD$10)^V107)-1)) -> 0 | X107: =IF(AND(K107>0,CustoContábil!$F$6>0),K107*(CustoContábil!$F$18/CustoContábil!$F$6)*W107,0) -> 0 | Y107: =IF(AND(N107>0,CustoContábil!$D$6>0),N107*(CustoContábil!$D$18/CustoContábil!$D$6)*W107,0) -> 0
C108: Materiais e equipamentos | K108: =SUM(K8:K107) -> 0 | L108: =SUM(L8:L107) -> 0 | M108: =SUM(M8:M107) -> 0 | N108: =SUM(N8:N107) -> 0 | V108: Custo anualizado total - Iluminação | W108: CAT ILUM | X108: =SUM(X8:X107) -> 0 | Y108: =SUM(Y8:Y107) -> 0
B109: MÃO DE OBRA E ADMINISTRAÇÃO PRÓPRIA - CEMIG | K109: ORIGEM DOS RECURSOS
C110: Mão de obra própria - CEMIG | K110: =Apoio!AY4 -> 0 | N110: =K110 -> 0 | Q110: RCBILUM_PEE | R110: =RCB!$G$9 -> 0
C111: Auditoria Contábil e Financeira - CEMIG | K111: =Apoio!BH4 -> 0 | N111: =K111 -> 0 | Q111: RCBPEE | R111: =RCB!$H$9 -> 0
B112: Mão de obra de terceiros | I112: Quantidade | J112: Preço unitário | K112: PEE | L112: Terceiros | M112: Consumidor | N112: Total
B113: 1 | C113: Diagnóstico Energético - Rateio | K113: =Terceiros!K14 -> 0 | L113: =Terceiros!L14 -> 0 | M113: =Terceiros!M14 -> 0 | N113: =Terceiros!N14 -> 0
B114: 2 | C114: Gerenciamento do Projeto - Rateio | K114: =Terceiros!K25 -> 0 | L114: =Terceiros!L25 -> 0 | M114: =Terceiros!M25 -> 0 | N114: =Terceiros!N25 -> 0
B115: 3 | C115: Relatório Final - Rateio | K115: =Terceiros!K36 -> 0 | L115: =Terceiros!L36 -> 0 | M115: =Terceiros!M36 -> 0 | N115: =Terceiros!N36 -> 0
B116: 4 | K116: =N116-L116-M116 -> 0 | N116: =I116*J116 -> 0
B117: 5 | K117: =N117-L117-M117 -> 0 | N117: =I117*J117 -> 0
B118: 6 | K118: =N118-L118-M118 -> 0 | N118: =I118*J118 -> 0
B119: 7 | K119: =N119-L119-M119 -> 0 | N119: =I119*J119 -> 0
B120: 8 | K120: =N120-L120-M120 -> 0 | N120: =I120*J120 -> 0
B121: 9 | K121: =N121-L121-M121 -> 0 | N121: =I121*J121 -> 0
B122: 10 | K122: =N122-L122-M122 -> 0 | N122: =I122*J122 -> 0
B123: 11 | K123: =N123-L123-M123 -> 0 | N123: =I123*J123 -> 0
B124: 12 | K124: =N124-L124-M124 -> 0 | N124: =I124*J124 -> 0
B125: 13 | K125: =N125-L125-M125 -> 0 | N125: =I125*J125 -> 0
B126: 14 | K126: =N126-L126-M126 -> 0 | N126: =I126*J126 -> 0
B127: 15 | K127: =N127-L127-M127 -> 0 | N127: =I127*J127 -> 0
... B132: 20 | K132: =N132-L132-M132 -> 0 | N132: =I132*J132 -> 0
C133: Mão de obra de terceiros | K133: =SUM(K113:K132) -> 0 | L133: =SUM(L113:L132) -> 0 | M133: =SUM(M113:M132) -> 0 | N133: =SUM(N113:N132) -> 0
C134: Administração Própria - CEMIG | K134: =Apoio!BE4 -> 0 | N134: =K134 -> 0
J135: Sub total - Mão de obra de terceiros e Administração Própria CEMIG | K135: =SUM(K110,K111,K133,K134) -> 0 | L135: =L133 -> 0 | M135: =M133 -> 0 | N135: =SUM(N110,N111,N133,N134) -> 0
J136: Sub total - Custos diretos | K136: =SUM(K108,K135) -> 0 | L136: =SUM(L108,L135) -> 0 | M136: =SUM(M108,M135) -> 0 | N136: =SUM(N108,N135) -> 0
B137: CUSTOS INDIRETOS
B138: CUSTOS INDIRETOS | K138: ORIGEM DOS RECURSOS
C139: Marketing | K139: =Marketing!K30 -> 0 | L139: =Marketing!L30 -> 0 | M139: =Marketing!M30 -> 0 | N139: =Marketing!N30 -> 0
C140: Treinamento e capacitação | K140: =Treinamento!K30 -> 0 | L140: =Treinamento!L30 -> 0 | M140: =Treinamento!M30 -> 0 | N140: =Treinamento!N30 -> 0
B141: Descarte de materiais | I141: Quantidade | J141: Preço unitário | K141: PEE | L141: Terceiros | M141: Consumidor | N141: Total
B142: 1 | K142: =N142-L142-M142 -> 0 | N142: =I142*J142 -> 0
B143: 2 | K143: =N143-L143-M143 -> 0 | N143: =I143*J143 -> 0
B144: 3 | K144: =N144-L144-M144 -> 0 | N144: =I144*J144 -> 0
B145: 4 | K145: =N145-L145-M145 -> 0 | N145: =I145*J145 -> 0
B146: 5 | K146: =N146-L146-M146 -> 0 | N146: =I146*J146 -> 0
B147: 6 | K147: =N147-L147-M147 -> 0 | N147: =I147*J147 -> 0
B148: 7 | K148: =N148-L148-M148 -> 0 | N148: =I148*J148 -> 0
B149: 8 | K149: =N149-L149-M149 -> 0 | N149: =I149*J149 -> 0
B150: 9 | K150: =N150-L150-M150 -> 0 | N150: =I150*J150 -> 0
B151: 10 | K151: =N151-L151-M151 -> 0 | N151: =I151*J151 -> 0
B152: 11 | K152: =N152-L152-M152 -> 0 | N152: =I152*J152 -> 0
B153: 12 | K153: =N153-L153-M153 -> 0 | N153: =I153*J153 -> 0
... B161: 20 | K161: =N161-L161-M161 -> 0 | N161: =I161*J161 -> 0
C162: Descarte de materiais | K162: =SUM(K142:K161) -> 0 | L162: =SUM(L142:L161) -> 0 | M162: =SUM(M142:M161) -> 0 | N162: =SUM(N142:N161) -> 0
C163: Medição e verificação | K163: ='M&V'!J17 -> 0 | L163: ='M&V'!K17 -> 0 | M163: ='M&V'!L17 -> 0 | N163: ='M&V'!M17 -> 0
J164: Sub total - Custos indiretos | K164: =SUM(K139,K140,K162,K163) -> 0 | L164: =SUM(L139,L140,L162,L163) -> 0 | M164: =SUM(M139,M140,M162,M163) -> 0 | N164: =SUM(N139,N140,N162,N163) -> 0
J165: Custos Totais - Iluminação | K165: =SUM(K136,K164) -> 0 | L165: =SUM(L136,L164) -> 0 | M165: =SUM(M136,M164) -> 0 | N165: =SUM(N136,N164) -> 0

Sheet IlumBenef
B4: ILUMINAÇÃO - SISTEMA ATUAL
B5: 0 | G5: TOTAL | H5: ilumin1 | I5: ilumin2 | J5: ilumin3 | K5: ilumin4 | L5: ilumin5 | M5: ilumin6 | N5: ilumin7 | O5: ilumin8 | P5: ilumin9 | Q5: ilumin10 | R5: ilumin11 | S5: ilumin12 | T5: ilumin13 | U5: ilumin14 | V5: ilumin15 | W5: ilumin16 | X5: ilumin17 | Y5: ilumin18 | Z5: ilumin19 | AA5: ilumin20 | AB5: ilumin21 | AC5: ilumin22 | AD5: ilumin23 | AE5: ilumin24 | AF5: ilumin25 | AG5: ilumin26 | AH5: ilumin27 | AI5: ilumin28 | AJ5: ilumin29 | AK5: ilumin30 | AL5: ilumin31 | AM5: ilumin32 | AN5: ilumin33 | AO5: ilumin34 | AP5: ilumin35 | AQ5: ilumin36 | AR5: ilumin37 | AS5: ilumin38 | AT5: ilumin39 | AU5: ilumin40 | AV5: ilumin41 | AW5: ilumin42 | AX5: ilumin43 | AY5: ilumin44 | AZ5: ilumin45 | BA5: ilumin46 | BB5: ilumin47 | BC5: ilumin48 | BD5: ilumin49 | BE5: ilumin50 | BF5: ilumin51 | BG5: ilumin52 | BH5: ilumin53 | BI5: ilumin54 | BJ5: ilumin55 | BK5: ilumin56 | BL5: ilumin57 | BM5: ilumin58 | BN5: ilumin59 | BO5: ilumin60 | BP5: ilumin61 | BQ5: ilumin62 | BR5: ilumin63 | BS5: ilumin64 | BT5: ilumin65 | BU5: ilumin66 | BV5: ilumin67 | BW5: ilumin68 | BX5: ilumin69 | BY5: ilumin70 | BZ5: ilumin71 | CA5: ilumin72 | CB5: ilumin73 | CC5: ilumin74 | CD5: ilumin75 | CE5: ilumin76 | CF5: ilumin77 | CG5: ilumin78 | CH5: ilumin79 | CI5: ilumin80 | CJ5: ilumin81 | CK5: ilumin82 | CL5: ilumin83 | CM5: ilumin84 | CN5: ilumin85 | CO5: ilumin86 | CP5: ilumin87 | CQ5: ilumin88 | CR5: ilumin89 | CS5: ilumin90 | CT5: ilumin91 | CU5: ilumin92 | CV5: ilumin93 | CW5: ilumin94 | CX5: ilumin95 | CY5: ilumin96 | CZ5: ilumin97 | DA5: ilumin98 | DB5: ilumin99 | DC5: ilumin100 | DD5: ilumin101 | DE5: ilumin102 | DF5: ilumin103 | DG5: ilumin104 | DH5: ilumin105 | DI5: ilumin106 | DJ5: ilumin107 | DK5: ilumin108 | DL5: ilumin109 | DM5: ilumin110 | DN5: ilumin111 | DO5: ilumin112 | DP5: ilumin113 | DQ5: ilumin114 | DR5: ilumin115 | DS5: ilumin116 | DT5: ilumin117 | DU5: ilumin118 | DV5: ilumin119 | DW5: ilumin120 | DX5: ilumin121 | DY5: ilumin122 | DZ5: ilumin123 | EA5: ilumin124 | EB5: ilumin125 | EC5: ilumin126 | ED5: ilumin127 | EE5: ilumin128 | EF5: ilumin129 | EG5: ilumin130 | EH5: ilumin131 | EI5: ilumin132 | EJ5: ilumin133 | EK5: ilumin134 | EL5: ilumin135 | EM5: ilumin136 | EN5: ilumin137 | EO5: ilumin138 | EP5: ilumin139 | EQ5: ilumin140 | ER5: ilumin141 | ES5: ilumin142 | ET5: ilumin143 | EU5: ilumin144 | EV5: ilumin145 | EW5: ilumin146 | EX5: ilumin147 | EY5: ilumin148 | EZ5: ilumin149 | FA5: ilumin150
B6: 1 | C6: Unidade Consumidora
B7: 2 | C7: Tipo de equipamento / tecnologia
C8: Quantidade de luminárias | G8: =IF(COUNTA(H8:FA8)=0,"",IF(SMALL(H8:FA8,1)<0,"ERRO",SUM(H8:FA8)))
B9: =B7+1 -> 3 | C9: Lâmpadas | D9: Potência | E9: W | F9: plai | G9: =IF(COUNTA(H9:FA9)=0,"",IF(SMALL(H9:FA9,1)<0,"ERRO",""))
D10: Quantidade | F10: qlai | G10: =IF(COUNTA(H10:FA10)=0,"",IF(SMALL(H10:FA10,1)<0,"ERRO",SUM(H10:FA10)))
B11: =B9+1 -> 4 | C11: Reatores | D11: Potência | E11: W | F11: prai | G11: =IF(COUNTA(H11:FA11)=0,"",IF(SMALL(H11:FA11,1)<0,"ERRO",""))
D12: Quantidade | F12: qrai | G12: =IF(COUNTA(H12:FA12)=0,"",IF(SMALL(H12:FA12,1)<0,"ERRO",SUM(H12:FA12)))
B13: =B11+1 -> 5 | C13: Potência instalada | E13: kW | F13: Pai | G13: =SUM(H13:FA13) -> 0 | H13: =(H9*H10+H11*H12)/1000 -> 0 | I13: =(I9*I10+I11*I12)/1000 -> 0 | J13: =(J9*J10+J11*J12)/1000 -> 0 | K13: =(K9*K10+K11*K12)/1000 -> 0 | L13: =(L9*L10+L11*L12)/1000 -> 0 | M13: =(M9*M10+M11*M12)/1000 -> 0 | N13: =(N9*N10+N11*N12)/1000 -> 0 | O13: =(O9*O10+O11*O12)/1000 -> 0 | ... FA13: =(FA9*FA10+FA11*FA12)/1000 -> 0
B14: =B13+1 -> 6 | C14: Tempo de utilização do sistema, em um dia | E14: h/dia | G14: =IF(COUNTA(H14:FA14)=0,"",IF(OR(LARGE(H14:FA14,1)>24,SMALL(H14:FA14,1)<0),"ERRO",""))
C15: Dias de utilização do sistema, em um ano | E15: dia/ano | G15: =IF(COUNTA(H15:FA15)=0,"",IF(OR(LARGE(H15:FA15,1)>365,SMALL(H15:FA15,1)<0),"ERRO",""))
C16: Funcionamento | E16: h/ano | F16: hai | G16: =IF(COUNTA(H16:FA16)=0,"",IF(OR(LARGE(H16:FA16,1)>8760,SMALL(H16:FA16,1)<0),"ERRO","")) | H16: =H14*H15 -> 0 | I16: =I14*I15 -> 0 | J16: =J14*J15 -> 0 | K16: =K14*K15 -> 0 | L16: =L14*L15 -> 0 | M16: =M14*M15 -> 0 | N16: =N14*N15 -> 0 | O16: =O14*O15 -> 0 | ... FA16: =FA14*FA15 -> 0
B17: =B14+1 -> 7 | C17: Horas de utilização em horário de ponta, em um dia | E17: h/dia | F17: nupai | G17: =IF(COUNTA(H17:FA17)=0,"",IF(OR(LARGE(H17:FA17,1)>3,SMALL(H17:FA17,1)<0),"ERRO",""))
C18: Dias úteis de utilização em horário de ponta, em um mês | E18: dia/mês | F18: ndai | G18: =IF(COUNTA(H18:FA18)=0,"",IF(OR(LARGE(H18:FA18,1)>22,SMALL(H18:FA18,1)<0),"ERRO",""))
C19: Meses de utilização em horário de ponta, em um ano | E19: mês/ano | F19: nmai | G19: =IF(COUNTA(H19:FA19)=0,"",IF(OR(LARGE(H19:FA19,1)>12,SMALL(H19:FA19,1)<0),"ERRO",""))
C20: Potência média na ponta | E20: kW | F20: dai | G20: =SUM(H20:FA20) -> 0 | H20: =H13*((H17*H18*H19)/792) -> 0 | I20: =I13*((I17*I18*I19)/792) -> 0 | J20: =J13*((J17*J18*J19)/792) -> 0 | K20: =K13*((K17*K18*K19)/792) -> 0 | L20: =L13*((L17*L18*L19)/792) -> 0 | M20: =M13*((M17*M18*M19)/792) -> 0 | N20: =N13*((N17*N18*N19)/792) -> 0 | O20: =O13*((O17*O18*O19)/792) -> 0 | ... FA20: =FA13*((FA17*FA18*FA19)/792) -> 0
C21: Fator de coincidência na ponta | F21: FCPai | G21: =IF(COUNTA(H21:FA21)=0,"",IF(OR(LARGE(H21:FA21,1)>1,SMALL(H21:FA21,1)<0),"ERRO","")) | H21: =IF(H13=0,0,H20/H13) -> 0 | I21: =IF(I13=0,0,I20/I13) -> 0 | J21: =IF(J13=0,0,J20/J13) -> 0 | K21: =IF(K13=0,0,K20/K13) -> 0 | L21: =IF(L13=0,0,L20/L13) -> 0 | M21: =IF(M13=0,0,M20/M13) -> 0 | N21: =IF(N13=0,0,N20/N13) -> 0 | O21: =IF(O13=0,0,O20/O13) -> 0 | ... FA21: =IF(FA13=0,0,FA20/FA13) -> 0
B22: =B17+1 -> 8 | C22: Energia consumida | E22: MWh/ano | F22: Eai | G22: =SUM(H22:FA22) -> 0 | H22: =(H13*H16)/1000 -> 0 | I22: =(I13*I16)/1000 -> 0 | J22: =(J13*J16)/1000 -> 0 | K22: =(K13*K16)/1000 -> 0 | L22: =(L13*L16)/1000 -> 0 | M22: =(M13*M16)/1000 -> 0 | N22: =(N13*N16)/1000 -> 0 | O22: =(O13*O16)/1000 -> 0 | ... FA22: =(FA13*FA16)/1000 -> 0
B23: =B22+1 -> 9 | C23: Demanda média na ponta | E23: kW | F23: Dai | G23: =SUM(H23:FA23) -> 0 | H23: =H13*H21 -> 0 | I23: =I13*I21 -> 0 | J23: =J13*J21 -> 0 | K23: =K13*K21 -> 0 | L23: =L13*L21 -> 0 | M23: =M13*M21 -> 0 | N23: =N13*N21 -> 0 | O23: =O13*O21 -> 0 | ... FA23: =FA13*FA21 -> 0
B25: ILUMINAÇÃO - SISTEMA PROPOSTO
G26: TOTAL | H26: ilumin 1 | I26: ilumin 2 | J26: ilumin 3 | K26: ilumin 4 | L26: ilumin 5 | M26: ilumin 6 | N26: ilumin 7 | O26: ilumin 8 | P26: ilumin 9 | Q26: ilumin 10 | R26: ilumin 11 | S26: ilumin 12 | T26: ilumin 13 | U26: ilumin 14 | V26: ilumin 15 | W26: ilumin 16 | X26: ilumin 17 | Y26: ilumin 18 | Z26: ilumin 19 | AA26: ilumin 20 | AB26: ilumin 21 | AC26: ilumin 22 | AD26: ilumin 23 | AE26: ilumin 24 | AF26: ilumin 25 | AG26: ilumin 26 | AH26: ilumin 27 | AI26: ilumin 28 | AJ26: ilumin 29 | AK26: ilumin 30 | AL26: ilumin 31 | AM26: ilumin 32 | AN26: ilumin 33 | AO26: ilumin 34 | AP26: ilumin 35 | AQ26: ilumin 36 | AR26: ilumin 37 | AS26: ilumin 38 | AT26: ilumin 39 | AU26: ilumin 40 | AV26: ilumin 41 | AW26: ilumin 42 | AX26: ilumin 43 | AY26: ilumin 44 | AZ26: ilumin 45 | BA26: ilumin 46 | BB26: ilumin 47 | BC26: ilumin 48 | BD26: ilumin 49 | BE26: ilumin 50 | BF26: ilumin 51 | BG26: ilumin 52 | BH26: ilumin 53 | BI26: ilumin 54 | BJ26: ilumin 55 | BK26: ilumin 56 | BL26: ilumin 57 | BM26: ilumin 58 | BN26: ilumin 59 | BO26: ilumin 60 | BP26: ilumin 61 | BQ26: ilumin 62 | BR26: ilumin 63 | BS26: ilumin 64 | BT26: ilumin 65 | BU26: ilumin 66 | BV26: ilumin 67 | BW26: ilumin 68 | BX26: ilumin 69 | BY26: ilumin 70 | BZ26: ilumin 71 | CA26: ilumin 72 | CB26: ilumin 73 | CC26: ilumin 74 | CD26: ilumin 75 | CE26: ilumin 76 | CF26: ilumin 77 | CG26: ilumin 78 | CH26: ilumin 79 | CI26: ilumin 80 | CJ26: ilumin 81 | CK26: ilumin 82 | CL26: ilumin 83 | CM26: ilumin 84 | CN26: ilumin 85 | CO26: ilumin 86 | CP26: ilumin 87 | CQ26: ilumin 88 | CR26: ilumin 89 | CS26: ilumin 90 | CT26: ilumin 91 | CU26: ilumin 92 | CV26: ilumin 93 | CW26: ilumin 94 | CX26: ilumin 95 | CY26: ilumin 96 | CZ26: ilumin 97 | DA26: ilumin 98 | DB26: ilumin 99 | DC26: ilumin 100 | DD26: ilumin 101 | DE26: ilumin 102 | DF26: ilumin 103 | DG26: ilumin 104 | DH26: ilumin 105 | DI26: ilumin 106 | DJ26: ilumin 107 | DK26: ilumin 108 | DL26: ilumin 109 | DM26: ilumin 110 | DN26: ilumin 111 | DO26: ilumin 112 | DP26: ilumin 113 | DQ26: ilumin 114 | DR26: ilumin 115 | DS26: ilumin 116 | DT26: ilumin 117 | DU26: ilumin 118 | DV26: ilumin 119 | DW26: ilumin 120 | DX26: ilumin 121 | DY26: ilumin 122 | DZ26: ilumin 123 | EA26: ilumin 124 | EB26: ilumin 125 | EC26: ilumin 126 | ED26: ilumin 127 | EE26: ilumin 128 | EF26: ilumin 129 | EG26: ilumin 130 | EH26: ilumin 131 | EI26: ilumin 132 | EJ26: ilumin 133 | EK26: ilumin 134 | EL26: ilumin 135 | EM26: ilumin 136 | EN26: ilumin 137 | EO26: ilumin 138 | EP26: ilumin 139 | EQ26: ilumin 140 | ER26: ilumin 141 | ES26: ilumin 142 | ET26: ilumin 143 | EU26: ilumin 144 | EV26: ilumin 145 | EW26: ilumin 146 | EX26: ilumin 147 | EY26: ilumin 148 | EZ26: ilumin 149 | FA26: ilumin 150
B27: =B23+1 -> 10 | C27: Unidade Consumidora | H27: =IF(H6="","",H6) | I27: =IF(I6="","",I6) | J27: =IF(J6="","",J6) | K27: =IF(K6="","",K6) | L27: =IF(L6="","",L6) | M27: =IF(M6="","",M6) | N27: =IF(N6="","",N6) | O27: =IF(O6="","",O6) | ... FA27: =IF(FA6="","",FA6)
B28: =B27+1 -> 11 | C28: Tipo de equipamento / tecnologia
C29: Quantidade de luminárias | G29: =IF(COUNTA(H29:FA29)=0,"",IF(SMALL(H29:FA29,1)<0,"ERRO",SUM(H29:FA29)))
B30: =B28+1 -> 12 | C30: Lâmpadas | D30: Potência | E30: W | F30: plpi | G30: =IF(COUNTA(H30:FA30)=0,"",IF(SMALL(H30:FA30,1)<0,"ERRO",""))
D31: Quantidade | F31: qlpi | G31: =IF(COUNTA(H31:FA31)=0,"",IF(SMALL(H31:FA31,1)<0,"ERRO",SUM(H31:FA31)))
B32: =B30+1 -> 13 | C32: Reatores | D32: Potência | E32: W | F32: prpi | G32: =IF(COUNTA(H32:FA32)=0,"",IF(SMALL(H32:FA32,1)<0,"ERRO",""))
D33: Quantidade | F33: qrpi | G33: =IF(COUNTA(H33:FA33)=0,"",IF(SMALL(H33:FA33,1)<0,"ERRO",SUM(H33:FA33)))
B34: =B32+1 -> 14 | C34: Potência instalada | E34: kW | F34: Ppi | G34: =SUM(H34:FA34) -> 0 | H34: =(H30*H31+H32*H33)/1000 -> 0 | I34: =(I30*I31+I32*I33)/1000 -> 0 | J34: =(J30*J31+J32*J33)/1000 -> 0 | K34: =(K30*K31+K32*K33)/1000 -> 0 | L34: =(L30*L31+L32*L33)/1000 -> 0 | M34: =(M30*M31+M32*M33)/1000 -> 0 | N34: =(N30*N31+N32*N33)/1000 -> 0 | O34: =(O30*O31+O32*O33)/1000 -> 0 | ... FA34: =(FA30*FA31+FA32*FA33)/1000 -> 0
B35: =B34+1 -> 15 | C35: Tempo de utilização do sistema, em um dia | E35: h/dia | G35: =IF(COUNTA(H35:FA35)=0,"",IF(OR(LARGE(H35:FA35,1)>24,SMALL(H35:FA35,1)<0),"ERRO",""))
C36: Dias de utilização do sistema, em um ano | E36: dia/ano | G36: =IF(COUNTA(H36:FA36)=0,"",IF(OR(LARGE(H36:FA36,1)>365,SMALL(H36:FA36,1)<0),"ERRO",""))
C37: Funcionamento | E37: h/ano | F37: hpi | G37: =IF(COUNTA(H37:FA37)=0,"",IF(OR(LARGE(H37:FA37,1)>8760,SMALL(H37:FA37,1)<0),"ERRO","")) | H37: =H35*H36 -> 0 | I37: =I35*I36 -> 0 | J37: =J35*J36 -> 0 | K37: =K35*K36 -> 0 | L37: =L35*L36 -> 0 | M37: =M35*M36 -> 0 | N37: =N35*N36 -> 0 | O37: =O35*O36 -> 0 | ... FA37: =FA35*FA36 -> 0
B38: =B35+1 -> 16 | C38: Horas de utilização em horário de ponta, em um dia | E38: h/dia | F38: nuppi | G38: =IF(COUNTA(H38:FA38)=0,"",IF(OR(LARGE(H38:FA38,1)>3,SMALL(H38:FA38,1)<0),"ERRO",""))
C39: Dias úteis de utilização em horário de ponta, em um mês | E39: dia/mês | F39: ndpi | G39: =IF(COUNTA(H39:FA39)=0,"",IF(OR(LARGE(H39:FA39,1)>22,SMALL(H39:FA39,1)<0),"ERRO",""))
C40: Meses de utilização em horário de ponta, em um ano | E40: mês/ano | F40: nmpi | G40: =IF(COUNTA(H40:FA40)=0,"",IF(OR(LARGE(H40:FA40,1)>12,SMALL(H40:FA40,1)<0),"ERRO",""))
C41: Potência média na ponta | E41: kW | F41: dpi | G41: =SUM(H41:FA41) -> 0 | H41: =H34*((H38*H39*H40)/792) -> 0 | I41: =I34*((I38*I39*I40)/792) -> 0 | J41: =J34*((J38*J39*J40)/792) -> 0 | K41: =K34*((K38*K39*K40)/792) -> 0 | L41: =L34*((L38*L39*L40)/792) -> 0 | M41: =M34*((M38*M39*M40)/792) -> 0 | N41: =N34*((N38*N39*N40)/792) -> 0 | O41: =O34*((O38*O39*O40)/792) -> 0 | ... FA41: =FA34*((FA38*FA39*FA40)/792) -> 0
C42: Fator de coincidência na ponta | F42: FCPpi | G42: =IF(COUNTA(H42:FA42)=0,"",IF(OR(LARGE(H42:FA42,1)>1,SMALL(H42:FA42,1)<0),"ERRO","")) | H42: =IF(H34=0,0,H41/H34) -> 0 | I42: =IF(I34=0,0,I41/I34) -> 0 | J42: =IF(J34=0,0,J41/J34) -> 0 | K42: =IF(K34=0,0,K41/K34) -> 0 | L42: =IF(L34=0,0,L41/L34) -> 0 | M42: =IF(M34=0,0,M41/M34) -> 0 | N42: =IF(N34=0,0,N41/N34) -> 0 | O42: =IF(O34=0,0,O41/O34) -> 0 | ... FA42: =IF(FA34=0,0,FA41/FA34) -> 0
B43: =B38+1 -> 17 | C43: Energia consumida | E43: MWh/ano | F43: Epi | G43: =SUM(H43:FA43) -> 0 | H43: =(H34*H37)/1000 -> 0 | I43: =(I34*I37)/1000 -> 0 | J43: =(J34*J37)/1000 -> 0 | K43: =(K34*K37)/1000 -> 0 | L43: =(L34*L37)/1000 -> 0 | M43: =(M34*M37)/1000 -> 0 | N43: =(N34*N37)/1000 -> 0 | O43: =(O34*O37)/1000 -> 0 | ... FA43: =(FA34*FA37)/1000 -> 0
B44: =B43+1 -> 18 | C44: Demanda média na ponta | E44: kW | F44: Dpi | G44: =SUM(H44:FA44) -> 0 | H44: =H34*H42 -> 0 | I44: =I34*I42 -> 0 | J44: =J34*J42 -> 0 | K44: =K34*K42 -> 0 | L44: =L34*L42 -> 0 | M44: =M34*M42 -> 0 | N44: =N34*N42 -> 0 | O44: =O34*O42 -> 0 | ... FA44: =FA34*FA42 -> 0
B46: ILUMINAÇÃO - RESULTADOS ESPERADOS
G47: TOTAL | H47: ilumin 1 | I47: ilumin 2 | J47: ilumin 3 | K47: ilumin 4 | L47: ilumin 5 | M47: ilumin 6 | N47: ilumin 7 | O47: ilumin 8 | P47: ilumin 9 | Q47: ilumin 10 | R47: ilumin 11 | S47: ilumin 12 | T47: ilumin 13 | U47: ilumin 14 | V47: ilumin 15 | W47: ilumin 16 | X47: ilumin 17 | Y47: ilumin 18 | Z47: ilumin 19 | AA47: ilumin 20 | AB47: ilumin 21 | AC47: ilumin 22 | AD47: ilumin 23 | AE47: ilumin 24 | AF47: ilumin 25 | AG47: ilumin 26 | AH47: ilumin 27 | AI47: ilumin 28 | AJ47: ilumin 29 | AK47: ilumin 30 | AL47: ilumin 31 | AM47: ilumin 32 | AN47: ilumin 33 | AO47: ilumin 34 | AP47: ilumin 35 | AQ47: ilumin 36 | AR47: ilumin 37 | AS47: ilumin 38 | AT47: ilumin 39 | AU47: ilumin 40 | AV47: ilumin 41 | AW47: ilumin 42 | AX47: ilumin 43 | AY47: ilumin 44 | AZ47: ilumin 45 | BA47: ilumin 46 | BB47: ilumin 47 | BC47: ilumin 48 | BD47: ilumin 49 | BE47: ilumin 50 | BF47: ilumin 51 | BG47: ilumin 52 | BH47: ilumin 53 | BI47: ilumin 54 | BJ47: ilumin 55 | BK47: ilumin 56 | BL47: ilumin 57 | BM47: ilumin 58 | BN47: ilumin 59 | BO47: ilumin 60 | BP47: ilumin 61 | BQ47: ilumin 62 | BR47: ilumin 63 | BS47: ilumin 64 | BT47: ilumin 65 | BU47: ilumin 66 | BV47: ilumin 67 | BW47: ilumin 68 | BX47: ilumin 69 | BY47: ilumin 70 | BZ47: ilumin 71 | CA47: ilumin 72 | CB47: ilumin 73 | CC47: ilumin 74 | CD47: ilumin 75 | CE47: ilumin 76 | CF47: ilumin 77 | CG47: ilumin 78 | CH47: ilumin 79 | CI47: ilumin 80 | CJ47: ilumin 81 | CK47: ilumin 82 | CL47: ilumin 83 | CM47: ilumin 84 | CN47: ilumin 85 | CO47: ilumin 86 | CP47: ilumin 87 | CQ47: ilumin 88 | CR47: ilumin 89 | CS47: ilumin 90 | CT47: ilumin 91 | CU47: ilumin 92 | CV47: ilumin 93 | CW47: ilumin 94 | CX47: ilumin 95 | CY47: ilumin 96 | CZ47: ilumin 97 | DA47: ilumin 98 | DB47: ilumin 99 | DC47: ilumin 100 | DD47: ilumin 101 | DE47: ilumin 102 | DF47: ilumin 103 | DG47: ilumin 104 | DH47: ilumin 105 | DI47: ilumin 106 | DJ47: ilumin 107 | DK47: ilumin 108 | DL47: ilumin 109 | DM47: ilumin 110 | DN47: ilumin 111 | DO47: ilumin 112 | DP47: ilumin 113 | DQ47: ilumin 114 | DR47: ilumin 115 | DS47: ilumin 116 | DT47: ilumin 117 | DU47: ilumin 118 | DV47: ilumin 119 | DW47: ilumin 120 | DX47: ilumin 121 | DY47: ilumin 122 | DZ47: ilumin 123 | EA47: ilumin 124 | EB47: ilumin 125 | EC47: ilumin 126 | ED47: ilumin 127 | EE47: ilumin 128 | EF47: ilumin 129 | EG47: ilumin 130 | EH47: ilumin 131 | EI47: ilumin 132 | EJ47: ilumin 133 | EK47: ilumin 134 | EL47: ilumin 135 | EM47: ilumin 136 | EN47: ilumin 137 | EO47: ilumin 138 | EP47: ilumin 139 | EQ47: ilumin 140 | ER47: ilumin 141 | ES47: ilumin 142 | ET47: ilumin 143 | EU47: ilumin 144 | EV47: ilumin 145 | EW47: ilumin 146 | EX47: ilumin 147 | EY47: ilumin 148 | EZ47: ilumin 149 | FA47: ilumin 150
B48: =B44+1 -> 19 | C48: Redução de demanda na ponta | E48: kW | F48: RDPi | G48: =SUM(H48:FA48) -> 0 | H48: =H23-H44 -> 0 | I48: =I23-I44 -> 0 | J48: =J23-J44 -> 0 | K48: =K23-K44 -> 0 | L48: =L23-L44 -> 0 | M48: =M23-M44 -> 0 | N48: =N23-N44 -> 0 | O48: =O23-O44 -> 0 | ... FA48: =FA23-FA44 -> 0
B49: =B48+1 -> 20 | C49: Custo evitado de demanda (CED) = | D49: =Projeto!$L$44 -> 0 | E49: % | F49: RDPi% | G49: =IF(G23=0,0,G48/G23) -> 0 | H49: =IF(H23=0,0,H48/H23) -> 0 | I49: =IF(I23=0,0,I48/I23) -> 0 | J49: =IF(J23=0,0,J48/J23) -> 0 | K49: =IF(K23=0,0,K48/K23) -> 0 | L49: =IF(L23=0,0,L48/L23) -> 0 | M49: =IF(M23=0,0,M48/M23) -> 0 | N49: =IF(N23=0,0,N48/N23) -> 0 | ... FA49: =IF(FA23=0,0,FA48/FA23) -> 0
B50: =B49+1 -> 21 | C50: Energia economizada | E50: MWh/ano | F50: EEi | G50: =SUM(H50:FA50) -> 0 | H50: =H22-H43 -> 0 | I50: =I22-I43 -> 0 | J50: =J22-J43 -> 0 | K50: =K22-K43 -> 0 | L50: =L22-L43 -> 0 | M50: =M22-M43 -> 0 | N50: =N22-N43 -> 0 | O50: =O22-O43 -> 0 | ... FA50: =FA22-FA43 -> 0
B51: =B50+1 -> 22 | C51: Custo da energia evitada (CEE) = | D51: =Projeto!$L$43 -> 0 | E51: % | F51: EEi% | G51: =IF(G22=0,0,G50/G22) -> 0 | H51: =IF(H22=0,0,H50/H22) -> 0 | I51: =IF(I22=0,0,I50/I22) -> 0 | J51: =IF(J22=0,0,J50/J22) -> 0 | K51: =IF(K22=0,0,K50/K22) -> 0 | L51: =IF(L22=0,0,L50/L22) -> 0 | M51: =IF(M22=0,0,M50/M22) -> 0 | N51: =IF(N22=0,0,N50/N22) -> 0 | ... FA51: =IF(FA22=0,0,FA50/FA22) -> 0
C52: Benefício anualizado - Iluminação | E52: R$ | F52: BILUM | G52: =SUM(H52:FA52) -> 0 | H52: =H48*$D$49+H50*$D$51 -> 0 | I52: =I48*$D$49+I50*$D$51 -> 0 | J52: =J48*$D$49+J50*$D$51 -> 0 | K52: =K48*$D$49+K50*$D$51 -> 0 | L52: =L48*$D$49+L50*$D$51 -> 0 | M52: =M48*$D$49+M50*$D$51 -> 0 | N52: =N48*$D$49+N50*$D$51 -> 0 | O52: =O48*$D$49+O50*$D$51 -> 0 | ... FA52: =FA48*$D$49+FA50*$D$51 -> 0
F54: RCBILUM_PEE | G54: =RCB!$G$9 -> 0
F55: RCBPEE | G55: =RCB!$H$9 -> 0

Sheet CondAmbCusto
B4: CONDICIONAMENTO AMBIENTAL | P4: =B4 -> CONDICIONAMENTO AMBIENTAL
B5: CUSTOS DIRETOS | P5: CUSTOS ANUALIZADOS
B6: MATERIAIS E EQUIPAMENTOS | K6: ORIGEM DOS RECURSOS | P6: MATERIAIS E EQUIPAMENTOS | X6: ORIGEM DOS RECURSOS
B7: Materiais e equipamentos | H7: Vida útil (anos) | I7: Quantidade | J7: Preço unitário | K7: PEE | L7: Terceiros | M7: Consumidor | N7: Total | P7: =B7 -> Materiais e equipamentos | V7: Vida útil | W7: FRC | X7: CAPEE | Y7: CATOTAL
B8: 1 | K8: =N8-L8-M8 -> 0 | N8: =I8*J8 -> 0 | P8: =B8 -> 1 | Q8: =IF(OR(C8=0,C8=""),"",C8) | V8: =IF(N8=0,"",H8) | W8: =IF(OR(V8="",V8=0),0,(Projeto!$AD$10*((1+Projeto!$AD$10)^V8))/(((1+Projeto!$AD$10)^V8)-1)) -> 0 | X8: =IF(AND(K8>0,CustoContábil!$F$6>0),K8*(CustoContábil!$F$18/CustoContábil!$F$6)*W8,0) -> 0 | Y8: =IF(AND(N8>0,CustoContábil!$D$6>0),N8*(CustoContábil!$D$18/CustoContábil!$D$6)*W8,0) -> 0
B9: 2 | K9: =N9-L9-M9 -> 0 | N9: =I9*J9 -> 0 | P9: =B9 -> 2 | Q9: =IF(OR(C9=0,C9=""),"",C9) | V9: =IF(N9=0,"",H9) | W9: =IF(OR(V9="",V9=0),0,(Projeto!$AD$10*((1+Projeto!$AD$10)^V9))/(((1+Projeto!$AD$10)^V9)-1)) -> 0 | X9: =IF(AND(K9>0,CustoContábil!$F$6>0),K9*(CustoContábil!$F$18/CustoContábil!$F$6)*W9,0) -> 0 | Y9: =IF(AND(N9>0,CustoContábil!$D$6>0),N9*(CustoContábil!$D$18/CustoContábil!$D$6)*W9,0) -> 0
B10: 3 | K10: =N10-L10-M10 -> 0 | N10: =I10*J10 -> 0 | P10: =B10 -> 3 | Q10: =IF(OR(C10=0,C10=""),"",C10) | V10: =IF(N10=0,"",H10) | W10: =IF(OR(V10="",V10=0),0,(Projeto!$AD$10*((1+Projeto!$AD$10)^V10))/(((1+Projeto!$AD$10)^V10)-1)) -> 0 | X10: =IF(AND(K10>0,CustoContábil!$F$6>0),K10*(CustoContábil!$F$18/CustoContábil!$F$6)*W10,0) -> 0 | Y10: =IF(AND(N10>0,CustoContábil!$D$6>0),N10*(CustoContábil!$D$18/CustoContábil!$D$6)*W10,0) -> 0
B11: 4 | K11: =N11-L11-M11 -> 0 | N11: =I11*J11 -> 0 | P11: =B11 -> 4 | Q11: =IF(OR(C11=0,C11=""),"",C11) | V11: =IF(N11=0,"",H11) | W11: =IF(OR(V11="",V11=0),0,(Projeto!$AD$10*((1+Projeto!$AD$10)^V11))/(((1+Projeto!$AD$10)^V11)-1)) -> 0 | X11: =IF(AND(K11>0,CustoContábil!$F$6>0),K11*(CustoContábil!$F$18/CustoContábil!$F$6)*W11,0) -> 0 | Y11: =IF(AND(N11>0,CustoContábil!$D$6>0),N11*(CustoContábil!$D$18/CustoContábil!$D$6)*W11,0) -> 0
B12: 5 | K12: =N12-L12-M12 -> 0 | N12: =I12*J12 -> 0 | P12: =B12 -> 5 | Q12: =IF(OR(C12=0,C12=""),"",C12) | V12: =IF(N12=0,"",H12) | W12: =IF(OR(V12="",V12=0),0,(Projeto!$AD$10*((1+Projeto!$AD$10)^V12))/(((1+Projeto!$AD$10)^V12)-1)) -> 0 | X12: =IF(AND(K12>0,CustoContábil!$F$6>0),K12*(CustoContábil!$F$18/CustoContábil!$F$6)*W12,0) -> 0 | Y12: =IF(AND(N12>0,CustoContábil!$D$6>0),N12*(CustoContábil!$D$18/CustoContábil!$D$6)*W12,0) -> 0
B13: 6 | K13: =N13-L13-M13 -> 0 | N13: =I13*J13 -> 0 | P13: =B13 -> 6 | Q13: =IF(OR(C13=0,C13=""),"",C13) | V13: =IF(N13=0,"",H13) | W13: =IF(OR(V13="",V13=0),0,(Projeto!$AD$10*((1+Projeto!$AD$10)^V13))/(((1+Projeto!$AD$10)^V13)-1)) -> 0 | X13: =IF(AND(K13>0,CustoContábil!$F$6>0),K13*(CustoContábil!$F$18/CustoContábil!$F$6)*W13,0) -> 0 | Y13: =IF(AND(N13>0,CustoContábil!$D$6>0),N13*(CustoContábil!$D$18/CustoContábil!$D$6)*W13,0) -> 0
B14: 7 | K14: =N14-L14-M14 -> 0 | N14: =I14*J14 -> 0 | P14: =B14 -> 7 | Q14: =IF(OR(C14=0,C14=""),"",C14) | V14: =IF(N14=0,"",H14) | W14: =IF(OR(V14="",V14=0),0,(Projeto!$AD$10*((1+Projeto!$AD$10)^V14))/(((1+Projeto!$AD$10)^V14)-1)) -> 0 | X14: =IF(AND(K14>0,CustoContábil!$F$6>0),K14*(CustoContábil!$F$18/CustoContábil!$F$6)*W14,0) -> 0 | Y14: =IF(AND(N14>0,CustoContábil!$D$6>0),N14*(CustoContábil!$D$18/CustoContábil!$D$6)*W14,0) -> 0
B15: 8 | K15: =N15-L15-M15 -> 0 | N15: =I15*J15 -> 0 | P15: =B15 -> 8 | Q15: =IF(OR(C15=0,C15=""),"",C15) | V15: =IF(N15=0,"",H15) | W15: =IF(OR(V15="",V15=0),0,(Projeto!$AD$10*((1+Projeto!$AD$10)^V15))/(((1+Projeto!$AD$10)^V15)-1)) -> 0 | X15: =IF(AND(K15>0,CustoContábil!$F$6>0),K15*(CustoContábil!$F$18/CustoContábil!$F$6)*W15,0) -> 0 | Y15: =IF(AND(N15>0,CustoContábil!$D$6>0),N15*(CustoContábil!$D$18/CustoContábil!$D$6)*W15,0) -> 0
B16: 9 | K16: =N16-L16-M16 -> 0 | N16: =I16*J16 -> 0 | P16: =B16 -> 9 | Q16: =IF(OR(C16=0,C16=""),"",C16) | V16: =IF(N16=0,"",H16) | W16: =IF(OR(V16="",V16=0),0,(Projeto!$AD$10*((1+Projeto!$AD$10)^V16))/(((1+Projeto!$AD$10)^V16)-1)) -> 0 | X16: =IF(AND(K16>0,CustoContábil!$F$6>0),K16*(CustoContábil!$F$18/CustoContábil!$F$6)*W16,0) -> 0 | Y16: =IF(AND(N16>0,CustoContábil!$D$6>0),N16*(CustoContábil!$D$18/CustoContábil!$D$6)*W16,0) -> 0
B17: 10 | K17: =N17-L17-M17 -> 0 | N17: =I17*J17 -> 0 | P17: =B17 -> 10 | Q17: =IF(OR(C17=0,C17=""),"",C17) | V17: =IF(N17=0,"",H17) | W17: =IF(OR(V17="",V17=0),0,(Projeto!$AD$10*((1+Projeto!$AD$10)^V17))/(((1+Projeto!$AD$10)^V17)-1)) -> 0 | X17: =IF(AND(K17>0,CustoContábil!$F$6>0),K17*(CustoContábil!$F$18/CustoContábil!$F$6)*W17,0) -> 0 | Y17: =IF(AND(N17>0,CustoContábil!$D$6>0),N17*(CustoContábil!$D$18/CustoContábil!$D$6)*W17,0) -> 0
B18: 11 | K18: =N18-L18-M18 -> 0 | N18: =I18*J18 -> 0 | P18: =B18 -> 11 | Q18: =IF(OR(C18=0,C18=""),"",C18) | V18: =IF(N18=0,"",H18) | W18: =IF(OR(V18="",V18=0),0,(Projeto!$AD$10*((1+Projeto!$AD$10)^V18))/(((1+Projeto!$AD$10)^V18)-1)) -> 0 | X18: =IF(AND(K18>0,CustoContábil!$F$6>0),K18*(CustoContábil!$F$18/CustoContábil!$F$6)*W18,0) -> 0 | Y18: =IF(AND(N18>0,CustoContábil!$D$6>0),N18*(CustoContábil!$D$18/CustoContábil!$D$6)*W18,0) -> 0
B19: 12 | K19: =N19-L19-M19 -> 0 | N19: =I19*J19 -> 0 | P19: =B19 -> 12 | Q19: =IF(OR(C19=0,C19=""),"",C19) | V19: =IF(N19=0,"",H19) | W19: =IF(OR(V19="",V19=0),0,(Projeto!$AD$10*((1+Projeto!$AD$10)^V19))/(((1+Projeto!$AD$10)^V19)-1)) -> 0 | X19: =IF(AND(K19>0,CustoContábil!$F$6>0),K19*(CustoContábil!$F$18/CustoContábil!$F$6)*W19,0) -> 0 | Y19: =IF(AND(N19>0,CustoContábil!$D$6>0),N19*(CustoContábil!$D$18/CustoContábil!$D$6)*W19,0) -> 0
... B57: 50 | K57: =N57-L57-M57 -> 0 | N57: =I57*J57 -> 0 | P57: =B57 -> 50 | Q57: =IF(OR(C57=0,C57=""),"",C57) | V57: =IF(N57=0,"",H57) | W57: =IF(OR(V57="",V57=0),0,(Projeto!$AD$10*((1+Projeto!$AD$10)^V57))/(((1+Projeto!$AD$10)^V57)-1)) -> 0 | X57: =IF(AND(K57>0,CustoContábil!$F$6>0),K57*(CustoContábil!$F$18/CustoContábil!$F$6)*W57,0) -> 0 | Y57: =IF(AND(N57>0,CustoContábil!$D$6>0),N57*(CustoContábil!$D$18/CustoContábil!$D$6)*W57,0) -> 0
C58: Materiais e equipamentos | K58: =SUM(K8:K57) -> 0 | L58: =SUM(L8:L57) -> 0 | M58: =SUM(M8:M57) -> 0 | N58: =SUM(N8:N57) -> 0 | V58: Custo anualizado total - Condicionamento Ambiental | W58: CAT COND | X58: =SUM(X8:X57) -> 0 | Y58: =SUM(Y8:Y57) -> 0
B59: MÃO DE OBRA E ADMINISTRAÇÃO PRÓPRIA - CEMIG | K59: ORIGEM DOS RECURSOS
C60: Mão de obra própria - CEMIG | K60: =Apoio!AY5 -> 0 | N60: =K60 -> 0 | Q60: RCBCOND_PEE | R60: =RCB!$G$10 -> 0
C61: Auditoria Contábil e Financeira - CEMIG | K61: =Apoio!BH5 -> 0 | N61: =K61 -> 0 | Q61: RCBPEE | R61: =RCB!$H$9 -> 0
B62: Mão de obra de terceiros | I62: Quantidade | J62: Preço unitário | K62: PEE | L62: Terceiros | M62: Consumidor | N62: Total
B63: 1 | C63: Diagnóstico Energético - Rateio | K63: =Terceiros!K15 -> 0 | L63: =Terceiros!L15 -> 0 | M63: =Terceiros!M15 -> 0 | N63: =Terceiros!N15 -> 0
B64: 2 | C64: Gerenciamento do Projeto - Rateio | K64: =Terceiros!K26 -> 0 | L64: =Terceiros!L26 -> 0 | M64: =Terceiros!M26 -> 0 | N64: =Terceiros!N26 -> 0
B65: 3 | C65: Relatório Final - Rateio | K65: =Terceiros!K37 -> 0 | L65: =Terceiros!L37 -> 0 | M65: =Terceiros!M37 -> 0 | N65: =Terceiros!N37 -> 0
B66: 4 | K66: =N66-L66-M66 -> 0 | N66: =I66*J66 -> 0
B67: 5 | K67: =N67-L67-M67 -> 0 | N67: =I67*J67 -> 0
B68: 6 | K68: =N68-L68-M68 -> 0 | N68: =I68*J68 -> 0
B69: 7 | K69: =N69-L69-M69 -> 0 | N69: =I69*J69 -> 0
B70: 8 | K70: =N70-L70-M70 -> 0 | N70: =I70*J70 -> 0
B71: 9 | K71: =N71-L71-M71 -> 0 | N71: =I71*J71 -> 0
B72: 10 | K72: =N72-L72-M72 -> 0 | N72: =I72*J72 -> 0
B73: 11 | K73: =N73-L73-M73 -> 0 | N73: =I73*J73 -> 0
B74: 12 | K74: =N74-L74-M74 -> 0 | N74: =I74*J74 -> 0
B75: 13 | K75: =N75-L75-M75 -> 0 | N75: =I75*J75 -> 0
B76: 14 | K76: =N76-L76-M76 -> 0 | N76: =I76*J76 -> 0
B77: 15 | K77: =N77-L77-M77 -> 0 | N77: =I77*J77 -> 0
... B82: 20 | K82: =N82-L82-M82 -> 0 | N82: =I82*J82 -> 0
C83: Mão de obra de terceiros | K83: =SUM(K63:K82) -> 0 | L83: =SUM(L63:L82) -> 0 | M83: =SUM(M63:M82) -> 0 | N83: =SUM(N63:N82) -> 0
C84: Administração Própria - CEMIG | K84: =Apoio!BE5 -> 0 | N84: =K84 -> 0
J85: Sub total - Mão de obra de terceiros e Administração Própria CEMIG | K85: =SUM(K60,K61,K83,K84) -> 0 | L85: =L83 -> 0 | M85: =M83 -> 0 | N85: =SUM(N60,N61,N83,N84) -> 0
J86: Sub total - Custos diretos | K86: =SUM(K58,K85) -> 0 | L86: =SUM(L58,L85) -> 0 | M86: =SUM(M58,M85) -> 0 | N86: =SUM(N58,N85) -> 0
B87: CUSTOS INDIRETOS
B88: CUSTOS INDIRETOS | K88: ORIGEM DOS RECURSOS
C89: Marketing | K89: =Marketing!K31 -> 0 | L89: =Marketing!L31 -> 0 | M89: =Marketing!M31 -> 0 | N89: =Marketing!N31 -> 0
C90: Treinamento e capacitação | K90: =Treinamento!K31 -> 0 | L90: =Treinamento!L31 -> 0 | M90: =Treinamento!M31 -> 0 | N90: =Treinamento!N31 -> 0
B91: Descarte de materiais | I91: Quantidade | J91: Preço unitário | K91: PEE | L91: Terceiros | M91: Consumidor | N91: Total
B92: 1 | K92: =N92-L92-M92 -> 0 | N92: =I92*J92 -> 0
B93: 2 | K93: =N93-L93-M93 -> 0 | N93: =I93*J93 -> 0
B94: 3 | K94: =N94-L94-M94 -> 0 | N94: =I94*J94 -> 0
B95: 4 | K95: =N95-L95-M95 -> 0 | N95: =I95*J95 -> 0
B96: 5 | K96: =N96-L96-M96 -> 0 | N96: =I96*J96 -> 0
B97: 6 | K97: =N97-L97-M97 -> 0 | N97: =I97*J97 -> 0
B98: 7 | K98: =N98-L98-M98 -> 0 | N98: =I98*J98 -> 0
B99: 8 | K99: =N99-L99-M99 -> 0 | N99: =I99*J99 -> 0
B100: 9 | K100: =N100-L100-M100 -> 0 | N100: =I100*J100 -> 0
B101: 10 | K101: =N101-L101-M101 -> 0 | N101: =I101*J101 -> 0
B102: 11 | K102: =N102-L102-M102 -> 0 | N102: =I102*J102 -> 0
B103: 12 | K103: =N103-L103-M103 -> 0 | N103: =I103*J103 -> 0
... B111: 20 | K111: =N111-L111-M111 -> 0 | N111: =I111*J111 -> 0
C112: Descarte de materiais | K112: =SUM(K92:K111) -> 0 | L112: =SUM(L92:L111) -> 0 | M112: =SUM(M92:M111) -> 0 | N112: =SUM(N92:N111) -> 0
C113: Medição e verificação | K113: ='M&V'!J30 -> 0 | L113: ='M&V'!K30 -> 0 | M113: ='M&V'!L30 -> 0 | N113: ='M&V'!M30 -> 0
J114: Sub total - Custos indiretos | K114: =SUM(K89,K90,K112,K113) -> 0 | L114: =SUM(L89,L90,L112,L113) -> 0 | M114: =SUM(M89,M90,M112,M113) -> 0 | N114: =SUM(N89,N90,N112,N113) -> 0
J115: Custos Totais - Condicionamento Ambiental | K115: =SUM(K86,K114) -> 0 | L115: =SUM(L86,L114) -> 0 | M115: =SUM(M86,M114) -> 0 | N115: =SUM(N86,N114) -> 0

Sheet CondAmbBenef
B4: CONDICIONAMENTO AMBIENTAL - SISTEMA ATUAL
B5: 0 | G5: TOTAL | H5: cond 1 | I5: cond 2 | J5: cond 3 | K5: cond 4 | L5: cond 5 | M5: cond 6 | N5: cond 7 | O5: cond 8 | P5: cond 9 | Q5: cond 10 | R5: cond 11 | S5: cond 12 | T5: cond 13 | U5: cond 14 | V5: cond 15 | W5: cond 16 | X5: cond 17 | Y5: cond 18 | Z5: cond 19 | AA5: cond 20 | AB5: cond 21 | AC5: cond 22 | AD5: cond 23 | AE5: cond 24 | AF5: cond 25 | AG5: cond 26 | AH5: cond 27 | AI5: cond 28 | AJ5: cond 29 | AK5: cond 30 | AL5: cond 31 | AM5: cond 32 | AN5: cond 33 | AO5: cond 34 | AP5: cond 35 | AQ5: cond 36 | AR5: cond 37 | AS5: cond 38 | AT5: cond 39 | AU5: cond 40 | AV5: cond 41 | AW5: cond 42 | AX5: cond 43 | AY5: cond 44 | AZ5: cond 45 | BA5: cond 46 | BB5: cond 47 | BC5: cond 48 | BD5: cond 49 | BE5: cond 50 | BF5: cond 51 | BG5: cond 52 | BH5: cond 53 | BI5: cond 54 | BJ5: cond 55 | BK5: cond 56 | BL5: cond 57 | BM5: cond 58 | BN5: cond 59 | BO5: cond 60 | BP5: cond 61 | BQ5: cond 62 | BR5: cond 63 | BS5: cond 64 | BT5: cond 65 | BU5: cond 66 | BV5: cond 67 | BW5: cond 68 | BX5: cond 69 | BY5: cond 70 | BZ5: cond 71 | CA5: cond 72 | CB5: cond 73 | CC5: cond 74 | CD5: cond 75 | CE5: cond 76 | CF5: cond 77 | CG5: cond 78 | CH5: cond 79 | CI5: cond 80 | CJ5: cond 81 | CK5: cond 82 | CL5: cond 83 | CM5: cond 84 | CN5: cond 85 | CO5: cond 86 | CP5: cond 87 | CQ5: cond 88 | CR5: cond 89 | CS5: cond 90 | CT5: cond 91 | CU5: cond 92 | CV5: cond 93 | CW5: cond 94 | CX5: cond 95 | CY5: cond 96 | CZ5: cond 97 | DA5: cond 98 | DB5: cond 99 | DC5: cond 100 | DD5: cond 101 | DE5: cond 102 | DF5: cond 103 | DG5: cond 104 | DH5: cond 105 | DI5: cond 106 | DJ5: cond 107 | DK5: cond 108 | DL5: cond 109 | DM5: cond 110 | DN5: cond 111 | DO5: cond 112 | DP5: cond 113 | DQ5: cond 114 | DR5: cond 115 | DS5: cond 116 | DT5: cond 117 | DU5: cond 118 | DV5: cond 119 | DW5: cond 120 | DX5: cond 121 | DY5: cond 122 | DZ5: cond 123 | EA5: cond 124 | EB5: cond 125 | EC5: cond 126 | ED5: cond 127 | EE5: cond 128 | EF5: cond 129 | EG5: cond 130 | EH5: cond 131 | EI5: cond 132 | EJ5: cond 133 | EK5: cond 134 | EL5: cond 135 | EM5: cond 136 | EN5: cond 137 | EO5: cond 138 | EP5: cond 139 | EQ5: cond 140 | ER5: cond 141 | ES5: cond 142 | ET5: cond 143 | EU5: cond 144 | EV5: cond 145 | EW5: cond 146 | EX5: cond 147 | EY5: cond 148 | EZ5: cond 149 | FA5: cond 150
B6: 1 | C6: Unidade Consumidora
B7: 2 | C7: Tipo de equipamento / tecnologia
B8: =B7+1 -> 3 | C8: Potência nominal de refrigeração | E8: BTU/h | F8: pai | G8: =IF(COUNTA(H8:FA8)=0,"",IF(SMALL(H8:FA8,1)<0,"ERRO",""))
B9: =B8+1 -> 4 | C9: Coefiente de eficiência energética (COP) | E9: W/W | F9: cai | G9: =IF(COUNTA(H9:FA9)=0,"",IF(SMALL(H9:FA9,1)<1,"ERRO",""))
B10: =B9+1 -> 5 | C10: Quantidade | F10: qai | G10: =IF(COUNTA(H10:FA10)=0,"",IF(SMALL(H10:FA10,1)<0,"ERRO",SUM(H10:FA10)))
B11: =B10+1 -> 6 | C11: Potência instalada | E11: kW | F11: Pai | G11: =SUM(H11:FA11) -> 0 | H11: =IF(H9=0,0,((H8*0.293*H10)/(1000*H9))) -> 0 | I11: =IF(I9=0,0,((I8*0.293*I10)/(1000*I9))) -> 0 | J11: =IF(J9=0,0,((J8*0.293*J10)/(1000*J9))) -> 0 | K11: =IF(K9=0,0,((K8*0.293*K10)/(1000*K9))) -> 0 | L11: =IF(L9=0,0,((L8*0.293*L10)/(1000*L9))) -> 0 | M11: =IF(M9=0,0,((M8*0.293*M10)/(1000*M9))) -> 0 | N11: =IF(N9=0,0,((N8*0.293*N10)/(1000*N9))) -> 0 | O11: =IF(O9=0,0,((O8*0.293*O10)/(1000*O9))) -> 0 | ... FA11: =IF(FA9=0,0,((FA8*0.293*FA10)/(1000*FA9))) -> 0
B12: =B11+1 -> 7 | C12: Fator de utilização | G12: =IF(COUNTA(H12:FA12)=0,"",IF(OR(SMALL(H12:FA12,1)<0,LARGE(H12:FA12,1)>1),"ERRO",""))
B13: =B12+1 -> 8 | C13: Potência média utilizada | E13: kW | F13: Puai | G13: =SUM(H13:FA13) -> 0 | H13: =H11*H12 -> 0 | I13: =I11*I12 -> 0 | J13: =J11*J12 -> 0 | K13: =K11*K12 -> 0 | L13: =L11*L12 -> 0 | M13: =M11*M12 -> 0 | N13: =N11*N12 -> 0 | O13: =O11*O12 -> 0 | ... FA13: =FA11*FA12 -> 0
B14: =B13+1 -> 9 | C14: Tempo de utilização do sistema, em um dia | E14: h/dia | G14: =IF(COUNTA(H14:FA14)=0,"",IF(OR(LARGE(H14:FA14,1)>24,SMALL(H14:FA14,1)<0),"ERRO",""))
C15: Dias de utilização do sistema, em um ano | E15: dia/ano | G15: =IF(COUNTA(H15:FA15)=0,"",IF(OR(LARGE(H15:FA15,1)>365,SMALL(H15:FA15,1)<0),"ERRO",""))
C16: Funcionamento | E16: h/ano | F16: hai | G16: =IF(COUNTA(H16:FA16)=0,"",IF(OR(LARGE(H16:FA16,1)>8760,SMALL(H16:FA16,1)<0),"ERRO","")) | H16: =H14*H15 -> 0 | I16: =I14*I15 -> 0 | J16: =J14*J15 -> 0 | K16: =K14*K15 -> 0 | L16: =L14*L15 -> 0 | M16: =M14*M15 -> 0 | N16: =N14*N15 -> 0 | O16: =O14*O15 -> 0 | ... FA16: =FA14*FA15 -> 0
B17: =B14+1 -> 10 | C17: Horas de utilização em horário de ponta, em um dia | E17: h/dia | F17: nupai | G17: =IF(COUNTA(H17:FA17)=0,"",IF(OR(LARGE(H17:FA17,1)>3,SMALL(H17:FA17,1)<0),"ERRO",""))
C18: Dias úteis de utilização em horário de ponta, em um mês | E18: dia/mês | F18: ndai | G18: =IF(COUNTA(H18:FA18)=0,"",IF(OR(LARGE(H18:FA18,1)>22,SMALL(H18:FA18,1)<0),"ERRO",""))
C19: Meses de utilização em horário de ponta, em um ano | E19: mês/ano | F19: nmai | G19: =IF(COUNTA(H19:FA19)=0,"",IF(OR(LARGE(H19:FA19,1)>12,SMALL(H19:FA19,1)<0),"ERRO",""))
C20: Fator de coincidência na ponta | F20: FCPai | G20: =IF(COUNTA(H20:FA20)=0,"",IF(OR(LARGE(H20:FA20,1)>1,SMALL(H20:FA20,1)<0),"ERRO","")) | H20: =H17*H18*H19/792 -> 0 | I20: =I17*I18*I19/792 -> 0 | J20: =J17*J18*J19/792 -> 0 | K20: =K17*K18*K19/792 -> 0 | L20: =L17*L18*L19/792 -> 0 | M20: =M17*M18*M19/792 -> 0 | N20: =N17*N18*N19/792 -> 0 | O20: =O17*O18*O19/792 -> 0 | ... FA20: =FA17*FA18*FA19/792 -> 0
B21: =B17+1 -> 11 | C21: Energia consumida | E21: MWh/ano | F21: Eai | G21: =SUM(H21:FA21) -> 0 | H21: =(H13*H16)/1000 -> 0 | I21: =(I13*I16)/1000 -> 0 | J21: =(J13*J16)/1000 -> 0 | K21: =(K13*K16)/1000 -> 0 | L21: =(L13*L16)/1000 -> 0 | M21: =(M13*M16)/1000 -> 0 | N21: =(N13*N16)/1000 -> 0 | O21: =(O13*O16)/1000 -> 0 | ... FA21: =(FA13*FA16)/1000 -> 0
B22: =B21+1 -> 12 | C22: Demanda média na ponta | E22: kW | F22: Dai | G22: =SUM(H22:FA22) -> 0 | H22: =H13*H20 -> 0 | I22: =I13*I20 -> 0 | J22: =J13*J20 -> 0 | K22: =K13*K20 -> 0 | L22: =L13*L20 -> 0 | M22: =M13*M20 -> 0 | N22: =N13*N20 -> 0 | O22: =O13*O20 -> 0 | ... FA22: =FA13*FA20 -> 0
B24: CONDICIONAMENTO AMBIENTAL - SISTEMA PROPOSTO
G25: TOTAL | H25: cond 1 | I25: cond 2 | J25: cond 3 | K25: cond 4 | L25: cond 5 | M25: cond 6 | N25: cond 7 | O25: cond 8 | P25: cond 9 | Q25: cond 10 | R25: cond 11 | S25: cond 12 | T25: cond 13 | U25: cond 14 | V25: cond 15 | W25: cond 16 | X25: cond 17 | Y25: cond 18 | Z25: cond 19 | AA25: cond 20 | AB25: cond 21 | AC25: cond 22 | AD25: cond 23 | AE25: cond 24 | AF25: cond 25 | AG25: cond 26 | AH25: cond 27 | AI25: cond 28 | AJ25: cond 29 | AK25: cond 30 | AL25: cond 31 | AM25: cond 32 | AN25: cond 33 | AO25: cond 34 | AP25: cond 35 | AQ25: cond 36 | AR25: cond 37 | AS25: cond 38 | AT25: cond 39 | AU25: cond 40 | AV25: cond 41 | AW25: cond 42 | AX25: cond 43 | AY25: cond 44 | AZ25: cond 45 | BA25: cond 46 | BB25: cond 47 | BC25: cond 48 | BD25: cond 49 | BE25: cond 50 | BF25: cond 51 | BG25: cond 52 | BH25: cond 53 | BI25: cond 54 | BJ25: cond 55 | BK25: cond 56 | BL25: cond 57 | BM25: cond 58 | BN25: cond 59 | BO25: cond 60 | BP25: cond 61 | BQ25: cond 62 | BR25: cond 63 | BS25: cond 64 | BT25: cond 65 | BU25: cond 66 | BV25: cond 67 | BW25: cond 68 | BX25: cond 69 | BY25: cond 70 | BZ25: cond 71 | CA25: cond 72 | CB25: cond 73 | CC25: cond 74 | CD25: cond 75 | CE25: cond 76 | CF25: cond 77 | CG25: cond 78 | CH25: cond 79 | CI25: cond 80 | CJ25: cond 81 | CK25: cond 82 | CL25: cond 83 | CM25: cond 84 | CN25: cond 85 | CO25: cond 86 | CP25: cond 87 | CQ25: cond 88 | CR25: cond 89 | CS25: cond 90 | CT25: cond 91 | CU25: cond 92 | CV25: cond 93 | CW25: cond 94 | CX25: cond 95 | CY25: cond 96 | CZ25: cond 97 | DA25: cond 98 | DB25: cond 99 | DC25: cond 100 | DD25: cond 101 | DE25: cond 102 | DF25: cond 103 | DG25: cond 104 | DH25: cond 105 | DI25: cond 106 | DJ25: cond 107 | DK25: cond 108 | DL25: cond 109 | DM25: cond 110 | DN25: cond 111 | DO25: cond 112 | DP25: cond 113 | DQ25: cond 114 | DR25: cond 115 | DS25: cond 116 | DT25: cond 117 | DU25: cond 118 | DV25: cond 119 | DW25: cond 120 | DX25: cond 121 | DY25: cond 122 | DZ25: cond 123 | EA25: cond 124 | EB25: cond 125 | EC25: cond 126 | ED25: cond 127 | EE25: cond 128 | EF25: cond 129 | EG25: cond 130 | EH25: cond 131 | EI25: cond 132 | EJ25: cond 133 | EK25: cond 134 | EL25: cond 135 | EM25: cond 136 | EN25: cond 137 | EO25: cond 138 | EP25: cond 139 | EQ25: cond 140 | ER25: cond 141 | ES25: cond 142 | ET25: cond 143 | EU25: cond 144 | EV25: cond 145 | EW25: cond 146 | EX25: cond 147 | EY25: cond 148 | EZ25: cond 149 | FA25: cond 150
B26: =B22+1 -> 13 | C26: Unidade Consumidora | H26: =IF(H6="","",H6) | I26: =IF(I6="","",I6) | J26: =IF(J6="","",J6) | K26: =IF(K6="","",K6) | L26: =IF(L6="","",L6) | M26: =IF(M6="","",M6) | N26: =IF(N6="","",N6) | O26: =IF(O6="","",O6) | ... FA26: =IF(FA6="","",FA6)
B27: =B26+1 -> 14 | C27: Tipo de equipamento / tecnologia
B28: =B27+1 -> 15 | C28: Potência nominal de refrigeração | E28: BTU/h | F28: ppi | G28: =IF(COUNTA(H28:FA28)=0,"",IF(SMALL(H28:FA28,1)<0,"ERRO",""))
B29: =B28+1 -> 16 | C29: Coefiente de eficiência energética (COP) | E29: W/W | F29: cpi | G29: =IF(COUNTA(H29:FA29)=0,"",IF(SMALL(H29:FA29,1)<1,"ERRO",""))
B30: =B29+1 -> 17 | C30: Quantidade | F30: qpi | G30: =IF(COUNTA(H30:FA30)=0,"",IF(SMALL(H30:FA30,1)<0,"ERRO",SUM(H30:FA30)))
B31: =B30+1 -> 18 | C31: Potência instalada | E31: kW | F31: Ppi | G31: =SUM(H31:FA31) -> 0 | H31: =IF(H29=0,0,((H28*0.293*H30)/(1000*H29))) -> 0 | I31: =IF(I29=0,0,((I28*0.293*I30)/(1000*I29))) -> 0 | J31: =IF(J29=0,0,((J28*0.293*J30)/(1000*J29))) -> 0 | K31: =IF(K29=0,0,((K28*0.293*K30)/(1000*K29))) -> 0 | L31: =IF(L29=0,0,((L28*0.293*L30)/(1000*L29))) -> 0 | M31: =IF(M29=0,0,((M28*0.293*M30)/(1000*M29))) -> 0 | N31: =IF(N29=0,0,((N28*0.293*N30)/(1000*N29))) -> 0 | O31: =IF(O29=0,0,((O28*0.293*O30)/(1000*O29))) -> 0 | ... FA31: =IF(FA29=0,0,((FA28*0.293*FA30)/(1000*FA29))) -> 0
B32: =B31+1 -> 19 | C32: Fator de utilização | G32: =IF(COUNTA(H32:FA32)=0,"",IF(OR(SMALL(H32:FA32,1)<0,LARGE(H32:FA32,1)>1),"ERRO",""))
B33: =B32+1 -> 20 | C33: Potência média utilizada | E33: kW | F33: Pupi | G33: =SUM(H33:FA33) -> 0 | H33: =H31*H32 -> 0 | I33: =I31*I32 -> 0 | J33: =J31*J32 -> 0 | K33: =K31*K32 -> 0 | L33: =L31*L32 -> 0 | M33: =M31*M32 -> 0 | N33: =N31*N32 -> 0 | O33: =O31*O32 -> 0 | ... FA33: =FA31*FA32 -> 0
B34: =B33+1 -> 21 | C34: Tempo de utilização do sistema, em um dia | E34: h/dia | G34: =IF(COUNTA(H34:FA34)=0,"",IF(OR(LARGE(H34:FA34,1)>24,SMALL(H34:FA34,1)<0),"ERRO",""))
C35: Dias de utilização do sistema, em um ano | E35: dia/ano | G35: =IF(COUNTA(H35:FA35)=0,"",IF(OR(LARGE(H35:FA35,1)>365,SMALL(H35:FA35,1)<0),"ERRO",""))
C36: Funcionamento | E36: h/ano | F36: hpi | G36: =IF(COUNTA(H36:FA36)=0,"",IF(OR(LARGE(H36:FA36,1)>8760,SMALL(H36:FA36,1)<0),"ERRO","")) | H36: =H34*H35 -> 0 | I36: =I34*I35 -> 0 | J36: =J34*J35 -> 0 | K36: =K34*K35 -> 0 | L36: =L34*L35 -> 0 | M36: =M34*M35 -> 0 | N36: =N34*N35 -> 0 | O36: =O34*O35 -> 0 | ... FA36: =FA34*FA35 -> 0
B37: =B34+1 -> 22 | C37: Horas de utilização em horário de ponta, em um dia | E37: h/dia | F37: nuppi | G37: =IF(COUNTA(H37:FA37)=0,"",IF(OR(LARGE(H37:FA37,1)>3,SMALL(H37:FA37,1)<0),"ERRO",""))
C38: Dias úteis de utilização em horário de ponta, em um mês | E38: dia/mês | F38: ndpi | G38: =IF(COUNTA(H38:FA38)=0,"",IF(OR(LARGE(H38:FA38,1)>22,SMALL(H38:FA38,1)<0),"ERRO",""))
C39: Meses de utilização em horário de ponta, em um ano | E39: mês/ano | F39: nmpi | G39: =IF(COUNTA(H39:FA39)=0,"",IF(OR(LARGE(H39:FA39,1)>12,SMALL(H39:FA39,1)<0),"ERRO",""))
C40: Fator de coincidência na ponta | F40: FCPpi | G40: =IF(COUNTA(H40:FA40)=0,"",IF(OR(LARGE(H40:FA40,1)>1,SMALL(H40:FA40,1)<0),"ERRO","")) | H40: =H37*H38*H39/792 -> 0 | I40: =I37*I38*I39/792 -> 0 | J40: =J37*J38*J39/792 -> 0 | K40: =K37*K38*K39/792 -> 0 | L40: =L37*L38*L39/792 -> 0 | M40: =M37*M38*M39/792 -> 0 | N40: =N37*N38*N39/792 -> 0 | O40: =O37*O38*O39/792 -> 0 | ... FA40: =FA37*FA38*FA39/792 -> 0
B41: =B37+1 -> 23 | C41: Energia consumida | E41: MWh/ano | F41: Epi | G41: =SUM(H41:FA41) -> 0 | H41: =(H33*H36)/1000 -> 0 | I41: =(I33*I36)/1000 -> 0 | J41: =(J33*J36)/1000 -> 0 | K41: =(K33*K36)/1000 -> 0 | L41: =(L33*L36)/1000 -> 0 | M41: =(M33*M36)/1000 -> 0 | N41: =(N33*N36)/1000 -> 0 | O41: =(O33*O36)/1000 -> 0 | ... FA41: =(FA33*FA36)/1000 -> 0
B42: =B41+1 -> 24 | C42: Demanda média na ponta | E42: kW | F42: Dpi | G42: =SUM(H42:FA42) -> 0 | H42: =H33*H40 -> 0 | I42: =I33*I40 -> 0 | J42: =J33*J40 -> 0 | K42: =K33*K40 -> 0 | L42: =L33*L40 -> 0 | M42: =M33*M40 -> 0 | N42: =N33*N40 -> 0 | O42: =O33*O40 -> 0 | ... FA42: =FA33*FA40 -> 0
B44: CONDICIONAMENTO AMBIENTAL - RESULTADOS ESPERADOS
G45: TOTAL | H45: cond 1 | I45: cond 2 | J45: cond 3 | K45: cond 4 | L45: cond 5 | M45: cond 6 | N45: cond 7 | O45: cond 8 | P45: cond 9 | Q45: cond 10 | R45: cond 11 | S45: cond 12 | T45: cond 13 | U45: cond 14 | V45: cond 15 | W45: cond 16 | X45: cond 17 | Y45: cond 18 | Z45: cond 19 | AA45: cond 20 | AB45: cond 21 | AC45: cond 22 | AD45: cond 23 | AE45: cond 24 | AF45: cond 25 | AG45: cond 26 | AH45: cond 27 | AI45: cond 28 | AJ45: cond 29 | AK45: cond 30 | AL45: cond 31 | AM45: cond 32 | AN45: cond 33 | AO45: cond 34 | AP45: cond 35 | AQ45: cond 36 | AR45: cond 37 | AS45: cond 38 | AT45: cond 39 | AU45: cond 40 | AV45: cond 41 | AW45: cond 42 | AX45: cond 43 | AY45: cond 44 | AZ45: cond 45 | BA45: cond 46 | BB45: cond 47 | BC45: cond 48 | BD45: cond 49 | BE45: cond 50 | BF45: cond 51 | BG45: cond 52 | BH45: cond 53 | BI45: cond 54 | BJ45: cond 55 | BK45: cond 56 | BL45: cond 57 | BM45: cond 58 | BN45: cond 59 | BO45: cond 60 | BP45: cond 61 | BQ45: cond 62 | BR45: cond 63 | BS45: cond 64 | BT45: cond 65 | BU45: cond 66 | BV45: cond 67 | BW45: cond 68 | BX45: cond 69 | BY45: cond 70 | BZ45: cond 71 | CA45: cond 72 | CB45: cond 73 | CC45: cond 74 | CD45: cond 75 | CE45: cond 76 | CF45: cond 77 | CG45: cond 78 | CH45: cond 79 | CI45: cond 80 | CJ45: cond 81 | CK45: cond 82 | CL45: cond 83 | CM45: cond 84 | CN45: cond 85 | CO45: cond 86 | CP45: cond 87 | CQ45: cond 88 | CR45: cond 89 | CS45: cond 90 | CT45: cond 91 | CU45: cond 92 | CV45: cond 93 | CW45: cond 94 | CX45: cond 95 | CY45: cond 96 | CZ45: cond 97 | DA45: cond 98 | DB45: cond 99 | DC45: cond 100 | DD45: cond 101 | DE45: cond 102 | DF45: cond 103 | DG45: cond 104 | DH45: cond 105 | DI45: cond 106 | DJ45: cond 107 | DK45: cond 108 | DL45: cond 109 | DM45: cond 110 | DN45: cond 111 | DO45: cond 112 | DP45: cond 113 | DQ45: cond 114 | DR45: cond 115 | DS45: cond 116 | DT45: cond 117 | DU45: cond 118 | DV45: cond 119 | DW45: cond 120 | DX45: cond 121 | DY45: cond 122 | DZ45: cond 123 | EA45: cond 124 | EB45: cond 125 | EC45: cond 126 | ED45: cond 127 | EE45: cond 128 | EF45: cond 129 | EG45: cond 130 | EH45: cond 131 | EI45: cond 132 | EJ45: cond 133 | EK45: cond 134 | EL45: cond 135 | EM45: cond 136 | EN45: cond 137 | EO45: cond 138 | EP45: cond 139 | EQ45: cond 140 | ER45: cond 141 | ES45: cond 142 | ET45: cond 143 | EU45: cond 144 | EV45: cond 145 | EW45: cond 146 | EX45: cond 147 | EY45: cond 148 | EZ45: cond 149 | FA45: cond 150
B46: =B42+1 -> 25 | C46: Redução de demanda na ponta | E46: kW | F46: RDPi | G46: =SUM(H46:FA46) -> 0 | H46: =H22-H42 -> 0 | I46: =I22-I42 -> 0 | J46: =J22-J42 -> 0 | K46: =K22-K42 -> 0 | L46: =L22-L42 -> 0 | M46: =M22-M42 -> 0 | N46: =N22-N42 -> 0 | O46: =O22-O42 -> 0 | ... FA46: =FA22-FA42 -> 0
B47: =B46+1 -> 26 | C47: Custo evitado de demanda (CED) = | D47: =Projeto!$L$44 -> 0 | E47: % | F47: RDPi% | G47: =IF(G22=0,0,G46/G22) -> 0 | H47: =IF(H22=0,0,H46/H22) -> 0 | I47: =IF(I22=0,0,I46/I22) -> 0 | J47: =IF(J22=0,0,J46/J22) -> 0 | K47: =IF(K22=0,0,K46/K22) -> 0 | L47: =IF(L22=0,0,L46/L22) -> 0 | M47: =IF(M22=0,0,M46/M22) -> 0 | N47: =IF(N22=0,0,N46/N22) -> 0 | ... FA47: =IF(FA22=0,0,FA46/FA22) -> 0
B48: =B47+1 -> 27 | C48: Energia economizada | E48: MWh/ano | F48: EEi | G48: =SUM(H48:FA48) -> 0 | H48: =H21-H41 -> 0 | I48: =I21-I41 -> 0 | J48: =J21-J41 -> 0 | K48: =K21-K41 -> 0 | L48: =L21-L41 -> 0 | M48: =M21-M41 -> 0 | N48: =N21-N41 -> 0 | O48: =O21-O41 -> 0 | ... FA48: =FA21-FA41 -> 0
B49: =B48+1 -> 28 | C49: Custo da energia evitada (CEE) = | D49: =Projeto!$L$43 -> 0 | E49: % | F49: EEi% | G49: =IF(G21=0,0,G48/G21) -> 0 | H49: =IF(H21=0,0,H48/H21) -> 0 | I49: =IF(I21=0,0,I48/I21) -> 0 | J49: =IF(J21=0,0,J48/J21) -> 0 | K49: =IF(K21=0,0,K48/K21) -> 0 | L49: =IF(L21=0,0,L48/L21) -> 0 | M49: =IF(M21=0,0,M48/M21) -> 0 | N49: =IF(N21=0,0,N48/N21) -> 0 | ... FA49: =IF(FA21=0,0,FA48/FA21) -> 0
C50: Benefício anualizado - Condicionamento Ambiental | E50: R$ | F50: BCOND | G50: =SUM(H50:FA50) -> 0 | H50: =H46*$D$47+H48*$D$49 -> 0 | I50: =I46*$D$47+I48*$D$49 -> 0 | J50: =J46*$D$47+J48*$D$49 -> 0 | K50: =K46*$D$47+K48*$D$49 -> 0 | L50: =L46*$D$47+L48*$D$49 -> 0 | M50: =M46*$D$47+M48*$D$49 -> 0 | N50: =N46*$D$47+N48*$D$49 -> 0 | O50: =O46*$D$47+O48*$D$49 -> 0 | ... FA50: =FA46*$D$47+FA48*$D$49 -> 0
F52: RCBCOND_PEE | G52: =RCB!$G$10 -> 0
F53: RCBPEE | G53: =RCB!$H$9 -> 0

Sheet MotorCusto
B4: SISTEMAS MOTRIZES | P4: =B4 -> SISTEMAS MOTRIZES
B5: CUSTOS DIRETOS | P5: CUSTOS ANUALIZADOS
B6: MATERIAIS E EQUIPAMENTOS | K6: ORIGEM DOS RECURSOS | P6: MATERIAIS E EQUIPAMENTOS | X6: ORIGEM DOS RECURSOS
B7: Materiais e equipamentos | H7: Vida útil (anos) | I7: Quantidade | J7: Preço unitário | K7: PEE | L7: Terceiros | M7: Consumidor | N7: Total | P7: =B7 -> Materiais e equipamentos | V7: Vida útil | W7: FRC | X7: CAPEE | Y7: CATOTAL
B8: 1 | K8: =N8-L8-M8 -> 0 | N8: =I8*J8 -> 0 | P8: =B8 -> 1 | Q8: =IF(OR(C8=0,C8=""),"",C8) | V8: =IF(N8=0,"",H8) | W8: =IF(OR(V8="",V8=0),0,(Projeto!$AD$10*((1+Projeto!$AD$10)^V8))/(((1+Projeto!$AD$10)^V8)-1)) -> 0 | X8: =IF(AND(K8>0,CustoContábil!$F$6>0),K8*(CustoContábil!$F$18/CustoContábil!$F$6)*W8,0) -> 0 | Y8: =IF(AND(N8>0,CustoContábil!$D$6>0),N8*(CustoContábil!$D$18/CustoContábil!$D$6)*W8,0) -> 0
B9: 2 | K9: =N9-L9-M9 -> 0 | N9: =I9*J9 -> 0 | P9: =B9 -> 2 | Q9: =IF(OR(C9=0,C9=""),"",C9) | V9: =IF(N9=0,"",H9) | W9: =IF(OR(V9="",V9=0),0,(Projeto!$AD$10*((1+Projeto!$AD$10)^V9))/(((1+Projeto!$AD$10)^V9)-1)) -> 0 | X9: =IF(AND(K9>0,CustoContábil!$F$6>0),K9*(CustoContábil!$F$18/CustoContábil!$F$6)*W9,0) -> 0 | Y9: =IF(AND(N9>0,CustoContábil!$D$6>0),N9*(CustoContábil!$D$18/CustoContábil!$D$6)*W9,0) -> 0
B10: 3 | K10: =N10-L10-M10 -> 0 | N10: =I10*J10 -> 0 | P10: =B10 -> 3 | Q10: =IF(OR(C10=0,C10=""),"",C10) | V10: =IF(N10=0,"",H10) | W10: =IF(OR(V10="",V10=0),0,(Projeto!$AD$10*((1+Projeto!$AD$10)^V10))/(((1+Projeto!$AD$10)^V10)-1)) -> 0 | X10: =IF(AND(K10>0,CustoContábil!$F$6>0),K10*(CustoContábil!$F$18/CustoContábil!$F$6)*W10,0) -> 0 | Y10: =IF(AND(N10>0,CustoContábil!$D$6>0),N10*(CustoContábil!$D$18/CustoContábil!$D$6)*W10,0) -> 0
B11: 4 | K11: =N11-L11-M11 -> 0 | N11: =I11*J11 -> 0 | P11: =B11 -> 4 | Q11: =IF(OR(C11=0,C11=""),"",C11) | V11: =IF(N11=0,"",H11) | W11: =IF(OR(V11="",V11=0),0,(Projeto!$AD$10*((1+Projeto!$AD$10)^V11))/(((1+Projeto!$AD$10)^V11)-1)) -> 0 | X11: =IF(AND(K11>0,CustoContábil!$F$6>0),K11*(CustoContábil!$F$18/CustoContábil!$F$6)*W11,0) -> 0 | Y11: =IF(AND(N11>0,CustoContábil!$D$6>0),N11*(CustoContábil!$D$18/CustoContábil!$D$6)*W11,0) -> 0
B12: 5 | K12: =N12-L12-M12 -> 0 | N12: =I12*J12 -> 0 | P12: =B12 -> 5 | Q12: =IF(OR(C12=0,C12=""),"",C12) | V12: =IF(N12=0,"",H12) | W12: =IF(OR(V12="",V12=0),0,(Projeto!$AD$10*((1+Projeto!$AD$10)^V12))/(((1+Projeto!$AD$10)^V12)-1)) -> 0 | X12: =IF(AND(K12>0,CustoContábil!$F$6>0),K12*(CustoContábil!$F$18/CustoContábil!$F$6)*W12,0) -> 0 | Y12: =IF(AND(N12>0,CustoContábil!$D$6>0),N12*(CustoContábil!$D$18/CustoContábil!$D$6)*W12,0) -> 0
B13: 6 | K13: =N13-L13-M13 -> 0 | N13: =I13*J13 -> 0 | P13: =B13 -> 6 | Q13: =IF(OR(C13=0,C13=""),"",C13) | V13: =IF(N13=0,"",H13) | W13: =IF(OR(V13="",V13=0),0,(Projeto!$AD$10*((1+Projeto!$AD$10)^V13))/(((1+Projeto!$AD$10)^V13)-1)) -> 0 | X13: =IF(AND(K13>0,CustoContábil!$F$6>0),K13*(CustoContábil!$F$18/CustoContábil!$F$6)*W13,0) -> 0 | Y13: =IF(AND(N13>0,CustoContábil!$D$6>0),N13*(CustoContábil!$D$18/CustoContábil!$D$6)*W13,0) -> 0
B14: 7 | K14: =N14-L14-M14 -> 0 | N14: =I14*J14 -> 0 | P14: =B14 -> 7 | Q14: =IF(OR(C14=0,C14=""),"",C14) | V14: =IF(N14=0,"",H14) | W14: =IF(OR(V14="",V14=0),0,(Projeto!$AD$10*((1+Projeto!$AD$10)^V14))/(((1+Projeto!$AD$10)^V14)-1)) -> 0 | X14: =IF(AND(K14>0,CustoContábil!$F$6>0),K14*(CustoContábil!$F$18/CustoContábil!$F$6)*W14,0) -> 0 | Y14: =IF(AND(N14>0,CustoContábil!$D$6>0),N14*(CustoContábil!$D$18/CustoContábil!$D$6)*W14,0) -> 0
B15: 8 | K15: =N15-L15-M15 -> 0 | N15: =I15*J15 -> 0 | P15: =B15 -> 8 | Q15: =IF(OR(C15=0,C15=""),"",C15) | V15: =IF(N15=0,"",H15) | W15: =IF(OR(V15="",V15=0),0,(Projeto!$AD$10*((1+Projeto!$AD$10)^V15))/(((1+Projeto!$AD$10)^V15)-1)) -> 0 | X15: =IF(AND(K15>0,CustoContábil!$F$6>0),K15*(CustoContábil!$F$18/CustoContábil!$F$6)*W15,0) -> 0 | Y15: =IF(AND(N15>0,CustoContábil!$D$6>0),N15*(CustoContábil!$D$18/CustoContábil!$D$6)*W15,0) -> 0
B16: 9 | K16: =N16-L16-M16 -> 0 | N16: =I16*J16 -> 0 | P16: =B16 -> 9 | Q16: =IF(OR(C16=0,C16=""),"",C16) | V16: =IF(N16=0,"",H16) | W16: =IF(OR(V16="",V16=0),0,(Projeto!$AD$10*((1+Projeto!$AD$10)^V16))/(((1+Projeto!$AD$10)^V16)-1)) -> 0 | X16: =IF(AND(K16>0,CustoContábil!$F$6>0),K16*(CustoContábil!$F$18/CustoContábil!$F$6)*W16,0) -> 0 | Y16: =IF(AND(N16>0,CustoContábil!$D$6>0),N16*(CustoContábil!$D$18/CustoContábil!$D$6)*W16,0) -> 0
B17: 10 | K17: =N17-L17-M17 -> 0 | N17: =I17*J17 -> 0 | P17: =B17 -> 10 | Q17: =IF(OR(C17=0,C17=""),"",C17) | V17: =IF(N17=0,"",H17) | W17: =IF(OR(V17="",V17=0),0,(Projeto!$AD$10*((1+Projeto!$AD$10)^V17))/(((1+Projeto!$AD$10)^V17)-1)) -> 0 | X17: =IF(AND(K17>0,CustoContábil!$F$6>0),K17*(CustoContábil!$F$18/CustoContábil!$F$6)*W17,0) -> 0 | Y17: =IF(AND(N17>0,CustoContábil!$D$6>0),N17*(CustoContábil!$D$18/CustoContábil!$D$6)*W17,0) -> 0
B18: 11 | K18: =N18-L18-M18 -> 0 | N18: =I18*J18 -> 0 | P18: =B18 -> 11 | Q18: =IF(OR(C18=0,C18=""),"",C18) | V18: =IF(N18=0,"",H18) | W18: =IF(OR(V18="",V18=0),0,(Projeto!$AD$10*((1+Projeto!$AD$10)^V18))/(((1+Projeto!$AD$10)^V18)-1)) -> 0 | X18: =IF(AND(K18>0,CustoContábil!$F$6>0),K18*(CustoContábil!$F$18/CustoContábil!$F$6)*W18,0) -> 0 | Y18: =IF(AND(N18>0,CustoContábil!$D$6>0),N18*(CustoContábil!$D$18/CustoContábil!$D$6)*W18,0) -> 0
B19: 12 | K19: =N19-L19-M19 -> 0 | N19: =I19*J19 -> 0 | P19: =B19 -> 12 | Q19: =IF(OR(C19=0,C19=""),"",C19) | V19: =IF(N19=0,"",H19) | W19: =IF(OR(V19="",V19=0),0,(Projeto!$AD$10*((1+Projeto!$AD$10)^V19))/(((1+Projeto!$AD$10)^V19)-1)) -> 0 | X19: =IF(AND(K19>0,CustoContábil!$F$6>0),K19*(CustoContábil!$F$18/CustoContábil!$F$6)*W19,0) -> 0 | Y19: =IF(AND(N19>0,CustoContábil!$D$6>0),N19*(CustoContábil!$D$18/CustoContábil!$D$6)*W19,0) -> 0
... B57: 50 | K57: =N57-L57-M57 -> 0 | N57: =I57*J57 -> 0 | P57: =B57 -> 50 | Q57: =IF(OR(C57=0,C57=""),"",C57) | V57: =IF(N57=0,"",H57) | W57: =IF(OR(V57="",V57=0),0,(Projeto!$AD$10*((1+Projeto!$AD$10)^V57))/(((1+Projeto!$AD$10)^V57)-1)) -> 0 | X57: =IF(AND(K57>0,CustoContábil!$F$6>0),K57*(CustoContábil!$F$18/CustoContábil!$F$6)*W57,0) -> 0 | Y57: =IF(AND(N57>0,CustoContábil!$D$6>0),N57*(CustoContábil!$D$18/CustoContábil!$D$6)*W57,0) -> 0
C58: Materiais e equipamentos | K58: =SUM(K8:K57) -> 0 | L58: =SUM(L8:L57) -> 0 | M58: =SUM(M8:M57) -> 0 | N58: =SUM(N8:N57) -> 0 | V58: Custo anualizado total - Sistemas Motrizes | W58: CAT MOTOR | X58: =SUM(X8:X57) -> 0 | Y58: =SUM(Y8:Y57) -> 0
B59: MÃO DE OBRA E ADMINISTRAÇÃO PRÓPRIA - CEMIG | K59: ORIGEM DOS RECURSOS
C60: Mão de obra própria - CEMIG | K60: =Apoio!AY6 -> 0 | N60: =K60 -> 0 | Q60: RCBMOTOR_PEE | R60: =RCB!$G$11 -> 0
C61: Auditoria Contábil e Financeira - CEMIG | K61: =Apoio!BH6 -> 0 | N61: =K61 -> 0 | Q61: RCBPEE | R61: =RCB!$H$9 -> 0
B62: Mão de obra de terceiros | I62: Quantidade | J62: Preço unitário | K62: PEE | L62: Terceiros | M62: Consumidor | N62: Total
B63: 1 | C63: Diagnóstico Energético - Rateio | K63: =Terceiros!K16 -> 0 | L63: =Terceiros!L16 -> 0 | M63: =Terceiros!M16 -> 0 | N63: =Terceiros!N16 -> 0
B64: 2 | C64: Gerenciamento do Projeto - Rateio | K64: =Terceiros!K27 -> 0 | L64: =Terceiros!L27 -> 0 | M64: =Terceiros!M27 -> 0 | N64: =Terceiros!N27 -> 0
B65: 3 | C65: Relatório Final - Rateio | K65: =Terceiros!K38 -> 0 | L65: =Terceiros!L38 -> 0 | M65: =Terceiros!M38 -> 0 | N65: =Terceiros!N38 -> 0
B66: 4 | K66: =N66-L66-M66 -> 0 | N66: =I66*J66 -> 0
B67: 5 | K67: =N67-L67-M67 -> 0 | N67: =I67*J67 -> 0
B68: 6 | K68: =N68-L68-M68 -> 0 | N68: =I68*J68 -> 0
B69: 7 | K69: =N69-L69-M69 -> 0 | N69: =I69*J69 -> 0
B70: 8 | K70: =N70-L70-M70 -> 0 | N70: =I70*J70 -> 0
B71: 9 | K71: =N71-L71-M71 -> 0 | N71: =I71*J71 -> 0
B72: 10 | K72: =N72-L72-M72 -> 0 | N72: =I72*J72 -> 0
B73: 11 | K73: =N73-L73-M73 -> 0 | N73: =I73*J73 -> 0
B74: 12 | K74: =N74-L74-M74 -> 0 | N74: =I74*J74 -> 0
B75: 13 | K75: =N75-L75-M75 -> 0 | N75: =I75*J75 -> 0
B76: 14 | K76: =N76-L76-M76 -> 0 | N76: =I76*J76 -> 0
B77: 15 | K77: =N77-L77-M77 -> 0 | N77: =I77*J77 -> 0
... B82: 20 | K82: =N82-L82-M82 -> 0 | N82: =I82*J82 -> 0
C83: Mão de obra de terceiros | K83: =SUM(K63:K82) -> 0 | L83: =SUM(L63:L82) -> 0 | M83: =SUM(M63:M82) -> 0 | N83: =SUM(N63:N82) -> 0
C84: Administração Própria - CEMIG | K84: =Apoio!BE6 -> 0 | N84: =K84 -> 0
J85: Sub total - Mão de obra de terceiros e Administração Própria CEMIG | K85: =SUM(K60,K61,K83,K84) -> 0 | L85: =L83 -> 0 | M85: =M83 -> 0 | N85: =SUM(N60,N61,N83,N84) -> 0
J86: Sub total - Custos diretos | K86: =SUM(K58,K85) -> 0 | L86: =SUM(L58,L85) -> 0 | M86: =SUM(M58,M85) -> 0 | N86: =SUM(N58,N85) -> 0
B87: CUSTOS INDIRETOS
B88: CUSTOS INDIRETOS | K88: ORIGEM DOS RECURSOS
C89: Marketing | K89: =Marketing!K32 -> 0 | L89: =Marketing!L32 -> 0 | M89: =Marketing!M32 -> 0 | N89: =Marketing!N32 -> 0
C90: Treinamento e capacitação | K90: =Treinamento!K32 -> 0 | L90: =Treinamento!L32 -> 0 | M90: =Treinamento!M32 -> 0 | N90: =Treinamento!N32 -> 0
B91: Descarte de materiais | I91: Quantidade | J91: Preço unitário | K91: PEE | L91: Terceiros | M91: Consumidor | N91: Total
B92: 1 | K92: =N92-L92-M92 -> 0 | N92: =I92*J92 -> 0
B93: 2 | K93: =N93-L93-M93 -> 0 | N93: =I93*J93 -> 0
B94: 3 | K94: =N94-L94-M94 -> 0 | N94: =I94*J94 -> 0
B95: 4 | K95: =N95-L95-M95 -> 0 | N95: =I95*J95 -> 0
B96: 5 | K96: =N96-L96-M96 -> 0 | N96: =I96*J96 -> 0
B97: 6 | K97: =N97-L97-M97 -> 0 | N97: =I97*J97 -> 0
B98: 7 | K98: =N98-L98-M98 -> 0 | N98: =I98*J98 -> 0
B99: 8 | K99: =N99-L99-M99 -> 0 | N99: =I99*J99 -> 0
B100: 9 | K100: =N100-L100-M100 -> 0 | N100: =I100*J100 -> 0
B101: 10 | K101: =N101-L101-M101 -> 0 | N101: =I101*J101 -> 0
B102: 11 | K102: =N102-L102-M102 -> 0 | N102: =I102*J102 -> 0
B103: 12 | K103: =N103-L103-M103 -> 0 | N103: =I103*J103 -> 0
... B111: 20 | K111: =N111-L111-M111 -> 0 | N111: =I111*J111 -> 0
C112: Descarte de materiais | K112: =SUM(K92:K111) -> 0 | L112: =SUM(L92:L111) -> 0 | M112: =SUM(M92:M111) -> 0 | N112: =SUM(N92:N111) -> 0
C113: Medição e verificação | K113: ='M&V'!J43 -> 0 | L113: ='M&V'!K43 -> 0 | M113: ='M&V'!L43 -> 0 | N113: ='M&V'!M43 -> 0
J114: Sub total - Custos indiretos | K114: =SUM(K89,K90,K112,K113) -> 0 | L114: =SUM(L89,L90,L112,L113) -> 0 | M114: =SUM(M89,M90,M112,M113) -> 0 | N114: =SUM(N89,N90,N112,N113) -> 0
J115: Custos Totais - Sistemas Motrizes | K115: =SUM(K86,K114) -> 0 | L115: =SUM(L86,L114) -> 0 | M115: =SUM(M86,M114) -> 0 | N115: =SUM(N86,N114) -> 0

Sheet MotorBenef
C2: Definição de | D2: SIST. MOT.:
B4: SISTEMAS MOTRIZES - SISTEMA ATUAL
B5: 0 | G5: TOTAL | H5: motor 1 | I5: motor 2 | J5: motor 3 | K5: motor 4 | L5: motor 5 | M5: motor 6 | N5: motor 7 | O5: motor 8 | P5: motor 9 | Q5: motor 10 | R5: motor 11 | S5: motor 12 | T5: motor 13 | U5: motor 14 | V5: motor 15 | W5: motor 16 | X5: motor 17 | Y5: motor 18 | Z5: motor 19 | AA5: motor 20 | AB5: motor 21 | AC5: motor 22 | AD5: motor 23 | AE5: motor 24 | AF5: motor 25 | AG5: motor 26 | AH5: motor 27 | AI5: motor 28 | AJ5: motor 29 | AK5: motor 30 | AL5: motor 31 | AM5: motor 32 | AN5: motor 33 | AO5: motor 34 | AP5: motor 35 | AQ5: motor 36 | AR5: motor 37 | AS5: motor 38 | AT5: motor 39 | AU5: motor 40 | AV5: motor 41 | AW5: motor 42 | AX5: motor 43 | AY5: motor 44 | AZ5: motor 45 | BA5: motor 46 | BB5: motor 47 | BC5: motor 48 | BD5: motor 49 | BE5: motor 50 | BF5: motor 51 | BG5: motor 52 | BH5: motor 53 | BI5: motor 54 | BJ5: motor 55 | BK5: motor 56 | BL5: motor 57 | BM5: motor 58 | BN5: motor 59 | BO5: motor 60 | BP5: motor 61 | BQ5: motor 62 | BR5: motor 63 | BS5: motor 64 | BT5: motor 65 | BU5: motor 66 | BV5: motor 67 | BW5: motor 68 | BX5: motor 69 | BY5: motor 70 | BZ5: motor 71 | CA5: motor 72 | CB5: motor 73 | CC5: motor 74 | CD5: motor 75 | CE5: motor 76 | CF5: motor 77 | CG5: motor 78 | CH5: motor 79 | CI5: motor 80 | CJ5: motor 81 | CK5: motor 82 | CL5: motor 83 | CM5: motor 84 | CN5: motor 85 | CO5: motor 86 | CP5: motor 87 | CQ5: motor 88 | CR5: motor 89 | CS5: motor 90 | CT5: motor 91 | CU5: motor 92 | CV5: motor 93 | CW5: motor 94 | CX5: motor 95 | CY5: motor 96 | CZ5: motor 97 | DA5: motor 98 | DB5: motor 99 | DC5: motor 100 | DD5: motor 101 | DE5: motor 102 | DF5: motor 103 | DG5: motor 104 | DH5: motor 105 | DI5: motor 106 | DJ5: motor 107 | DK5: motor 108 | DL5: motor 109 | DM5: motor 110 | DN5: motor 111 | DO5: motor 112 | DP5: motor 113 | DQ5: motor 114 | DR5: motor 115 | DS5: motor 116 | DT5: motor 117 | DU5: motor 118 | DV5: motor 119 | DW5: motor 120 | DX5: motor 121 | DY5: motor 122 | DZ5: motor 123 | EA5: motor 124 | EB5: motor 125 | EC5: motor 126 | ED5: motor 127 | EE5: motor 128 | EF5: motor 129 | EG5: motor 130 | EH5: motor 131 | EI5: motor 132 | EJ5: motor 133 | EK5: motor 134 | EL5: motor 135 | EM5: motor 136 | EN5: motor 137 | EO5: motor 138 | EP5: motor 139 | EQ5: motor 140 | ER5: motor 141 | ES5: motor 142 | ET5: motor 143 | EU5: motor 144 | EV5: motor 145 | EW5: motor 146 | EX5: motor 147 | EY5: motor 148 | EZ5: motor 149 | FA5: motor 150
B6: 1 | C6: Unidade Consumidora
B7: 2 | C7: Potência do motor | E7: cv | F7: pai | G7: =IF(COUNTA(H7:FA7)=0,"",IF(SMALL(H7:FA7,1)<0,"ERRO",""))
B8: =B7+1 -> 3 | C8: Carregamento | E8: % | F8: γai | G8: =IF(COUNTA(H8:FA8)=0,"",IF(SMALL(H8:FA8,1)<0,"ERRO",""))
B9: =B8+1 -> 4 | C9: Rendimento nominal | E9: % | F9: ηnai | G9: =IF(COUNTA(H9:FA9)=0,"",IF(OR(SMALL(H9:FA9,1)<0,LARGE(H9:FA9,1)>1),"ERRO",""))
B10: 4a | C10: Rendimento no ponto de carregamento | E10: % | F10: ηai | G10: =IF(COUNTA(H10:FA10)=0,"",IF(OR(SMALL(H10:FA10,1)<0,LARGE(H10:FA10,1)>1),"ERRO",""))
B11: =B9+1 -> 5 | C11: Quantidade | F11: qai | G11: =IF(COUNTA(H11:FA11)=0,"",IF(SMALL(H11:FA11,1)<0,"ERRO",SUM(H11:FA11)))
B12: =B11+1 -> 6 | C12: Potência instalada | E12: kW | F12: Pai | G12: =SUM(H12:FA12) -> 0 | H12: =IF(H9=0,0,H7*0.736*H11/H9) -> 0 | I12: =IF(I9=0,0,I7*0.736*I11/I9) -> 0 | J12: =IF(J9=0,0,J7*0.736*J11/J9) -> 0 | K12: =IF(K9=0,0,K7*0.736*K11/K9) -> 0 | L12: =IF(L9=0,0,L7*0.736*L11/L9) -> 0 | M12: =IF(M9=0,0,M7*0.736*M11/M9) -> 0 | N12: =IF(N9=0,0,N7*0.736*N11/N9) -> 0 | O12: =IF(O9=0,0,O7*0.736*O11/O9) -> 0 | ... FA12: =IF(FA9=0,0,FA7*0.736*FA11/FA9) -> 0
B13: =B12+1 -> 7 | C13: Potência média utilizada | E13: kW | F13: Puai | G13: =SUM(H13:FA13) -> 0 | H13: =IF(H11=0,0,H12*H8*H9/H10) -> 0 | I13: =IF(I11=0,0,I12*I8*I9/I10) -> 0 | J13: =IF(J11=0,0,J12*J8*J9/J10) -> 0 | K13: =IF(K11=0,0,K12*K8*K9/K10) -> 0 | L13: =IF(L11=0,0,L12*L8*L9/L10) -> 0 | M13: =IF(M11=0,0,M12*M8*M9/M10) -> 0 | N13: =IF(N11=0,0,N12*N8*N9/N10) -> 0 | O13: =IF(O11=0,0,O12*O8*O9/O10) -> 0 | ... FA13: =IF(FA11=0,0,FA12*FA8*FA9/FA10) -> 0
B14: =B13+1 -> 8 | C14: Tempo de utilização do sistema, em um dia | E14: h/dia | G14: =IF(COUNTA(H14:FA14)=0,"",IF(OR(LARGE(H14:FA14,1)>24,SMALL(H14:FA14,1)<0),"ERRO",""))
C15: Dias de utilização do sistema, em um ano | E15: dia/ano | G15: =IF(COUNTA(H15:FA15)=0,"",IF(OR(LARGE(H15:FA15,1)>365,SMALL(H15:FA15,1)<0),"ERRO",""))
C16: Funcionamento | E16: h/ano | F16: hai | G16: =IF(COUNTA(H16:FA16)=0,"",IF(OR(LARGE(H16:FA16,1)>8760,SMALL(H16:FA16,1)<0),"ERRO","")) | H16: =H14*H15 -> 0 | I16: =I14*I15 -> 0 | J16: =J14*J15 -> 0 | K16: =K14*K15 -> 0 | L16: =L14*L15 -> 0 | M16: =M14*M15 -> 0 | N16: =N14*N15 -> 0 | O16: =O14*O15 -> 0 | ... FA16: =FA14*FA15 -> 0
B17: =B14+1 -> 9 | C17: Horas de utilização em horário de ponta, em um dia | E17: h/dia | F17: nupai | G17: =IF(COUNTA(H17:FA17)=0,"",IF(OR(LARGE(H17:FA17,1)>3,SMALL(H17:FA17,1)<0),"ERRO",""))
C18: Dias úteis de utilização em horário de ponta, em um mês | E18: dia/mês | F18: ndai | G18: =IF(COUNTA(H18:FA18)=0,"",IF(OR(LARGE(H18:FA18,1)>22,SMALL(H18:FA18,1)<0),"ERRO",""))
C19: Meses de utilização em horário de ponta, em um ano | E19: mês/ano | F19: nmai | G19: =IF(COUNTA(H19:FA19)=0,"",IF(OR(LARGE(H19:FA19,1)>12,SMALL(H19:FA19,1)<0),"ERRO",""))
C20: Fator de coincidência na ponta | F20: FCPai | G20: =IF(COUNTA(H20:FA20)=0,"",IF(OR(LARGE(H20:FA20,1)>1,SMALL(H20:FA20,1)<0),"ERRO","")) | H20: =H17*H18*H19/792 -> 0 | I20: =I17*I18*I19/792 -> 0 | J20: =J17*J18*J19/792 -> 0 | K20: =K17*K18*K19/792 -> 0 | L20: =L17*L18*L19/792 -> 0 | M20: =M17*M18*M19/792 -> 0 | N20: =N17*N18*N19/792 -> 0 | O20: =O17*O18*O19/792 -> 0 | ... FA20: =FA17*FA18*FA19/792 -> 0
B21: =B17+1 -> 10 | C21: Energia consumida | E21: MWh/ano | F21: Eai | G21: =SUM(H21:FA21) -> 0 | H21: =H13*H16/1000 -> 0 | I21: =I13*I16/1000 -> 0 | J21: =J13*J16/1000 -> 0 | K21: =K13*K16/1000 -> 0 | L21: =L13*L16/1000 -> 0 | M21: =M13*M16/1000 -> 0 | N21: =N13*N16/1000 -> 0 | O21: =O13*O16/1000 -> 0 | ... FA21: =FA13*FA16/1000 -> 0
B22: =B21+1 -> 11 | C22: Demanda média na ponta | E22: kW | F22: Dai | G22: =SUM(H22:FA22) -> 0 | H22: =H13*H20 -> 0 | I22: =I13*I20 -> 0 | J22: =J13*J20 -> 0 | K22: =K13*K20 -> 0 | L22: =L13*L20 -> 0 | M22: =M13*M20 -> 0 | N22: =N13*N20 -> 0 | O22: =O13*O20 -> 0 | ... FA22: =FA13*FA20 -> 0
B24: SISTEMAS MOTRIZES - SISTEMA PROPOSTO
G25: TOTAL | H25: motor 1 | I25: motor 2 | J25: motor 3 | K25: motor 4 | L25: motor 5 | M25: motor 6 | N25: motor 7 | O25: motor 8 | P25: motor 9 | Q25: motor 10 | R25: motor 11 | S25: motor 12 | T25: motor 13 | U25: motor 14 | V25: motor 15 | W25: motor 16 | X25: motor 17 | Y25: motor 18 | Z25: motor 19 | AA25: motor 20 | AB25: motor 21 | AC25: motor 22 | AD25: motor 23 | AE25: motor 24 | AF25: motor 25 | AG25: motor 26 | AH25: motor 27 | AI25: motor 28 | AJ25: motor 29 | AK25: motor 30 | AL25: motor 31 | AM25: motor 32 | AN25: motor 33 | AO25: motor 34 | AP25: motor 35 | AQ25: motor 36 | AR25: motor 37 | AS25: motor 38 | AT25: motor 39 | AU25: motor 40 | AV25: motor 41 | AW25: motor 42 | AX25: motor 43 | AY25: motor 44 | AZ25: motor 45 | BA25: motor 46 | BB25: motor 47 | BC25: motor 48 | BD25: motor 49 | BE25: motor 50 | BF25: motor 51 | BG25: motor 52 | BH25: motor 53 | BI25: motor 54 | BJ25: motor 55 | BK25: motor 56 | BL25: motor 57 | BM25: motor 58 | BN25: motor 59 | BO25: motor 60 | BP25: motor 61 | BQ25: motor 62 | BR25: motor 63 | BS25: motor 64 | BT25: motor 65 | BU25: motor 66 | BV25: motor 67 | BW25: motor 68 | BX25: motor 69 | BY25: motor 70 | BZ25: motor 71 | CA25: motor 72 | CB25: motor 73 | CC25: motor 74 | CD25: motor 75 | CE25: motor 76 | CF25: motor 77 | CG25: motor 78 | CH25: motor 79 | CI25: motor 80 | CJ25: motor 81 | CK25: motor 82 | CL25: motor 83 | CM25: motor 84 | CN25: motor 85 | CO25: motor 86 | CP25: motor 87 | CQ25: motor 88 | CR25: motor 89 | CS25: motor 90 | CT25: motor 91 | CU25: motor 92 | CV25: motor 93 | CW25: motor 94 | CX25: motor 95 | CY25: motor 96 | CZ25: motor 97 | DA25: motor 98 | DB25: motor 99 | DC25: motor 100 | DD25: motor 101 | DE25: motor 102 | DF25: motor 103 | DG25: motor 104 | DH25: motor 105 | DI25: motor 106 | DJ25: motor 107 | DK25: motor 108 | DL25: motor 109 | DM25: motor 110 | DN25: motor 111 | DO25: motor 112 | DP25: motor 113 | DQ25: motor 114 | DR25: motor 115 | DS25: motor 116 | DT25: motor 117 | DU25: motor 118 | DV25: motor 119 | DW25: motor 120 | DX25: motor 121 | DY25: motor 122 | DZ25: motor 123 | EA25: motor 124 | EB25: motor 125 | EC25: motor 126 | ED25: motor 127 | EE25: motor 128 | EF25: motor 129 | EG25: motor 130 | EH25: motor 131 | EI25: motor 132 | EJ25: motor 133 | EK25: motor 134 | EL25: motor 135 | EM25: motor 136 | EN25: motor 137 | EO25: motor 138 | EP25: motor 139 | EQ25: motor 140 | ER25: motor 141 | ES25: motor 142 | ET25: motor 143 | EU25: motor 144 | EV25: motor 145 | EW25: motor 146 | EX25: motor 147 | EY25: motor 148 | EZ25: motor 149 | FA25: motor 150
B26: =B22+1 -> 12 | C26: Unidade Consumidora | H26: =IF(H6="","",H6) | I26: =IF(I6="","",I6) | J26: =IF(J6="","",J6) | K26: =IF(K6="","",K6) | L26: =IF(L6="","",L6) | M26: =IF(M6="","",M6) | N26: =IF(N6="","",N6) | O26: =IF(O6="","",O6) | ... FA26: =IF(FA6="","",FA6)
B27: =B26+1 -> 13 | C27: Potência do motor | E27: cv | F27: ppi | G27: =IF(COUNTA(H27:FA27)=0,"",IF(SMALL(H27:FA27,1)<0,"ERRO",""))
B28: =B27+1 -> 14 | C28: Carregamento | E28: % | F28: γpi | G28: =IF(COUNTA(H28:FA28)=0,"",IF(SMALL(H28:FA28,1)<0,"ERRO",""))
B29: =B28+1 -> 15 | C29: Rendimento nominal | E29: % | F29: ηnpi | G29: =IF(COUNTA(H29:FA29)=0,"",IF(OR(SMALL(H29:FA29,1)<0,LARGE(H29:FA29,1)>1),"ERRO",""))
B30: 15a | C30: Rendimento no ponto de carregamento | E30: % | F30: ηpi | G30: =IF(COUNTA(H30:FA30)=0,"",IF(OR(SMALL(H30:FA30,1)<0,LARGE(H30:FA30,1)>1),"ERRO",""))
B31: =B29+1 -> 16 | C31: Quantidade | F31: qpi | G31: =IF(COUNTA(H31:FA31)=0,"",IF(SMALL(H31:FA31,1)<0,"ERRO",SUM(H31:FA31)))
B32: =B31+1 -> 17 | C32: Potência instalada | E32: kW | F32: Ppi | G32: =SUM(H32:FA32) -> 0 | H32: =IF(H29=0,0,H27*0.736*H31/H29) -> 0 | I32: =IF(I29=0,0,I27*0.736*I31/I29) -> 0 | J32: =IF(J29=0,0,J27*0.736*J31/J29) -> 0 | K32: =IF(K29=0,0,K27*0.736*K31/K29) -> 0 | L32: =IF(L29=0,0,L27*0.736*L31/L29) -> 0 | M32: =IF(M29=0,0,M27*0.736*M31/M29) -> 0 | N32: =IF(N29=0,0,N27*0.736*N31/N29) -> 0 | O32: =IF(O29=0,0,O27*0.736*O31/O29) -> 0 | ... FA32: =IF(FA29=0,0,FA27*0.736*FA31/FA29) -> 0
B33: =B32+1 -> 18 | C33: Potência média utilizada | E33: kW | F33: Pupi | G33: =SUM(H33:FA33) -> 0 | H33: =IF(H31=0,0,H27*0.736*H28/H30*H31) -> 0 | I33: =IF(I31=0,0,I27*0.736*I28/I30*I31) -> 0 | J33: =IF(J31=0,0,J27*0.736*J28/J30*J31) -> 0 | K33: =IF(K31=0,0,K27*0.736*K28/K30*K31) -> 0 | L33: =IF(L31=0,0,L27*0.736*L28/L30*L31) -> 0 | M33: =IF(M31=0,0,M27*0.736*M28/M30*M31) -> 0 | N33: =IF(N31=0,0,N27*0.736*N28/N30*N31) -> 0 | O33: =IF(O31=0,0,O27*0.736*O28/O30*O31) -> 0 | ... FA33: =IF(FA31=0,0,FA27*0.736*FA28/FA30*FA31) -> 0
B34: =B33+1 -> 19 | C34: Tempo de utilização do sistema, em um dia | E34: h/dia | G34: =IF(COUNTA(H34:FA34)=0,"",IF(OR(LARGE(H34:FA34,1)>24,SMALL(H34:FA34,1)<0),"ERRO",""))
C35: Dias de utilização do sistema, em um ano | E35: dia/ano | G35: =IF(COUNTA(H35:FA35)=0,"",IF(OR(LARGE(H35:FA35,1)>365,SMALL(H35:FA35,1)<0),"ERRO",""))
C36: Funcionamento | E36: h/ano | F36: hpi | G36: =IF(COUNTA(H36:FA36)=0,"",IF(OR(LARGE(H36:FA36,1)>8760,SMALL(H36:FA36,1)<0),"ERRO","")) | H36: =H34*H35 -> 0 | I36: =I34*I35 -> 0 | J36: =J34*J35 -> 0 | K36: =K34*K35 -> 0 | L36: =L34*L35 -> 0 | M36: =M34*M35 -> 0 | N36: =N34*N35 -> 0 | O36: =O34*O35 -> 0 | ... FA36: =FA34*FA35 -> 0
B37: =B34+1 -> 20 | C37: Horas de utilização em horário de ponta, em um dia | E37: h/dia | F37: nuppi | G37: =IF(COUNTA(H37:FA37)=0,"",IF(OR(LARGE(H37:FA37,1)>3,SMALL(H37:FA37,1)<0),"ERRO",""))
C38: Dias úteis de utilização em horário de ponta, em um mês | E38: dia/mês | F38: ndpi | G38: =IF(COUNTA(H38:FA38)=0,"",IF(OR(LARGE(H38:FA38,1)>22,SMALL(H38:FA38,1)<0),"ERRO",""))
C39: Meses de utilização em horário de ponta, em um ano | E39: mês/ano | F39: nmpi | G39: =IF(COUNTA(H39:FA39)=0,"",IF(OR(LARGE(H39:FA39,1)>12,SMALL(H39:FA39,1)<0),"ERRO",""))
C40: Fator de coincidência na ponta | F40: FCPpi | G40: =IF(COUNTA(H40:FA40)=0,"",IF(OR(LARGE(H40:FA40,1)>1,SMALL(H40:FA40,1)<0),"ERRO","")) | H40: =H37*H38*H39/792 -> 0 | I40: =I37*I38*I39/792 -> 0 | J40: =J37*J38*J39/792 -> 0 | K40: =K37*K38*K39/792 -> 0 | L40: =L37*L38*L39/792 -> 0 | M40: =M37*M38*M39/792 -> 0 | N40: =N37*N38*N39/792 -> 0 | O40: =O37*O38*O39/792 -> 0 | ... FA40: =FA37*FA38*FA39/792 -> 0
B41: =B37+1 -> 21 | C41: Energia consumida | E41: MWh/ano | F41: Epi | G41: =SUM(H41:FA41) -> 0 | H41: =H33*H36/1000 -> 0 | I41: =I33*I36/1000 -> 0 | J41: =J33*J36/1000 -> 0 | K41: =K33*K36/1000 -> 0 | L41: =L33*L36/1000 -> 0 | M41: =M33*M36/1000 -> 0 | N41: =N33*N36/1000 -> 0 | O41: =O33*O36/1000 -> 0 | ... FA41: =FA33*FA36/1000 -> 0
B42: =B41+1 -> 22 | C42: Demanda média na ponta | E42: kW | F42: Dpi | G42: =SUM(H42:FA42) -> 0 | H42: =H33*H40 -> 0 | I42: =I33*I40 -> 0 | J42: =J33*J40 -> 0 | K42: =K33*K40 -> 0 | L42: =L33*L40 -> 0 | M42: =M33*M40 -> 0 | N42: =N33*N40 -> 0 | O42: =O33*O40 -> 0 | ... FA42: =FA33*FA40 -> 0
B44: SISTEMAS MOTRIZES - RESULTADO ESPERADO
G45: TOTAL | H45: motor 1 | I45: motor 2 | J45: motor 3 | K45: motor 4 | L45: motor 5 | M45: motor 6 | N45: motor 7 | O45: motor 8 | P45: motor 9 | Q45: motor 10 | R45: motor 11 | S45: motor 12 | T45: motor 13 | U45: motor 14 | V45: motor 15 | W45: motor 16 | X45: motor 17 | Y45: motor 18 | Z45: motor 19 | AA45: motor 20 | AB45: motor 21 | AC45: motor 22 | AD45: motor 23 | AE45: motor 24 | AF45: motor 25 | AG45: motor 26 | AH45: motor 27 | AI45: motor 28 | AJ45: motor 29 | AK45: motor 30 | AL45: motor 31 | AM45: motor 32 | AN45: motor 33 | AO45: motor 34 | AP45: motor 35 | AQ45: motor 36 | AR45: motor 37 | AS45: motor 38 | AT45: motor 39 | AU45: motor 40 | AV45: motor 41 | AW45: motor 42 | AX45: motor 43 | AY45: motor 44 | AZ45: motor 45 | BA45: motor 46 | BB45: motor 47 | BC45: motor 48 | BD45: motor 49 | BE45: motor 50 | BF45: motor 51 | BG45: motor 52 | BH45: motor 53 | BI45: motor 54 | BJ45: motor 55 | BK45: motor 56 | BL45: motor 57 | BM45: motor 58 | BN45: motor 59 | BO45: motor 60 | BP45: motor 61 | BQ45: motor 62 | BR45: motor 63 | BS45: motor 64 | BT45: motor 65 | BU45: motor 66 | BV45: motor 67 | BW45: motor 68 | BX45: motor 69 | BY45: motor 70 | BZ45: motor 71 | CA45: motor 72 | CB45: motor 73 | CC45: motor 74 | CD45: motor 75 | CE45: motor 76 | CF45: motor 77 | CG45: motor 78 | CH45: motor 79 | CI45: motor 80 | CJ45: motor 81 | CK45: motor 82 | CL45: motor 83 | CM45: motor 84 | CN45: motor 85 | CO45: motor 86 | CP45: motor 87 | CQ45: motor 88 | CR45: motor 89 | CS45: motor 90 | CT45: motor 91 | CU45: motor 92 | CV45: motor 93 | CW45: motor 94 | CX45: motor 95 | CY45: motor 96 | CZ45: motor 97 | DA45: motor 98 | DB45: motor 99 | DC45: motor 100 | DD45: motor 101 | DE45: motor 102 | DF45: motor 103 | DG45: motor 104 | DH45: motor 105 | DI45: motor 106 | DJ45: motor 107 | DK45: motor 108 | DL45: motor 109 | DM45: motor 110 | DN45: motor 111 | DO45: motor 112 | DP45: motor 113 | DQ45: motor 114 | DR45: motor 115 | DS45: motor 116 | DT45: motor 117 | DU45: motor 118 | DV45: motor 119 | DW45: motor 120 | DX45: motor 121 | DY45: motor 122 | DZ45: motor 123 | EA45: motor 124 | EB45: motor 125 | EC45: motor 126 | ED45: motor 127 | EE45: motor 128 | EF45: motor 129 | EG45: motor 130 | EH45: motor 131 | EI45: motor 132 | EJ45: motor 133 | EK45: motor 134 | EL45: motor 135 | EM45: motor 136 | EN45: motor 137 | EO45: motor 138 | EP45: motor 139 | EQ45: motor 140 | ER45: motor 141 | ES45: motor 142 | ET45: motor 143 | EU45: motor 144 | EV45: motor 145 | EW45: motor 146 | EX45: motor 147 | EY45: motor 148 | EZ45: motor 149 | FA45: motor 150
B46: =B42+1 -> 23 | C46: Redução de demanda na ponta | E46: kW | F46: RDPi | G46: =SUM(H46:FA46) -> 0 | H46: =H22-H42 -> 0 | I46: =I22-I42 -> 0 | J46: =J22-J42 -> 0 | K46: =K22-K42 -> 0 | L46: =L22-L42 -> 0 | M46: =M22-M42 -> 0 | N46: =N22-N42 -> 0 | O46: =O22-O42 -> 0 | ... FA46: =FA22-FA42 -> 0
B47: =B46+1 -> 24 | C47: Custo evitado de demanda (CED) = | D47: =Projeto!$L$44 -> 0 | E47: % | F47: RDPi% | G47: =IF(G22=0,0,G46/G22) -> 0 | H47: =IF(H22=0,0,H46/H22) -> 0 | I47: =IF(I22=0,0,I46/I22) -> 0 | J47: =IF(J22=0,0,J46/J22) -> 0 | K47: =IF(K22=0,0,K46/K22) -> 0 | L47: =IF(L22=0,0,L46/L22) -> 0 | M47: =IF(M22=0,0,M46/M22) -> 0 | N47: =IF(N22=0,0,N46/N22) -> 0 | ... FA47: =IF(FA22=0,0,FA46/FA22) -> 0
B48: =B47+1 -> 25 | C48: Energia economizada | E48: MWh/ano | F48: EEi | G48: =SUM(H48:FA48) -> 0 | H48: =H21-H41 -> 0 | I48: =I21-I41 -> 0 | J48: =J21-J41 -> 0 | K48: =K21-K41 -> 0 | L48: =L21-L41 -> 0 | M48: =M21-M41 -> 0 | N48: =N21-N41 -> 0 | O48: =O21-O41 -> 0 | ... FA48: =FA21-FA41 -> 0
B49: =B48+1 -> 26 | C49: Custo da energia evitada (CEE) = | D49: =Projeto!$L$43 -> 0 | E49: % | F49: EEi% | G49: =IF(G21=0,0,G48/G21) -> 0 | H49: =IF(H21=0,0,H48/H21) -> 0 | I49: =IF(I21=0,0,I48/I21) -> 0 | J49: =IF(J21=0,0,J48/J21) -> 0 | K49: =IF(K21=0,0,K48/K21) -> 0 | L49: =IF(L21=0,0,L48/L21) -> 0 | M49: =IF(M21=0,0,M48/M21) -> 0 | N49: =IF(N21=0,0,N48/N21) -> 0 | ... FA49: =IF(FA21=0,0,FA48/FA21) -> 0
C50: Benefício anualizado - Sistemas Motrizes | E50: R$ | F50: BMOTOR | G50: =SUM(H50:FA50) -> 0 | H50: =H46*$D$47+H48*$D$49 -> 0 | I50: =I46*$D$47+I48*$D$49 -> 0 | J50: =J46*$D$47+J48*$D$49 -> 0 | K50: =K46*$D$47+K48*$D$49 -> 0 | L50: =L46*$D$47+L48*$D$49 -> 0 | M50: =M46*$D$47+M48*$D$49 -> 0 | N50: =N46*$D$47+N48*$D$49 -> 0 | O50: =O46*$D$47+O48*$D$49 -> 0 | ... FA50: =FA46*$D$47+FA48*$D$49 -> 0
F52: RCBMOTOR_PEE | G52: =RCB!$G$11 -> 0
F53: RCBPEE | G53: =RCB!$H$9 -> 0

Sheet RefrigCusto
B4: SISTEMAS DE REFRIGERAÇÃO | P4: =B4 -> SISTEMAS DE REFRIGERAÇÃO
B5: CUSTOS DIRETOS | P5: CUSTOS ANUALIZADOS
B6: MATERIAIS E EQUIPAMENTOS | K6: ORIGEM DOS RECURSOS | P6: MATERIAIS E EQUIPAMENTOS | X6: ORIGEM DOS RECURSOS
B7: Materiais e equipamentos | H7: Vida útil (anos) | I7: Quantidade | J7: Preço unitário | K7: PEE | L7: Terceiros | M7: Consumidor | N7: Total | P7: =B7 -> Materiais e equipamentos | V7: Vida útil | W7: FRC | X7: CAPEE | Y7: CATOTAL
B8: 1 | K8: =N8-L8-M8 -> 0 | N8: =I8*J8 -> 0 | P8: =B8 -> 1 | Q8: =IF(OR(C8=0,C8=""),"",C8) | V8: =IF(N8=0,"",H8) | W8: =IF(OR(V8="",V8=0),0,(Projeto!$AD$10*((1+Projeto!$AD$10)^V8))/(((1+Projeto!$AD$10)^V8)-1)) -> 0 | X8: =IF(AND(K8>0,CustoContábil!$F$6>0),K8*(CustoContábil!$F$18/CustoContábil!$F$6)*W8,0) -> 0 | Y8: =IF(AND(N8>0,CustoContábil!$D$6>0),N8*(CustoContábil!$D$18/CustoContábil!$D$6)*W8,0) -> 0
B9: 2 | K9: =N9-L9-M9 -> 0 | N9: =I9*J9 -> 0 | P9: =B9 -> 2 | Q9: =IF(OR(C9=0,C9=""),"",C9) | V9: =IF(N9=0,"",H9) | W9: =IF(OR(V9="",V9=0),0,(Projeto!$AD$10*((1+Projeto!$AD$10)^V9))/(((1+Projeto!$AD$10)^V9)-1)) -> 0 | X9: =IF(AND(K9>0,CustoContábil!$F$6>0),K9*(CustoContábil!$F$18/CustoContábil!$F$6)*W9,0) -> 0 | Y9: =IF(AND(N9>0,CustoContábil!$D$6>0),N9*(CustoContábil!$D$18/CustoContábil!$D$6)*W9,0) -> 0
B10: 3 | K10: =N10-L10-M10 -> 0 | N10: =I10*J10 -> 0 | P10: =B10 -> 3 | Q10: =IF(OR(C10=0,C10=""),"",C10) | V10: =IF(N10=0,"",H10) | W10: =IF(OR(V10="",V10=0),0,(Projeto!$AD$10*((1+Projeto!$AD$10)^V10))/(((1+Projeto!$AD$10)^V10)-1)) -> 0 | X10: =IF(AND(K10>0,CustoContábil!$F$6>0),K10*(CustoContábil!$F$18/CustoContábil!$F$6)*W10,0) -> 0 | Y10: =IF(AND(N10>0,CustoContábil!$D$6>0),N10*(CustoContábil!$D$18/CustoContábil!$D$6)*W10,0) -> 0
B11: 4 | K11: =N11-L11-M11 -> 0 | N11: =I11*J11 -> 0 | P11: =B11 -> 4 | Q11: =IF(OR(C11=0,C11=""),"",C11) | V11: =IF(N11=0,"",H11) | W11: =IF(OR(V11="",V11=0),0,(Projeto!$AD$10*((1+Projeto!$AD$10)^V11))/(((1+Projeto!$AD$10)^V11)-1)) -> 0 | X11: =IF(AND(K11>0,CustoContábil!$F$6>0),K11*(CustoContábil!$F$18/CustoContábil!$F$6)*W11,0) -> 0 | Y11: =IF(AND(N11>0,CustoContábil!$D$6>0),N11*(CustoContábil!$D$18/CustoContábil!$D$6)*W11,0) -> 0
B12: 5 | K12: =N12-L12-M12 -> 0 | N12: =I12*J12 -> 0 | P12: =B12 -> 5 | Q12: =IF(OR(C12=0,C12=""),"",C12) | V12: =IF(N12=0,"",H12) | W12: =IF(OR(V12="",V12=0),0,(Projeto!$AD$10*((1+Projeto!$AD$10)^V12))/(((1+Projeto!$AD$10)^V12)-1)) -> 0 | X12: =IF(AND(K12>0,CustoContábil!$F$6>0),K12*(CustoContábil!$F$18/CustoContábil!$F$6)*W12,0) -> 0 | Y12: =IF(AND(N12>0,CustoContábil!$D$6>0),N12*(CustoContábil!$D$18/CustoContábil!$D$6)*W12,0) -> 0
B13: 6 | K13: =N13-L13-M13 -> 0 | N13: =I13*J13 -> 0 | P13: =B13 -> 6 | Q13: =IF(OR(C13=0,C13=""),"",C13) | V13: =IF(N13=0,"",H13) | W13: =IF(OR(V13="",V13=0),0,(Projeto!$AD$10*((1+Projeto!$AD$10)^V13))/(((1+Projeto!$AD$10)^V13)-1)) -> 0 | X13: =IF(AND(K13>0,CustoContábil!$F$6>0),K13*(CustoContábil!$F$18/CustoContábil!$F$6)*W13,0) -> 0 | Y13: =IF(AND(N13>0,CustoContábil!$D$6>0),N13*(CustoContábil!$D$18/CustoContábil!$D$6)*W13,0) -> 0
B14: 7 | K14: =N14-L14-M14 -> 0 | N14: =I14*J14 -> 0 | P14: =B14 -> 7 | Q14: =IF(OR(C14=0,C14=""),"",C14) | V14: =IF(N14=0,"",H14) | W14: =IF(OR(V14="",V14=0),0,(Projeto!$AD$10*((1+Projeto!$AD$10)^V14))/(((1+Projeto!$AD$10)^V14)-1)) -> 0 | X14: =IF(AND(K14>0,CustoContábil!$F$6>0),K14*(CustoContábil!$F$18/CustoContábil!$F$6)*W14,0) -> 0 | Y14: =IF(AND(N14>0,CustoContábil!$D$6>0),N14*(CustoContábil!$D$18/CustoContábil!$D$6)*W14,0) -> 0
B15: 8 | K15: =N15-L15-M15 -> 0 | N15: =I15*J15 -> 0 | P15: =B15 -> 8 | Q15: =IF(OR(C15=0,C15=""),"",C15) | V15: =IF(N15=0,"",H15) | W15: =IF(OR(V15="",V15=0),0,(Projeto!$AD$10*((1+Projeto!$AD$10)^V15))/(((1+Projeto!$AD$10)^V15)-1)) -> 0 | X15: =IF(AND(K15>0,CustoContábil!$F$6>0),K15*(CustoContábil!$F$18/CustoContábil!$F$6)*W15,0) -> 0 | Y15: =IF(AND(N15>0,CustoContábil!$D$6>0),N15*(CustoContábil!$D$18/CustoContábil!$D$6)*W15,0) -> 0
B16: 9 | K16: =N16-L16-M16 -> 0 | N16: =I16*J16 -> 0 | P16: =B16 -> 9 | Q16: =IF(OR(C16=0,C16=""),"",C16) | V16: =IF(N16=0,"",H16) | W16: =IF(OR(V16="",V16=0),0,(Projeto!$AD$10*((1+Projeto!$AD$10)^V16))/(((1+Projeto!$AD$10)^V16)-1)) -> 0 | X16: =IF(AND(K16>0,CustoContábil!$F$6>0),K16*(CustoContábil!$F$18/CustoContábil!$F$6)*W16,0) -> 0 | Y16: =IF(AND(N16>0,CustoContábil!$D$6>0),N16*(CustoContábil!$D$18/CustoContábil!$D$6)*W16,0) -> 0
B17: 10 | K17: =N17-L17-M17 -> 0 | N17: =I17*J17 -> 0 | P17: =B17 -> 10 | Q17: =IF(OR(C17=0,C17=""),"",C17) | V17: =IF(N17=0,"",H17) | W17: =IF(OR(V17="",V17=0),0,(Projeto!$AD$10*((1+Projeto!$AD$10)^V17))/(((1+Projeto!$AD$10)^V17)-1)) -> 0 | X17: =IF(AND(K17>0,CustoContábil!$F$6>0),K17*(CustoContábil!$F$18/CustoContábil!$F$6)*W17,0) -> 0 | Y17: =IF(AND(N17>0,CustoContábil!$D$6>0),N17*(CustoContábil!$D$18/CustoContábil!$D$6)*W17,0) -> 0
B18: 11 | K18: =N18-L18-M18 -> 0 | N18: =I18*J18 -> 0 | P18: =B18 -> 11 | Q18: =IF(OR(C18=0,C18=""),"",C18) | V18: =IF(N18=0,"",H18) | W18: =IF(OR(V18="",V18=0),0,(Projeto!$AD$10*((1+Projeto!$AD$10)^V18))/(((1+Projeto!$AD$10)^V18)-1)) -> 0 | X18: =IF(AND(K18>0,CustoContábil!$F$6>0),K18*(CustoContábil!$F$18/CustoContábil!$F$6)*W18,0) -> 0 | Y18: =IF(AND(N18>0,CustoContábil!$D$6>0),N18*(CustoContábil!$D$18/CustoContábil!$D$6)*W18,0) -> 0
B19: 12 | K19: =N19-L19-M19 -> 0 | N19: =I19*J19 -> 0 | P19: =B19 -> 12 | Q19: =IF(OR(C19=0,C19=""),"",C19) | V19: =IF(N19=0,"",H19) | W19: =IF(OR(V19="",V19=0),0,(Projeto!$AD$10*((1+Projeto!$AD$10)^V19))/(((1+Projeto!$AD$10)^V19)-1)) -> 0 | X19: =IF(AND(K19>0,CustoContábil!$F$6>0),K19*(CustoContábil!$F$18/CustoContábil!$F$6)*W19,0) -> 0 | Y19: =IF(AND(N19>0,CustoContábil!$D$6>0),N19*(CustoContábil!$D$18/CustoContábil!$D$6)*W19,0) -> 0
... B57: 50 | K57: =N57-L57-M57 -> 0 | N57: =I57*J57 -> 0 | P57: =B57 -> 50 | Q57: =IF(OR(C57=0,C57=""),"",C57) | V57: =IF(N57=0,"",H57) | W57: =IF(OR(V57="",V57=0),0,(Projeto!$AD$10*((1+Projeto!$AD$10)^V57))/(((1+Projeto!$AD$10)^V57)-1)) -> 0 | X57: =IF(AND(K57>0,CustoContábil!$F$6>0),K57*(CustoContábil!$F$18/CustoContábil!$F$6)*W57,0) -> 0 | Y57: =IF(AND(N57>0,CustoContábil!$D$6>0),N57*(CustoContábil!$D$18/CustoContábil!$D$6)*W57,0) -> 0
C58: Materiais e equipamentos | K58: =SUM(K8:K57) -> 0 | L58: =SUM(L8:L57) -> 0 | M58: =SUM(M8:M57) -> 0 | N58: =SUM(N8:N57) -> 0 | V58: Custo anualizado total - Sistemas de Refrigeração | W58: CAT REFRIG | X58: =SUM(X8:X57) -> 0 | Y58: =SUM(Y8:Y57) -> 0
B59: MÃO DE OBRA E ADMINISTRAÇÃO PRÓPRIA - CEMIG | K59: ORIGEM DOS RECURSOS
C60: Mão de obra própria - CEMIG | K60: =Apoio!AY7 -> 0 | N60: =K60 -> 0 | Q60: RCBREFRIG_PEE | R60: =RCB!$G$12 -> 0
C61: Auditoria Contábil e Financeira - CEMIG | K61: =Apoio!BH7 -> 0 | N61: =K61 -> 0 | Q61: RCBPEE | R61: =RCB!$H$9 -> 0
B62: Mão de obra de terceiros | I62: Quantidade | J62: Preço unitário | K62: PEE | L62: Terceiros | M62: Consumidor | N62: Total
B63: 1 | C63: Diagnóstico Energético - Rateio | K63: =Terceiros!K17 -> 0 | L63: =Terceiros!L17 -> 0 | M63: =Terceiros!M17 -> 0 | N63: =Terceiros!N17 -> 0
B64: 2 | C64: Gerenciamento do Projeto - Rateio | K64: =Terceiros!K28 -> 0 | L64: =Terceiros!L28 -> 0 | M64: =Terceiros!M28 -> 0 | N64: =Terceiros!N28 -> 0
B65: 3 | C65: Relatório Final - Rateio | K65: =Terceiros!K39 -> 0 | L65: =Terceiros!L39 -> 0 | M65: =Terceiros!M39 -> 0 | N65: =Terceiros!N39 -> 0
B66: 4 | K66: =N66-L66-M66 -> 0 | N66: =I66*J66 -> 0
B67: 5 | K67: =N67-L67-M67 -> 0 | N67: =I67*J67 -> 0
B68: 6 | K68: =N68-L68-M68 -> 0 | N68: =I68*J68 -> 0
B69: 7 | K69: =N69-L69-M69 -> 0 | N69: =I69*J69 -> 0
B70: 8 | K70: =N70-L70-M70 -> 0 | N70: =I70*J70 -> 0
B71: 9 | K71: =N71-L71-M71 -> 0 | N71: =I71*J71 -> 0
B72: 10 | K72: =N72-L72-M72 -> 0 | N72: =I72*J72 -> 0
B73: 11 | K73: =N73-L73-M73 -> 0 | N73: =I73*J73 -> 0
B74: 12 | K74: =N74-L74-M74 -> 0 | N74: =I74*J74 -> 0
B75: 13 | K75: =N75-L75-M75 -> 0 | N75: =I75*J75 -> 0
B76: 14 | K76: =N76-L76-M76 -> 0 | N76: =I76*J76 -> 0
B77: 15 | K77: =N77-L77-M77 -> 0 | N77: =I77*J77 -> 0
... B82: 20 | K82: =N82-L82-M82 -> 0 | N82: =I82*J82 -> 0
C83: Mão de obra de terceiros | K83: =SUM(K63:K82) -> 0 | L83: =SUM(L63:L82) -> 0 | M83: =SUM(M63:M82) -> 0 | N83: =SUM(N63:N82) -> 0
C84: Administração Própria - CEMIG | K84: =Apoio!BE7 -> 0 | N84: =K84 -> 0
J85: Sub total - Mão de obra de terceiros e Administração Própria CEMIG | K85: =SUM(K60,K61,K83,K84) -> 0 | L85: =L83 -> 0 | M85: =M83 -> 0 | N85: =SUM(N60,N61,N83,N84) -> 0
J86: Sub total - Custos diretos | K86: =SUM(K58,K85) -> 0 | L86: =SUM(L58,L85) -> 0 | M86: =SUM(M58,M85) -> 0 | N86: =SUM(N58,N85) -> 0
B87: CUSTOS INDIRETOS
B88: CUSTOS INDIRETOS | K88: ORIGEM DOS RECURSOS
C89: Marketing | K89: =Marketing!K33 -> 0 | L89: =Marketing!L33 -> 0 | M89: =Marketing!M33 -> 0 | N89: =Marketing!N33 -> 0
C90: Treinamento e capacitação | K90: =Treinamento!K33 -> 0 | L90: =Treinamento!L33 -> 0 | M90: =Treinamento!M33 -> 0 | N90: =Treinamento!N33 -> 0
B91: Descarte de materiais | I91: Quantidade | J91: Preço unitário | K91: PEE | L91: Terceiros | M91: Consumidor | N91: Total
B92: 1 | K92: =N92-L92-M92 -> 0 | N92: =I92*J92 -> 0
B93: 2 | K93: =N93-L93-M93 -> 0 | N93: =I93*J93 -> 0
B94: 3 | K94: =N94-L94-M94 -> 0 | N94: =I94*J94 -> 0
B95: 4 | K95: =N95-L95-M95 -> 0 | N95: =I95*J95 -> 0
B96: 5 | K96: =N96-L96-M96 -> 0 | N96: =I96*J96 -> 0
B97: 6 | K97: =N97-L97-M97 -> 0 | N97: =I97*J97 -> 0
B98: 7 | K98: =N98-L98-M98 -> 0 | N98: =I98*J98 -> 0
B99: 8 | K99: =N99-L99-M99 -> 0 | N99: =I99*J99 -> 0
B100: 9 | K100: =N100-L100-M100 -> 0 | N100: =I100*J100 -> 0
B101: 10 | K101: =N101-L101-M101 -> 0 | N101: =I101*J101 -> 0
B102: 11 | K102: =N102-L102-M102 -> 0 | N102: =I102*J102 -> 0
B103: 12 | K103: =N103-L103-M103 -> 0 | N103: =I103*J103 -> 0
... B111: 20 | K111: =N111-L111-M111 -> 0 | N111: =I111*J111 -> 0
C112: Descarte de materiais | K112: =SUM(K92:K111) -> 0 | L112: =SUM(L92:L111) -> 0 | M112: =SUM(M92:M111) -> 0 | N112: =SUM(N92:N111) -> 0
C113: Medição e verificação | K113: ='M&V'!J56 -> 0 | L113: ='M&V'!K56 -> 0 | M113: ='M&V'!L56 -> 0 | N113: ='M&V'!M56 -> 0
J114: Sub total - Custos indiretos | K114: =SUM(K89,K90,K112,K113) -> 0 | L114: =SUM(L89,L90,L112,L113) -> 0 | M114: =SUM(M89,M90,M112,M113) -> 0 | N114: =SUM(N89,N90,N112,N113) -> 0
J115: Custos Totais - Sistemas de Refrigeração | K115: =SUM(K86,K114) -> 0 | L115: =SUM(L86,L114) -> 0 | M115: =SUM(M86,M114) -> 0 | N115: =SUM(N86,N114) -> 0

Sheet RefrigBenef
C2: Definição de | D2: SIST. REF.:
B4: SISTEMAS DE REFRIGERAÇÃO - SISTEMA ATUAL
B5: 0 | G5: TOTAL | H5: refrig 1 | I5: refrig 2 | J5: refrig 3 | K5: refrig 4 | L5: refrig 5 | M5: refrig 6 | N5: refrig 7 | O5: refrig 8 | P5: refrig 9 | Q5: refrig 10 | R5: refrig 11 | S5: refrig 12 | T5: refrig 13 | U5: refrig 14 | V5: refrig 15 | W5: refrig 16 | X5: refrig 17 | Y5: refrig 18 | Z5: refrig 19 | AA5: refrig 20 | AB5: refrig 21 | AC5: refrig 22 | AD5: refrig 23 | AE5: refrig 24 | AF5: refrig 25 | AG5: refrig 26 | AH5: refrig 27 | AI5: refrig 28 | AJ5: refrig 29 | AK5: refrig 30 | AL5: refrig 31 | AM5: refrig 32 | AN5: refrig 33 | AO5: refrig 34 | AP5: refrig 35 | AQ5: refrig 36 | AR5: refrig 37 | AS5: refrig 38 | AT5: refrig 39 | AU5: refrig 40 | AV5: refrig 41 | AW5: refrig 42 | AX5: refrig 43 | AY5: refrig 44 | AZ5: refrig 45 | BA5: refrig 46 | BB5: refrig 47 | BC5: refrig 48 | BD5: refrig 49 | BE5: refrig 50 | BF5: refrig 51 | BG5: refrig 52 | BH5: refrig 53 | BI5: refrig 54 | BJ5: refrig 55 | BK5: refrig 56 | BL5: refrig 57 | BM5: refrig 58 | BN5: refrig 59 | BO5: refrig 60 | BP5: refrig 61 | BQ5: refrig 62 | BR5: refrig 63 | BS5: refrig 64 | BT5: refrig 65 | BU5: refrig 66 | BV5: refrig 67 | BW5: refrig 68 | BX5: refrig 69 | BY5: refrig 70 | BZ5: refrig 71 | CA5: refrig 72 | CB5: refrig 73 | CC5: refrig 74 | CD5: refrig 75 | CE5: refrig 76 | CF5: refrig 77 | CG5: refrig 78 | CH5: refrig 79 | CI5: refrig 80 | CJ5: refrig 81 | CK5: refrig 82 | CL5: refrig 83 | CM5: refrig 84 | CN5: refrig 85 | CO5: refrig 86 | CP5: refrig 87 | CQ5: refrig 88 | CR5: refrig 89 | CS5: refrig 90 | CT5: refrig 91 | CU5: refrig 92 | CV5: refrig 93 | CW5: refrig 94 | CX5: refrig 95 | CY5: refrig 96 | CZ5: refrig 97 | DA5: refrig 98 | DB5: refrig 99 | DC5: refrig 100 | DD5: refrig 101 | DE5: refrig 102 | DF5: refrig 103 | DG5: refrig 104 | DH5: refrig 105 | DI5: refrig 106 | DJ5: refrig 107 | DK5: refrig 108 | DL5: refrig 109 | DM5: refrig 110 | DN5: refrig 111 | DO5: refrig 112 | DP5: refrig 113 | DQ5: refrig 114 | DR5: refrig 115 | DS5: refrig 116 | DT5: refrig 117 | DU5: refrig 118 | DV5: refrig 119 | DW5: refrig 120 | DX5: refrig 121 | DY5: refrig 122 | DZ5: refrig 123 | EA5: refrig 124 | EB5: refrig 125 | EC5: refrig 126 | ED5: refrig 127 | EE5: refrig 128 | EF5: refrig 129 | EG5: refrig 130 | EH5: refrig 131 | EI5: refrig 132 | EJ5: refrig 133 | EK5: refrig 134 | EL5: refrig 135 | EM5: refrig 136 | EN5: refrig 137 | EO5: refrig 138 | EP5: refrig 139 | EQ5: refrig 140 | ER5: refrig 141 | ES5: refrig 142 | ET5: refrig 143 | EU5: refrig 144 | EV5: refrig 145 | EW5: refrig 146 | EX5: refrig 147 | EY5: refrig 148 | EZ5: refrig 149 | FA5: refrig 150
B6: 1 | C6: Unidade Consumidora
B7: 2 | C7: Tipo de equipamento / tecnologia
B8: =B7+1 -> 3 | C8: Potência nominal | E8: kW | F8: Pai | G8: =IF(COUNTA(H8:FA8)=0,"",IF(SMALL(H8:FA8,1)<0,"ERRO",""))
B9: =B8+1 -> 4 | C9: Fator de utilização | G9: =IF(COUNTA(H9:FA9)=0,"",IF(OR(SMALL(H9:FA9,1)<0,LARGE(H9:FA9,1)>1),"ERRO",""))
B10: =B9+1 -> 5 | C10: Consumo mensal | E10: kWh/mês | F10: Cai | G10: =IF(COUNTA(H10:FA10)=0,"",IF(SMALL(H10:FA10,1)<0,"ERRO",""))
B11: =B10+1 -> 6 | C11: Potência média utilizada | E11: kW | F11: Puai | G11: =SUM(H11:FA11) -> 0 | H11: =IF(H8>0,H8*H9,H10/730) -> 0 | I11: =IF(I8>0,I8*I9,I10/730) -> 0 | J11: =IF(J8>0,J8*J9,J10/730) -> 0 | K11: =IF(K8>0,K8*K9,K10/730) -> 0 | L11: =IF(L8>0,L8*L9,L10/730) -> 0 | M11: =IF(M8>0,M8*M9,M10/730) -> 0 | N11: =IF(N8>0,N8*N9,N10/730) -> 0 | O11: =IF(O8>0,O8*O9,O10/730) -> 0 | ... FA11: =IF(FA8>0,FA8*FA9,FA10/730) -> 0
B12: =B11+1 -> 7 | C12: Quantidade | F12: qai | G12: =IF(COUNTA(H12:FA12)=0,"",IF(SMALL(H12:FA12,1)<0,"ERRO",SUM(H12:FA12)))
B13: =B12+1 -> 8 | C13: Tempo de utilização do sistema, em um dia | E13: h/dia | G13: =IF(COUNTA(H13:FA13)=0,"",IF(OR(LARGE(H13:FA13,1)>24,SMALL(H13:FA13,1)<0),"ERRO",""))
C14: Dias de utilização do sistema, em um ano | E14: dia/ano | G14: =IF(COUNTA(H14:FA14)=0,"",IF(OR(LARGE(H14:FA14,1)>365,SMALL(H14:FA14,1)<0),"ERRO",""))
C15: Funcionamento | E15: h/ano | F15: hai | G15: =IF(COUNTA(H15:FA15)=0,"",IF(OR(LARGE(H15:FA15,1)>8760,SMALL(H15:FA15,1)<0),"ERRO","")) | H15: =H13*H14 -> 0 | I15: =I13*I14 -> 0 | J15: =J13*J14 -> 0 | K15: =K13*K14 -> 0 | L15: =L13*L14 -> 0 | M15: =M13*M14 -> 0 | N15: =N13*N14 -> 0 | O15: =O13*O14 -> 0 | ... FA15: =FA13*FA14 -> 0
B16: =B13+1 -> 9 | C16: Horas de utilização em horário de ponta, em um dia | E16: h/dia | F16: nupai | G16: =IF(COUNTA(H16:FA16)=0,"",IF(OR(LARGE(H16:FA16,1)>3,SMALL(H16:FA16,1)<0),"ERRO",""))
C17: Dias úteis de utilização em horário de ponta, em um mês | E17: dia/mês | F17: ndai | G17: =IF(COUNTA(H17:FA17)=0,"",IF(OR(LARGE(H17:FA17,1)>22,SMALL(H17:FA17,1)<0),"ERRO",""))
C18: Meses de utilização em horário de ponta, em um ano | E18: mês/ano | F18: nmai | G18: =IF(COUNTA(H18:FA18)=0,"",IF(OR(LARGE(H18:FA18,1)>12,SMALL(H18:FA18,1)<0),"ERRO",""))
C19: Fator de coincidência na ponta | F19: FCPai | G19: =IF(COUNTA(H19:FA19)=0,"",IF(OR(LARGE(H19:FA19,1)>1,SMALL(H19:FA19,1)<0),"ERRO","")) | H19: =H16*H17*H18/792 -> 0 | I19: =I16*I17*I18/792 -> 0 | J19: =J16*J17*J18/792 -> 0 | K19: =K16*K17*K18/792 -> 0 | L19: =L16*L17*L18/792 -> 0 | M19: =M16*M17*M18/792 -> 0 | N19: =N16*N17*N18/792 -> 0 | O19: =O16*O17*O18/792 -> 0 | ... FA19: =FA16*FA17*FA18/792 -> 0
B20: =B16+1 -> 10 | C20: Energia consumida | E20: MWh/ano | F20: Eai | G20: =SUM(H20:FA20) -> 0 | H20: =(H11*H12*H15)/1000 -> 0 | I20: =(I11*I12*I15)/1000 -> 0 | J20: =(J11*J12*J15)/1000 -> 0 | K20: =(K11*K12*K15)/1000 -> 0 | L20: =(L11*L12*L15)/1000 -> 0 | M20: =(M11*M12*M15)/1000 -> 0 | N20: =(N11*N12*N15)/1000 -> 0 | O20: =(O11*O12*O15)/1000 -> 0 | ... FA20: =(FA11*FA12*FA15)/1000 -> 0
B21: =B20+1 -> 11 | C21: Demanda média na ponta | E21: kW | F21: Dai | G21: =SUM(H21:FA21) -> 0 | H21: =H11*H12*H19 -> 0 | I21: =I11*I12*I19 -> 0 | J21: =J11*J12*J19 -> 0 | K21: =K11*K12*K19 -> 0 | L21: =L11*L12*L19 -> 0 | M21: =M11*M12*M19 -> 0 | N21: =N11*N12*N19 -> 0 | O21: =O11*O12*O19 -> 0 | ... FA21: =FA11*FA12*FA19 -> 0
B23: SISTEMAS DE REFRIGERAÇÃO - SISTEMA PROPOSTO
G24: TOTAL | H24: refrig 1 | I24: refrig 2 | J24: refrig 3 | K24: refrig 4 | L24: refrig 5 | M24: refrig 6 | N24: refrig 7 | O24: refrig 8 | P24: refrig 9 | Q24: refrig 10 | R24: refrig 11 | S24: refrig 12 | T24: refrig 13 | U24: refrig 14 | V24: refrig 15 | W24: refrig 16 | X24: refrig 17 | Y24: refrig 18 | Z24: refrig 19 | AA24: refrig 20 | AB24: refrig 21 | AC24: refrig 22 | AD24: refrig 23 | AE24: refrig 24 | AF24: refrig 25 | AG24: refrig 26 | AH24: refrig 27 | AI24: refrig 28 | AJ24: refrig 29 | AK24: refrig 30 | AL24: refrig 31 | AM24: refrig 32 | AN24: refrig 33 | AO24: refrig 34 | AP24: refrig 35 | AQ24: refrig 36 | AR24: refrig 37 | AS24: refrig 38 | AT24: refrig 39 | AU24: refrig 40 | AV24: refrig 41 | AW24: refrig 42 | AX24: refrig 43 | AY24: refrig 44 | AZ24: refrig 45 | BA24: refrig 46 | BB24: refrig 47 | BC24: refrig 48 | BD24: refrig 49 | BE24: refrig 50 | BF24: refrig 51 | BG24: refrig 52 | BH24: refrig 53 | BI24: refrig 54 | BJ24: refrig 55 | BK24: refrig 56 | BL24: refrig 57 | BM24: refrig 58 | BN24: refrig 59 | BO24: refrig 60 | BP24: refrig 61 | BQ24: refrig 62 | BR24: refrig 63 | BS24: refrig 64 | BT24: refrig 65 | BU24: refrig 66 | BV24: refrig 67 | BW24: refrig 68 | BX24: refrig 69 | BY24: refrig 70 | BZ24: refrig 71 | CA24: refrig 72 | CB24: refrig 73 | CC24: refrig 74 | CD24: refrig 75 | CE24: refrig 76 | CF24: refrig 77 | CG24: refrig 78 | CH24: refrig 79 | CI24: refrig 80 | CJ24: refrig 81 | CK24: refrig 82 | CL24: refrig 83 | CM24: refrig 84 | CN24: refrig 85 | CO24: refrig 86 | CP24: refrig 87 | CQ24: refrig 88 | CR24: refrig 89 | CS24: refrig 90 | CT24: refrig 91 | CU24: refrig 92 | CV24: refrig 93 | CW24: refrig 94 | CX24: refrig 95 | CY24: refrig 96 | CZ24: refrig 97 | DA24: refrig 98 | DB24: refrig 99 | DC24: refrig 100 | DD24: refrig 101 | DE24: refrig 102 | DF24: refrig 103 | DG24: refrig 104 | DH24: refrig 105 | DI24: refrig 106 | DJ24: refrig 107 | DK24: refrig 108 | DL24: refrig 109 | DM24: refrig 110 | DN24: refrig 111 | DO24: refrig 112 | DP24: refrig 113 | DQ24: refrig 114 | DR24: refrig 115 | DS24: refrig 116 | DT24: refrig 117 | DU24: refrig 118 | DV24: refrig 119 | DW24: refrig 120 | DX24: refrig 121 | DY24: refrig 122 | DZ24: refrig 123 | EA24: refrig 124 | EB24: refrig 125 | EC24: refrig 126 | ED24: refrig 127 | EE24: refrig 128 | EF24: refrig 129 | EG24: refrig 130 | EH24: refrig 131 | EI24: refrig 132 | EJ24: refrig 133 | EK24: refrig 134 | EL24: refrig 135 | EM24: refrig 136 | EN24: refrig 137 | EO24: refrig 138 | EP24: refrig 139 | EQ24: refrig 140 | ER24: refrig 141 | ES24: refrig 142 | ET24: refrig 143 | EU24: refrig 144 | EV24: refrig 145 | EW24: refrig 146 | EX24: refrig 147 | EY24: refrig 148 | EZ24: refrig 149 | FA24: refrig 150
B25: =B21+1 -> 12 | C25: Unidade Consumidora | H25: =IF(H6="","",H6) | I25: =IF(I6="","",I6) | J25: =IF(J6="","",J6) | K25: =IF(K6="","",K6) | L25: =IF(L6="","",L6) | M25: =IF(M6="","",M6) | N25: =IF(N6="","",N6) | O25: =IF(O6="","",O6) | ... FA25: =IF(FA6="","",FA6)
B26: =B25+1 -> 13 | C26: Tipo de equipamento / tecnologia
B27: =B26+1 -> 14 | C27: Potência nominal | E27: kW | F27: Pai | G27: =IF(COUNTA(H27:FA27)=0,"",IF(SMALL(H27:FA27,1)<0,"ERRO",""))
B28: =B27+1 -> 15 | C28: Fator de utilização | G28: =IF(COUNTA(H28:FA28)=0,"",IF(OR(SMALL(H28:FA28,1)<0,LARGE(H28:FA28,1)>1),"ERRO",""))
B29: =B28+1 -> 16 | C29: Consumo mensal | E29: kWh/mês | F29: Cpi | G29: =IF(COUNTA(H29:FA29)=0,"",IF(SMALL(H29:FA29,1)<0,"ERRO",""))
B30: =B29+1 -> 17 | C30: Potência média utilizada | E30: W | F30: Pupi | G30: =SUM(H30:FA30) -> 0 | H30: =IF(H27>0,H27*H28,H29/730) -> 0 | I30: =IF(I27>0,I27*I28,I29/730) -> 0 | J30: =IF(J27>0,J27*J28,J29/730) -> 0 | K30: =IF(K27>0,K27*K28,K29/730) -> 0 | L30: =IF(L27>0,L27*L28,L29/730) -> 0 | M30: =IF(M27>0,M27*M28,M29/730) -> 0 | N30: =IF(N27>0,N27*N28,N29/730) -> 0 | O30: =IF(O27>0,O27*O28,O29/730) -> 0 | ... FA30: =IF(FA27>0,FA27*FA28,FA29/730) -> 0
B31: =B30+1 -> 18 | C31: Quantidade | F31: qpi | G31: =IF(COUNTA(H31:FA31)=0,"",IF(SMALL(H31:FA31,1)<0,"ERRO",SUM(H31:FA31)))
B32: =B31+1 -> 19 | C32: Tempo de utilização do sistema, em um dia | E32: h/dia | G32: =IF(COUNTA(H32:FA32)=0,"",IF(OR(LARGE(H32:FA32,1)>24,SMALL(H32:FA32,1)<0),"ERRO",""))
C33: Dias de utilização do sistema, em um ano | E33: dia/ano | G33: =IF(COUNTA(H33:FA33)=0,"",IF(OR(LARGE(H33:FA33,1)>365,SMALL(H33:FA33,1)<0),"ERRO",""))
C34: Funcionamento | E34: h/ano | F34: hpi | G34: =IF(COUNTA(H34:FA34)=0,"",IF(OR(LARGE(H34:FA34,1)>8760,SMALL(H34:FA34,1)<0),"ERRO","")) | H34: =H32*H33 -> 0 | I34: =I32*I33 -> 0 | J34: =J32*J33 -> 0 | K34: =K32*K33 -> 0 | L34: =L32*L33 -> 0 | M34: =M32*M33 -> 0 | N34: =N32*N33 -> 0 | O34: =O32*O33 -> 0 | ... FA34: =FA32*FA33 -> 0
B35: =B32+1 -> 20 | C35: Horas de utilização em horário de ponta, em um dia | E35: h/dia | F35: nuppi | G35: =IF(COUNTA(H35:FA35)=0,"",IF(OR(LARGE(H35:FA35,1)>3,SMALL(H35:FA35,1)<0),"ERRO",""))
C36: Dias úteis de utilização em horário de ponta, em um mês | E36: dia/mês | F36: ndpi | G36: =IF(COUNTA(H36:FA36)=0,"",IF(OR(LARGE(H36:FA36,1)>22,SMALL(H36:FA36,1)<0),"ERRO",""))
C37: Meses de utilização em horário de ponta, em um ano | E37: mês/ano | F37: nmpi | G37: =IF(COUNTA(H37:FA37)=0,"",IF(OR(LARGE(H37:FA37,1)>12,SMALL(H37:FA37,1)<0),"ERRO",""))
C38: Fator de coincidência na ponta | F38: FCPpi | G38: =IF(COUNTA(H38:FA38)=0,"",IF(OR(LARGE(H38:FA38,1)>1,SMALL(H38:FA38,1)<0),"ERRO","")) | H38: =H35*H36*H37/792 -> 0 | I38: =I35*I36*I37/792 -> 0 | J38: =J35*J36*J37/792 -> 0 | K38: =K35*K36*K37/792 -> 0 | L38: =L35*L36*L37/792 -> 0 | M38: =M35*M36*M37/792 -> 0 | N38: =N35*N36*N37/792 -> 0 | O38: =O35*O36*O37/792 -> 0 | ... FA38: =FA35*FA36*FA37/792 -> 0
B39: =B35+1 -> 21 | C39: Energia consumida | E39: MWh/ano | F39: Epi | G39: =SUM(H39:FA39) -> 0 | H39: =(H30*H31*H34)/1000 -> 0 | I39: =(I30*I31*I34)/1000 -> 0 | J39: =(J30*J31*J34)/1000 -> 0 | K39: =(K30*K31*K34)/1000 -> 0 | L39: =(L30*L31*L34)/1000 -> 0 | M39: =(M30*M31*M34)/1000 -> 0 | N39: =(N30*N31*N34)/1000 -> 0 | O39: =(O30*O31*O34)/1000 -> 0 | ... FA39: =(FA30*FA31*FA34)/1000 -> 0
B40: =B39+1 -> 22 | C40: Demanda média na ponta | E40: kW | F40: Dpi | G40: =SUM(H40:FA40) -> 0 | H40: =H30*H31*H38 -> 0 | I40: =I30*I31*I38 -> 0 | J40: =J30*J31*J38 -> 0 | K40: =K30*K31*K38 -> 0 | L40: =L30*L31*L38 -> 0 | M40: =M30*M31*M38 -> 0 | N40: =N30*N31*N38 -> 0 | O40: =O30*O31*O38 -> 0 | ... FA40: =FA30*FA31*FA38 -> 0
B42: SISTEMAS DE REFRIGERAÇÃO - RESULTADOS ESPERADOS
G43: TOTAL | H43: refrig 1 | I43: refrig 2 | J43: refrig 3 | K43: refrig 4 | L43: refrig 5 | M43: refrig 6 | N43: refrig 7 | O43: refrig 8 | P43: refrig 9 | Q43: refrig 10 | R43: refrig 11 | S43: refrig 12 | T43: refrig 13 | U43: refrig 14 | V43: refrig 15 | W43: refrig 16 | X43: refrig 17 | Y43: refrig 18 | Z43: refrig 19 | AA43: refrig 20 | AB43: refrig 21 | AC43: refrig 22 | AD43: refrig 23 | AE43: refrig 24 | AF43: refrig 25 | AG43: refrig 26 | AH43: refrig 27 | AI43: refrig 28 | AJ43: refrig 29 | AK43: refrig 30 | AL43: refrig 31 | AM43: refrig 32 | AN43: refrig 33 | AO43: refrig 34 | AP43: refrig 35 | AQ43: refrig 36 | AR43: refrig 37 | AS43: refrig 38 | AT43: refrig 39 | AU43: refrig 40 | AV43: refrig 41 | AW43: refrig 42 | AX43: refrig 43 | AY43: refrig 44 | AZ43: refrig 45 | BA43: refrig 46 | BB43: refrig 47 | BC43: refrig 48 | BD43: refrig 49 | BE43: refrig 50 | BF43: refrig 51 | BG43: refrig 52 | BH43: refrig 53 | BI43: refrig 54 | BJ43: refrig 55 | BK43: refrig 56 | BL43: refrig 57 | BM43: refrig 58 | BN43: refrig 59 | BO43: refrig 60 | BP43: refrig 61 | BQ43: refrig 62 | BR43: refrig 63 | BS43: refrig 64 | BT43: refrig 65 | BU43: refrig 66 | BV43: refrig 67 | BW43: refrig 68 | BX43: refrig 69 | BY43: refrig 70 | BZ43: refrig 71 | CA43: refrig 72 | CB43: refrig 73 | CC43: refrig 74 | CD43: refrig 75 | CE43: refrig 76 | CF43: refrig 77 | CG43: refrig 78 | CH43: refrig 79 | CI43: refrig 80 | CJ43: refrig 81 | CK43: refrig 82 | CL43: refrig 83 | CM43: refrig 84 | CN43: refrig 85 | CO43: refrig 86 | CP43: refrig 87 | CQ43: refrig 88 | CR43: refrig 89 | CS43: refrig 90 | CT43: refrig 91 | CU43: refrig 92 | CV43: refrig 93 | CW43: refrig 94 | CX43: refrig 95 | CY43: refrig 96 | CZ43: refrig 97 | DA43: refrig 98 | DB43: refrig 99 | DC43: refrig 100 | DD43: refrig 101 | DE43: refrig 102 | DF43: refrig 103 | DG43: refrig 104 | DH43: refrig 105 | DI43: refrig 106 | DJ43: refrig 107 | DK43: refrig 108 | DL43: refrig 109 | DM43: refrig 110 | DN43: refrig 111 | DO43: refrig 112 | DP43: refrig 113 | DQ43: refrig 114 | DR43: refrig 115 | DS43: refrig 116 | DT43: refrig 117 | DU43: refrig 118 | DV43: refrig 119 | DW43: refrig 120 | DX43: refrig 121 | DY43: refrig 122 | DZ43: refrig 123 | EA43: refrig 124 | EB43: refrig 125 | EC43: refrig 126 | ED43: refrig 127 | EE43: refrig 128 | EF43: refrig 129 | EG43: refrig 130 | EH43: refrig 131 | EI43: refrig 132 | EJ43: refrig 133 | EK43: refrig 134 | EL43: refrig 135 | EM43: refrig 136 | EN43: refrig 137 | EO43: refrig 138 | EP43: refrig 139 | EQ43: refrig 140 | ER43: refrig 141 | ES43: refrig 142 | ET43: refrig 143 | EU43: refrig 144 | EV43: refrig 145 | EW43: refrig 146 | EX43: refrig 147 | EY43: refrig 148 | EZ43: refrig 149 | FA43: refrig 150
B44: =B40+1 -> 23 | C44: Redução de demanda na ponta | E44: kW | F44: RDPi | G44: =SUM(H44:FA44) -> 0 | H44: =H21-H40 -> 0 | I44: =I21-I40 -> 0 | J44: =J21-J40 -> 0 | K44: =K21-K40 -> 0 | L44: =L21-L40 -> 0 | M44: =M21-M40 -> 0 | N44: =N21-N40 -> 0 | O44: =O21-O40 -> 0 | ... FA44: =FA21-FA40 -> 0
B45: =B44+1 -> 24 | C45: Custo evitado de demanda (CED) = | D45: =Projeto!$L$44 -> 0 | E45: % | F45: RDPi% | G45: =IF(G21=0,0,G44/G21) -> 0 | H45: =IF(H21=0,0,H44/H21) -> 0 | I45: =IF(I21=0,0,I44/I21) -> 0 | J45: =IF(J21=0,0,J44/J21) -> 0 | K45: =IF(K21=0,0,K44/K21) -> 0 | L45: =IF(L21=0,0,L44/L21) -> 0 | M45: =IF(M21=0,0,M44/M21) -> 0 | N45: =IF(N21=0,0,N44/N21) -> 0 | ... FA45: =IF(FA21=0,0,FA44/FA21) -> 0
B46: =B45+1 -> 25 | C46: Energia economizada | E46: MWh/ano | F46: EEi | G46: =SUM(H46:FA46) -> 0 | H46: =H20-H39 -> 0 | I46: =I20-I39 -> 0 | J46: =J20-J39 -> 0 | K46: =K20-K39 -> 0 | L46: =L20-L39 -> 0 | M46: =M20-M39 -> 0 | N46: =N20-N39 -> 0 | O46: =O20-O39 -> 0 | ... FA46: =FA20-FA39 -> 0
B47: =B46+1 -> 26 | C47: Custo da energia evitada (CEE) = | D47: =Projeto!$L$43 -> 0 | E47: % | F47: EEi% | G47: =IF(G20=0,0,G46/G20) -> 0 | H47: =IF(H20=0,0,H46/H20) -> 0 | I47: =IF(I20=0,0,I46/I20) -> 0 | J47: =IF(J20=0,0,J46/J20) -> 0 | K47: =IF(K20=0,0,K46/K20) -> 0 | L47: =IF(L20=0,0,L46/L20) -> 0 | M47: =IF(M20=0,0,M46/M20) -> 0 | N47: =IF(N20=0,0,N46/N20) -> 0 | ... FA47: =IF(FA20=0,0,FA46/FA20) -> 0
C48: Benefício anualizado - Sistemas de Refrigeração | E48: R$ | F48: BREFRIG | G48: =SUM(H48:FA48) -> 0 | H48: =H44*$D$45+H46*$D$47 -> 0 | I48: =I44*$D$45+I46*$D$47 -> 0 | J48: =J44*$D$45+J46*$D$47 -> 0 | K48: =K44*$D$45+K46*$D$47 -> 0 | L48: =L44*$D$45+L46*$D$47 -> 0 | M48: =M44*$D$45+M46*$D$47 -> 0 | N48: =N44*$D$45+N46*$D$47 -> 0 | O48: =O44*$D$45+O46*$D$47 -> 0 | ... FA48: =FA44*$D$45+FA46*$D$47 -> 0
F50: RCBREFRIG_PEE | G50: =RCB!$G$12 -> 0
F51: RCBPEE | G51: =RCB!$H$9 -> 0

Sheet HospCusto
B4: EQUIPAMENTOS HOSPITALARES | P4: =B4 -> EQUIPAMENTOS HOSPITALARES
B5: CUSTOS DIRETOS | P5: CUSTOS ANUALIZADOS
B6: MATERIAIS E EQUIPAMENTOS | K6: ORIGEM DOS RECURSOS | P6: MATERIAIS E EQUIPAMENTOS | X6: ORIGEM DOS RECURSOS
B7: Materiais e equipamentos | H7: Vida útil (anos) | I7: Quantidade | J7: Preço unitário | K7: PEE | L7: Terceiros | M7: Consumidor | N7: Total | P7: =B7 -> Materiais e equipamentos | V7: Vida útil | W7: FRC | X7: CAPEE | Y7: CATOTAL
B8: 1 | K8: =N8-L8-M8 -> 0 | N8: =I8*J8 -> 0 | P8: =B8 -> 1 | Q8: =IF(OR(C8=0,C8=""),"",C8) | V8: =IF(N8=0,"",H8) | W8: =IF(OR(V8="",V8=0),0,(Projeto!$AD$10*((1+Projeto!$AD$10)^V8))/(((1+Projeto!$AD$10)^V8)-1)) -> 0 | X8: =IF(AND(K8>0,CustoContábil!$F$6>0),K8*(CustoContábil!$F$18/CustoContábil!$F$6)*W8,0) -> 0 | Y8: =IF(AND(N8>0,CustoContábil!$D$6>0),N8*(CustoContábil!$D$18/CustoContábil!$D$6)*W8,0) -> 0
B9: 2 | K9: =N9-L9-M9 -> 0 | N9: =I9*J9 -> 0 | P9: =B9 -> 2 | Q9: =IF(OR(C9=0,C9=""),"",C9) | V9: =IF(N9=0,"",H9) | W9: =IF(OR(V9="",V9=0),0,(Projeto!$AD$10*((1+Projeto!$AD$10)^V9))/(((1+Projeto!$AD$10)^V9)-1)) -> 0 | X9: =IF(AND(K9>0,CustoContábil!$F$6>0),K9*(CustoContábil!$F$18/CustoContábil!$F$6)*W9,0) -> 0 | Y9: =IF(AND(N9>0,CustoContábil!$D$6>0),N9*(CustoContábil!$D$18/CustoContábil!$D$6)*W9,0) -> 0
B10: 3 | K10: =N10-L10-M10 -> 0 | N10: =I10*J10 -> 0 | P10: =B10 -> 3 | Q10: =IF(OR(C10=0,C10=""),"",C10) | V10: =IF(N10=0,"",H10) | W10: =IF(OR(V10="",V10=0),0,(Projeto!$AD$10*((1+Projeto!$AD$10)^V10))/(((1+Projeto!$AD$10)^V10)-1)) -> 0 | X10: =IF(AND(K10>0,CustoContábil!$F$6>0),K10*(CustoContábil!$F$18/CustoContábil!$F$6)*W10,0) -> 0 | Y10: =IF(AND(N10>0,CustoContábil!$D$6>0),N10*(CustoContábil!$D$18/CustoContábil!$D$6)*W10,0) -> 0
B11: 4 | K11: =N11-L11-M11 -> 0 | N11: =I11*J11 -> 0 | P11: =B11 -> 4 | Q11: =IF(OR(C11=0,C11=""),"",C11) | V11: =IF(N11=0,"",H11) | W11: =IF(OR(V11="",V11=0),0,(Projeto!$AD$10*((1+Projeto!$AD$10)^V11))/(((1+Projeto!$AD$10)^V11)-1)) -> 0 | X11: =IF(AND(K11>0,CustoContábil!$F$6>0),K11*(CustoContábil!$F$18/CustoContábil!$F$6)*W11,0) -> 0 | Y11: =IF(AND(N11>0,CustoContábil!$D$6>0),N11*(CustoContábil!$D$18/CustoContábil!$D$6)*W11,0) -> 0
B12: 5 | K12: =N12-L12-M12 -> 0 | N12: =I12*J12 -> 0 | P12: =B12 -> 5 | Q12: =IF(OR(C12=0,C12=""),"",C12) | V12: =IF(N12=0,"",H12) | W12: =IF(OR(V12="",V12=0),0,(Projeto!$AD$10*((1+Projeto!$AD$10)^V12))/(((1+Projeto!$AD$10)^V12)-1)) -> 0 | X12: =IF(AND(K12>0,CustoContábil!$F$6>0),K12*(CustoContábil!$F$18/CustoContábil!$F$6)*W12,0) -> 0 | Y12: =IF(AND(N12>0,CustoContábil!$D$6>0),N12*(CustoContábil!$D$18/CustoContábil!$D$6)*W12,0) -> 0
B13: 6 | K13: =N13-L13-M13 -> 0 | N13: =I13*J13 -> 0 | P13: =B13 -> 6 | Q13: =IF(OR(C13=0,C13=""),"",C13) | V13: =IF(N13=0,"",H13) | W13: =IF(OR(V13="",V13=0),0,(Projeto!$AD$10*((1+Projeto!$AD$10)^V13))/(((1+Projeto!$AD$10)^V13)-1)) -> 0 | X13: =IF(AND(K13>0,CustoContábil!$F$6>0),K13*(CustoContábil!$F$18/CustoContábil!$F$6)*W13,0) -> 0 | Y13: =IF(AND(N13>0,CustoContábil!$D$6>0),N13*(CustoContábil!$D$18/CustoContábil!$D$6)*W13,0) -> 0
B14: 7 | K14: =N14-L14-M14 -> 0 | N14: =I14*J14 -> 0 | P14: =B14 -> 7 | Q14: =IF(OR(C14=0,C14=""),"",C14) | V14: =IF(N14=0,"",H14) | W14: =IF(OR(V14="",V14=0),0,(Projeto!$AD$10*((1+Projeto!$AD$10)^V14))/(((1+Projeto!$AD$10)^V14)-1)) -> 0 | X14: =IF(AND(K14>0,CustoContábil!$F$6>0),K14*(CustoContábil!$F$18/CustoContábil!$F$6)*W14,0) -> 0 | Y14: =IF(AND(N14>0,CustoContábil!$D$6>0),N14*(CustoContábil!$D$18/CustoContábil!$D$6)*W14,0) -> 0
B15: 8 | K15: =N15-L15-M15 -> 0 | N15: =I15*J15 -> 0 | P15: =B15 -> 8 | Q15: =IF(OR(C15=0,C15=""),"",C15) | V15: =IF(N15=0,"",H15) | W15: =IF(OR(V15="",V15=0),0,(Projeto!$AD$10*((1+Projeto!$AD$10)^V15))/(((1+Projeto!$AD$10)^V15)-1)) -> 0 | X15: =IF(AND(K15>0,CustoContábil!$F$6>0),K15*(CustoContábil!$F$18/CustoContábil!$F$6)*W15,0) -> 0 | Y15: =IF(AND(N15>0,CustoContábil!$D$6>0),N15*(CustoContábil!$D$18/CustoContábil!$D$6)*W15,0) -> 0
B16: 9 | K16: =N16-L16-M16 -> 0 | N16: =I16*J16 -> 0 | P16: =B16 -> 9 | Q16: =IF(OR(C16=0,C16=""),"",C16) | V16: =IF(N16=0,"",H16) | W16: =IF(OR(V16="",V16=0),0,(Projeto!$AD$10*((1+Projeto!$AD$10)^V16))/(((1+Projeto!$AD$10)^V16)-1)) -> 0 | X16: =IF(AND(K16>0,CustoContábil!$F$6>0),K16*(CustoContábil!$F$18/CustoContábil!$F$6)*W16,0) -> 0 | Y16: =IF(AND(N16>0,CustoContábil!$D$6>0),N16*(CustoContábil!$D$18/CustoContábil!$D$6)*W16,0) -> 0
B17: 10 | K17: =N17-L17-M17 -> 0 | N17: =I17*J17 -> 0 | P17: =B17 -> 10 | Q17: =IF(OR(C17=0,C17=""),"",C17) | V17: =IF(N17=0,"",H17) | W17: =IF(OR(V17="",V17=0),0,(Projeto!$AD$10*((1+Projeto!$AD$10)^V17))/(((1+Projeto!$AD$10)^V17)-1)) -> 0 | X17: =IF(AND(K17>0,CustoContábil!$F$6>0),K17*(CustoContábil!$F$18/CustoContábil!$F$6)*W17,0) -> 0 | Y17: =IF(AND(N17>0,CustoContábil!$D$6>0),N17*(CustoContábil!$D$18/CustoContábil!$D$6)*W17,0) -> 0
B18: 11 | K18: =N18-L18-M18 -> 0 | N18: =I18*J18 -> 0 | P18: =B18 -> 11 | Q18: =IF(OR(C18=0,C18=""),"",C18) | V18: =IF(N18=0,"",H18) | W18: =IF(OR(V18="",V18=0),0,(Projeto!$AD$10*((1+Projeto!$AD$10)^V18))/(((1+Projeto!$AD$10)^V18)-1)) -> 0 | X18: =IF(AND(K18>0,CustoContábil!$F$6>0),K18*(CustoContábil!$F$18/CustoContábil!$F$6)*W18,0) -> 0 | Y18: =IF(AND(N18>0,CustoContábil!$D$6>0),N18*(CustoContábil!$D$18/CustoContábil!$D$6)*W18,0) -> 0
B19: 12 | K19: =N19-L19-M19 -> 0 | N19: =I19*J19 -> 0 | P19: =B19 -> 12 | Q19: =IF(OR(C19=0,C19=""),"",C19) | V19: =IF(N19=0,"",H19) | W19: =IF(OR(V19="",V19=0),0,(Projeto!$AD$10*((1+Projeto!$AD$10)^V19))/(((1+Projeto!$AD$10)^V19)-1)) -> 0 | X19: =IF(AND(K19>0,CustoContábil!$F$6>0),K19*(CustoContábil!$F$18/CustoContábil!$F$6)*W19,0) -> 0 | Y19: =IF(AND(N19>0,CustoContábil!$D$6>0),N19*(CustoContábil!$D$18/CustoContábil!$D$6)*W19,0) -> 0
... B57: 50 | K57: =N57-L57-M57 -> 0 | N57: =I57*J57 -> 0 | P57: =B57 -> 50 | Q57: =IF(OR(C57=0,C57=""),"",C57) | V57: =IF(N57=0,"",H57) | W57: =IF(OR(V57="",V57=0),0,(Projeto!$AD$10*((1+Projeto!$AD$10)^V57))/(((1+Projeto!$AD$10)^V57)-1)) -> 0 | X57: =IF(AND(K57>0,CustoContábil!$F$6>0),K57*(CustoContábil!$F$18/CustoContábil!$F$6)*W57,0) -> 0 | Y57: =IF(AND(N57>0,CustoContábil!$D$6>0),N57*(CustoContábil!$D$18/CustoContábil!$D$6)*W57,0) -> 0
